Workbook

Sheet Datos Preescolar
B1: Mes | C1: Día | D1: Estudiante | E1: Grado | F1: Como conoció el colegio | G1: Inicio proceso | H1: Observación | I1: Matrícula | J1: Estado del proceso | K1: Observaciones | L1: Días entre cita de info e inicio de observa | M1: Días entre inici de observa y matrícula | N1: Días entre cita de info y matrícula | O1: =AVERAGEIF(L2:L899,">0",L2:L899) -> 161.26087 | P1: =AVERAGEIF(M2:M899,">0",M2:M899) -> 42.611111 | Q1: =AVERAGEIF(N2:N899,">0",N2:N899) -> 195.16667 | S1: =AVERAGEIF(N2:N899,">0",L2:L899) -> 152.55556 | T1: =AVERAGEIF(N2:N899,">0",M2:M899) -> 42.611111
B2: Enero | C2: 44939 | D2: Alicia Barrientos | E2: Transición | G2: SI | H2: 44949 | I2: 44972 | L2: =IF(H2>0,H2-C2,0) -> 10 | M2: =IF(I2>0,I2-H2,0) -> 23 | N2: =IF(I2>0,I2-C2,0) -> 33
B3: Enero | C3: 44944 | D3: Antonia Tabares | E3: Prejardín | G3: NO | L3: =IF(H3>0,H3-C3,0) -> 0 | M3: =IF(I3>0,I3-H3,0) -> 0 | N3: =IF(I3>0,I3-C3,0) -> 0
B4: Enero | C4: 44944 | D4: Luna Waton Lu Jaramillo | E4: Prejardín | G4: NO | L4: =IF(H4>0,H4-C4,0) -> 0 | M4: =IF(I4>0,I4-H4,0) -> 0 | N4: =IF(I4>0,I4-C4,0) -> 0
B5: Enero | C5: 44944 | D5: Gabriela Díaz Arrieta | E5: Prejardín | G5: SI | H5: 45216 | I5: 45306 | L5: =IF(H5>0,H5-C5,0) -> 272 | M5: =IF(I5>0,I5-H5,0) -> 90 | N5: =IF(I5>0,I5-C5,0) -> 362
B6: Enero | C6: 44944 | D6: Elisa Delgado González | E6: Prejardín | G6: NO | L6: =IF(H6>0,H6-C6,0) -> 0 | M6: =IF(I6>0,I6-H6,0) -> 0 | N6: =IF(I6>0,I6-C6,0) -> 0
B7: Enero | C7: 44953 | D7: David Gabriel Peña Díaz | E7: Prejardín | G7: NO | L7: =IF(H7>0,H7-C7,0) -> 0 | M7: =IF(I7>0,I7-H7,0) -> 0 | N7: =IF(I7>0,I7-C7,0) -> 0
B8: Febrero | C8: 44958 | D8: Martina Páez Cano | E8: Prejardín | G8: NO | J8: Tenía cupo reservado y desitió | L8: =IF(H8>0,H8-C8,0) -> 0 | M8: =IF(I8>0,I8-H8,0) -> 0 | N8: =IF(I8>0,I8-C8,0) -> 0
B9: Febrero | C9: 44958 | D9: Lucio Arango Parra | E9: Prejardín | G9: NO | L9: =IF(H9>0,H9-C9,0) -> 0 | M9: =IF(I9>0,I9-H9,0) -> 0 | N9: =IF(I9>0,I9-C9,0) -> 0
B10: Febrero | C10: 44958 | D10: Amelia Gaitán | E10: Prejardín | G10: NO | L10: =IF(H10>0,H10-C10,0) -> 0 | M10: =IF(I10>0,I10-H10,0) -> 0 | N10: =IF(I10>0,I10-C10,0) -> 0
B11: Febrero | C11: 44968 | D11: Alicia Vasco García | E11: Transición | G11: SI | H11: 45222 | I11: 45306 | L11: =IF(H11>0,H11-C11,0) -> 254 | M11: =IF(I11>0,I11-H11,0) -> 84 | N11: =IF(I11>0,I11-C11,0) -> 338
B12: Febrero | C12: 44972 | D12: Guadalupe Pérez puerta | E12: Prejardín | G12: NO | L12: =IF(H12>0,H12-C12,0) -> 0 | M12: =IF(I12>0,I12-H12,0) -> 0 | N12: =IF(I12>0,I12-C12,0) -> 0
B13: Febrero | C13: 44972 | D13: Martín velasquez | E13: Jardín | G13: NO | L13: =IF(H13>0,H13-C13,0) -> 0 | M13: =IF(I13>0,I13-H13,0) -> 0 | N13: =IF(I13>0,I13-C13,0) -> 0
B14: Febrero | C14: 44972 | D14: Mayu Kiriki Ríos - Yudai Kiriki Ríos | E14: Transición | G14: NO | L14: =IF(H14>0,H14-C14,0) -> 0 | M14: =IF(I14>0,I14-H14,0) -> 0 | N14: =IF(I14>0,I14-C14,0) -> 0
B15: Marzo | C15: 45014 | D15: Agustín Hoyos Cruz | E15: Transición | G15: NO | L15: =IF(H15>0,H15-C15,0) -> 0 | M15: =IF(I15>0,I15-H15,0) -> 0 | N15: =IF(I15>0,I15-C15,0) -> 0
B16: Marzo | C16: 45014 | D16: Miguel Ángel Páez Montoya | E16: Transición | G16: NO | L16: =IF(H16>0,H16-C16,0) -> 0 | M16: =IF(I16>0,I16-H16,0) -> 0 | N16: =IF(I16>0,I16-C16,0) -> 0
B17: Marzo | C17: 45014 | D17: Juan Matías Fonseca | E17: Transición | G17: NO | L17: =IF(H17>0,H17-C17,0) -> 0 | M17: =IF(I17>0,I17-H17,0) -> 0 | N17: =IF(I17>0,I17-C17,0) -> 0
B18: Abril | C18: 45035 | D18: Matías Usma | E18: Jardín | G18: NO | L18: =IF(H18>0,H18-C18,0) -> 0 | M18: =IF(I18>0,I18-H18,0) -> 0 | N18: =IF(I18>0,I18-C18,0) -> 0
B19: Abril | C19: 45042 | D19: Luca Aristizábal Forero | E19: Prejardín | G19: NO | L19: =IF(H19>0,H19-C19,0) -> 0 | M19: =IF(I19>0,I19-H19,0) -> 0 | N19: =IF(I19>0,I19-C19,0) -> 0
B20: Abril | C20: 45042 | D20: Luiyi Fontalvo Gutiérrez | E20: Prejardín | G20: NO | L20: =IF(H20>0,H20-C20,0) -> 0 | M20: =IF(I20>0,I20-H20,0) -> 0 | N20: =IF(I20>0,I20-C20,0) -> 0
B21: Abril | C21: 45042 | D21: José Manuel Guzmán Barrera | E21: Prejardín | G21: NO | J21: Tenía cupo reservado y desitió | L21: =IF(H21>0,H21-C21,0) -> 0 | M21: =IF(I21>0,I21-H21,0) -> 0 | N21: =IF(I21>0,I21-C21,0) -> 0
B22: Abril | C22: 45043 | D22: Emilia Ocampo López | E22: Prejardín | G22: SI | H22: 45117 | I22: 45138 | L22: =IF(H22>0,H22-C22,0) -> 74 | M22: =IF(I22>0,I22-H22,0) -> 21 | N22: =IF(I22>0,I22-C22,0) -> 95
B23: Abril | C23: 45043 | D23: Aya Amor Correa Ramírez | E23: Prejardín | G23: NO | L23: =IF(H23>0,H23-C23,0) -> 0 | M23: =IF(I23>0,I23-H23,0) -> 0 | N23: =IF(I23>0,I23-C23,0) -> 0
B24: Abril | C24: 45043 | D24: Lucía Urbina Wilches | E24: Prejardín | G24: NO | L24: =IF(H24>0,H24-C24,0) -> 0 | M24: =IF(I24>0,I24-H24,0) -> 0 | N24: =IF(I24>0,I24-C24,0) -> 0
B25: Abril | C25: 45043 | D25: Pablo Jiménez Barrera | E25: Jardín | G25: NO | L25: =IF(H25>0,H25-C25,0) -> 0 | M25: =IF(I25>0,I25-H25,0) -> 0 | N25: =IF(I25>0,I25-C25,0) -> 0
B26: Mayo | C26: 45056 | D26: Agustín Diosa Bedoya | E26: Prejardín | G26: NO | L26: =IF(H26>0,H26-C26,0) -> 0 | M26: =IF(I26>0,I26-H26,0) -> 0 | N26: =IF(I26>0,I26-C26,0) -> 0
B27: Mayo | C27: 45056 | D27: Valentino Iguarán | E27: Jardín | G27: SI | H27: 45124 | I27: 45149 | L27: =IF(H27>0,H27-C27,0) -> 68 | M27: =IF(I27>0,I27-H27,0) -> 25 | N27: =IF(I27>0,I27-C27,0) -> 93
B28: Mayo | C28: 45056 | D28: Abril Vallejo Villegas | E28: Transición | G28: SI | H28: 45684 | J28: No admitida | L28: =IF(H28>0,H28-C28,0) -> 628 | M28: =IF(I28>0,I28-H28,0) -> 0 | N28: =IF(I28>0,I28-C28,0) -> 0
B29: Mayo | C29: 45056 | D29: Miranda Rodríguez | E29: Transición | G29: SI | H29: 45117 | I29: 45138 | L29: =IF(H29>0,H29-C29,0) -> 61 | M29: =IF(I29>0,I29-H29,0) -> 21 | N29: =IF(I29>0,I29-C29,0) -> 82
B30: Mayo | C30: 45058 | D30: Juan Felipe Gómez Uribe | E30: Transición | G30: NO | L30: =IF(H30>0,H30-C30,0) -> 0 | M30: =IF(I30>0,I30-H30,0) -> 0 | N30: =IF(I30>0,I30-C30,0) -> 0
B31: Mayo | C31: 45070 | D31: Martina Álvarez | E31: Jardín | G31: NO | L31: =IF(H31>0,H31-C31,0) -> 0 | M31: =IF(I31>0,I31-H31,0) -> 0 | N31: =IF(I31>0,I31-C31,0) -> 0
B32: Mayo | C32: 45070 | D32: Fabiana Álvarez | E32: Prejardín | G32: NO | L32: =IF(H32>0,H32-C32,0) -> 0 | M32: =IF(I32>0,I32-H32,0) -> 0 | N32: =IF(I32>0,I32-C32,0) -> 0
B33: Mayo | C33: 45070 | D33: Emilia Jaramillo Arroyave | E33: Prejardín | G33: NO | L33: =IF(H33>0,H33-C33,0) -> 0 | M33: =IF(I33>0,I33-H33,0) -> 0 | N33: =IF(I33>0,I33-C33,0) -> 0
B34: Junio | C34: 45093 | D34: Agustín Ospina | E34: Jardín | G34: NO | L34: =IF(H34>0,H34-C34,0) -> 0 | M34: =IF(I34>0,I34-H34,0) -> 0 | N34: =IF(I34>0,I34-C34,0) -> 0
B35: Junio | C35: 45098 | D35: Agustín Giraldo Jaramillo | E35: Prejardín | G35: NO | L35: =IF(H35>0,H35-C35,0) -> 0 | M35: =IF(I35>0,I35-H35,0) -> 0 | N35: =IF(I35>0,I35-C35,0) -> 0
B36: Junio | C36: 45098 | D36: Celeste Vélez Ramírez | E36: Prejardín | G36: NO | L36: =IF(H36>0,H36-C36,0) -> 0 | M36: =IF(I36>0,I36-H36,0) -> 0 | N36: =IF(I36>0,I36-C36,0) -> 0
B37: Junio | C37: 45098 | D37: Santiago Contreras | E37: Prejardín | G37: NO | L37: =IF(H37>0,H37-C37,0) -> 0 | M37: =IF(I37>0,I37-H37,0) -> 0 | N37: =IF(I37>0,I37-C37,0) -> 0
B38: Julio | C38: 45126 | D38: Helena Osorio Ascuntar | E38: Transición | G38: NO | L38: =IF(H38>0,H38-C38,0) -> 0 | M38: =IF(I38>0,I38-H38,0) -> 0 | N38: =IF(I38>0,I38-C38,0) -> 0
B39: Julio | C39: 45126 | D39: Juan Martín Isaza | E39: Jardín | G39: NO | L39: =IF(H39>0,H39-C39,0) -> 0 | M39: =IF(I39>0,I39-H39,0) -> 0 | N39: =IF(I39>0,I39-C39,0) -> 0
B40: Julio | C40: 45126 | D40: Isabella Usme | E40: Transición | G40: NO | L40: =IF(H40>0,H40-C40,0) -> 0 | M40: =IF(I40>0,I40-H40,0) -> 0 | N40: =IF(I40>0,I40-C40,0) -> 0
B41: Julio | C41: 45126 | D41: Lucas Gómez Fernández | E41: Prejardín | G41: NO | L41: =IF(H41>0,H41-C41,0) -> 0 | M41: =IF(I41>0,I41-H41,0) -> 0 | N41: =IF(I41>0,I41-C41,0) -> 0
... B45: Agosto | C45: 45140 | D45: Ermes Suárez Mejía | E45: Transición | G45: NO | L45: =IF(H45>0,H45-C45,0) -> 0 | M45: =IF(I45>0,I45-H45,0) -> 0 | N45: =IF(I45>0,I45-C45,0) -> 0
B46: Agosto | C46: 45140 | D46: Federico Aristizábal Rubiano | E46: Transición | G46: SI | H46: 45222 | I46: 45306 | L46: =IF(H46>0,H46-C46,0) -> 82 | M46: =IF(I46>0,I46-H46,0) -> 84 | N46: =IF(I46>0,I46-C46,0) -> 166
B47: Agosto | C47: 45154 | D47: Miguel Cardona Gómez | E47: Prejardín | G47: NO | L47: =IF(H47>0,H47-C47,0) -> 0 | M47: =IF(I47>0,I47-H47,0) -> 0 | N47: =IF(I47>0,I47-C47,0) -> 0
B48: Agosto | C48: 45154 | D48: Guadalupe Naranjo | E48: Transición | G48: NO | L48: =IF(H48>0,H48-C48,0) -> 0 | M48: =IF(I48>0,I48-H48,0) -> 0 | N48: =IF(I48>0,I48-C48,0) -> 0
B49: Agosto | C49: 45161 | D49: Salvador Garcés | E49: Transición | G49: SI | H49: 45229 | J49: Desistieron del proceso | L49: =IF(H49>0,H49-C49,0) -> 68 | M49: =IF(I49>0,I49-H49,0) -> 0 | N49: =IF(I49>0,I49-C49,0) -> 0
B50: Septiembre | C50: 45181 | D50: Amalia Paucar Álvarez | E50: Prejardín | G50: NO | L50: =IF(H50>0,H50-C50,0) -> 0 | M50: =IF(I50>0,I50-H50,0) -> 0 | N50: =IF(I50>0,I50-C50,0) -> 0
B51: Septiembre | C51: 45196 | D51: Lorenzo Posada | E51: Prejardín | G51: NO | L51: =IF(H51>0,H51-C51,0) -> 0 | M51: =IF(I51>0,I51-H51,0) -> 0 | N51: =IF(I51>0,I51-C51,0) -> 0
B52: Septiembre | C52: 45196 | D52: Roma Arango Arango | E52: Prejardín | G52: NO | L52: =IF(H52>0,H52-C52,0) -> 0 | M52: =IF(I52>0,I52-H52,0) -> 0 | N52: =IF(I52>0,I52-C52,0) -> 0
B53: Septiembre | C53: 45196 | D53: Dante Guerrero | E53: Prejardín | G53: SI | H53: 45601 | I53: 45673 | L53: =IF(H53>0,H53-C53,0) -> 405 | M53: =IF(I53>0,I53-H53,0) -> 72 | N53: =IF(I53>0,I53-C53,0) -> 477
B54: Septiembre | C54: 45196 | D54: Guadalupe Sánchez | E54: Prejardín | G54: SI | H54: 45601 | I54: 45673 | L54: =IF(H54>0,H54-C54,0) -> 405 | M54: =IF(I54>0,I54-H54,0) -> 72 | N54: =IF(I54>0,I54-C54,0) -> 477
B55: Septiembre | C55: 45198 | D55: Maximiliano Lopera Salinas | E55: Transición | G55: NO | L55: =IF(H55>0,H55-C55,0) -> 0 | M55: =IF(I55>0,I55-H55,0) -> 0 | N55: =IF(I55>0,I55-C55,0) -> 0
B56: Octubre | C56: 45217 | D56: Juan Emilio Taborda | E56: Jardín | G56: NO | L56: =IF(H56>0,H56-C56,0) -> 0 | M56: =IF(I56>0,I56-H56,0) -> 0 | N56: =IF(I56>0,I56-C56,0) -> 0
B57: Octubre | C57: 45217 | D57: Ela Saldarriaga | E57: Prejardín | G57: NO | L57: =IF(H57>0,H57-C57,0) -> 0 | M57: =IF(I57>0,I57-H57,0) -> 0 | N57: =IF(I57>0,I57-C57,0) -> 0
B58: Noviembre | C58: 45245 | D58: Martina Franco | E58: Transición | G58: NO | L58: =IF(H58>0,H58-C58,0) -> 0 | M58: =IF(I58>0,I58-H58,0) -> 0 | N58: =IF(I58>0,I58-C58,0) -> 0
B59: Noviembre | C59: 45245 | D59: Ismael Betancur Montoya | E59: Jardín | G59: NO | L59: =IF(H59>0,H59-C59,0) -> 0 | M59: =IF(I59>0,I59-H59,0) -> 0 | N59: =IF(I59>0,I59-C59,0) -> 0
B60: Noviembre | C60: 45259 | D60: Lorenzo Eslava Restrepo | E60: Jardín | G60: SI | H60: 45524 | I60: 45552 | L60: =IF(H60>0,H60-C60,0) -> 265 | M60: =IF(I60>0,I60-H60,0) -> 28 | N60: =IF(I60>0,I60-C60,0) -> 293
B61: Enero | C61: 45315 | D61: Juan Martín Soto | E61: Prejardín | F61: Referido Alex Valencia | G61: NO | K61: Bebè de 4 meses | L61: =IF(H61>0,H61-C61,0) -> 0 | M61: =IF(I61>0,I61-H61,0) -> 0 | N61: =IF(I61>0,I61-C61,0) -> 0
B62: Enero | C62: 45315 | D62: Clemente Ramírez | E62: Transición | F62: Referido Carolina Hoyos y Camila Urrego | G62: NO | K62: Validando otras opciones | L62: =IF(H62>0,H62-C62,0) -> 0 | M62: =IF(I62>0,I62-H62,0) -> 0 | N62: =IF(I62>0,I62-C62,0) -> 0
B63: Enero | C63: 45315 | D63: Samuel Restrepo | E63: Prejardín | F63: Referido Alejandro Arango | G63: NO | K63: Desean proceso en octubre | L63: =IF(H63>0,H63-C63,0) -> 0 | M63: =IF(I63>0,I63-H63,0) -> 0 | N63: =IF(I63>0,I63-C63,0) -> 0
B64: Enero | C64: 45306 | D64: Juan Antonio Duque Yanini | E64: Transición | F64: Internet | G64: SI | H64: 45320 | I64: 45336 | L64: =IF(H64>0,H64-C64,0) -> 14 | M64: =IF(I64>0,I64-H64,0) -> 16 | N64: =IF(I64>0,I64-C64,0) -> 30
B65: Enero | C65: 45306 | D65: Helena Rocha Zapata | E65: Jardín | F65: Referido | G65: NO | L65: =IF(H65>0,H65-C65,0) -> 0 | M65: =IF(I65>0,I65-H65,0) -> 0 | N65: =IF(I65>0,I65-C65,0) -> 0
B66: Febrero | C66: 45329 | D66: Antonia Ramírez | E66: Prejardín | G66: NO | K66: Tiene 2 años | L66: =IF(H66>0,H66-C66,0) -> 0 | M66: =IF(I66>0,I66-H66,0) -> 0 | N66: =IF(I66>0,I66-C66,0) -> 0
B67: Febrero | C67: 45329 | D67: Iris Thomson | E67: Prejardín | F67: Referido Kora Dominica | G67: NO | K67: Tiene 2 años | L67: =IF(H67>0,H67-C67,0) -> 0 | M67: =IF(I67>0,I67-H67,0) -> 0 | N67: =IF(I67>0,I67-C67,0) -> 0
B68: Febrero | C68: 45343 | D68: Lucas Álvarez Santaularia | E68: Prejardín | F68: Referido | G68: NO | K68: No desea continuar proceso | L68: =IF(H68>0,H68-C68,0) -> 0 | M68: =IF(I68>0,I68-H68,0) -> 0 | N68: =IF(I68>0,I68-C68,0) -> 0
B69: Febrero | C69: 45329 | D69: Emma Ruìz Jaramillo | E69: Jardín | F69: Referido de Isaac Collins | G69: NO | K69: No desea continuar proceso | L69: =IF(H69>0,H69-C69,0) -> 0 | M69: =IF(I69>0,I69-H69,0) -> 0 | N69: =IF(I69>0,I69-C69,0) -> 0
B70: Marzo | C70: 45357 | D70: Amelia Sosa Arcila | E70: Jardín | F70: Referido | G70: NO | K70: Se hace contacto y no responde | L70: =IF(H70>0,H70-C70,0) -> 0 | M70: =IF(I70>0,I70-H70,0) -> 0 | N70: =IF(I70>0,I70-C70,0) -> 0
B71: Abril | C71: 45408 | D71: Máximo Barreto | E71: Jardín | F71: Feria Conocer | G71: NO | K71: No desea continuar proceso | L71: =IF(H71>0,H71-C71,0) -> 0 | M71: =IF(I71>0,I71-H71,0) -> 0 | N71: =IF(I71>0,I71-C71,0) -> 0
B72: Abril | C72: 45408 | D72: Juan Sebastian Ruíz | E72: Prejardín | F72: Feria Conocer | G72: NO | K72: Se hace contacto y no responde | L72: =IF(H72>0,H72-C72,0) -> 0 | M72: =IF(I72>0,I72-H72,0) -> 0 | N72: =IF(I72>0,I72-C72,0) -> 0
B73: Abril | C73: 45408 | D73: Antonio Saldarriaga | E73: Jardín | F73: Internet | G73: NO | K73: Desean proceso màs adelante | L73: =IF(H73>0,H73-C73,0) -> 0 | M73: =IF(I73>0,I73-H73,0) -> 0 | N73: =IF(I73>0,I73-C73,0) -> 0
B74: Abril | C74: 45412 | D74: Camila Oesch | E74: Prejardín | F74: Referido Adriana Fontàn | G74: NO | K74: Tiene cupo reservado en el Columbus | L74: =IF(H74>0,H74-C74,0) -> 0 | M74: =IF(I74>0,I74-H74,0) -> 0 | N74: =IF(I74>0,I74-C74,0) -> 0
B75: Abril | C75: 45412 | D75: Federico Oesch | E75: Prejardín | F75: Referido Adriana Fontàn | G75: NO | K75: Tiene cupo reservado en el Columbus | L75: =IF(H75>0,H75-C75,0) -> 0 | M75: =IF(I75>0,I75-H75,0) -> 0 | N75: =IF(I75>0,I75-C75,0) -> 0
B76: Mayo | C76: 45420 | D76: Paul Jean Leon Bakaert | E76: Prejardín | F76: Referido | G76: NO | K76: Tiene 2 años | L76: =IF(H76>0,H76-C76,0) -> 0 | M76: =IF(I76>0,I76-H76,0) -> 0 | N76: =IF(I76>0,I76-C76,0) -> 0
B77: Mayo | C77: 45429 | D77: Olivia Cruz | E77: Jardín | F77: Egresada del colegio | G77: SI | H77: 45502 | J77: No admitida | L77: =IF(H77>0,H77-C77,0) -> 73 | M77: =IF(I77>0,I77-H77,0) -> 0 | N77: =IF(I77>0,I77-C77,0) -> 0
B78: Mayo | C78: 45429 | D78: Iris Cruz | E78: Prejardín | F78: Egresada del colegio | G78: NO | K78: Tiene 2 años esperando que cumpla la edad | L78: =IF(H78>0,H78-C78,0) -> 0 | M78: =IF(I78>0,I78-H78,0) -> 0 | N78: =IF(I78>0,I78-C78,0) -> 0
B79: Mayo | C79: 45429 | D79: Kala Guerrero | E79: Jardín | F79: Internet | G79: NO | K79: Se hace contacto y no responde | L79: =IF(H79>0,H79-C79,0) -> 0 | M79: =IF(I79>0,I79-H79,0) -> 0 | N79: =IF(I79>0,I79-C79,0) -> 0
B80: Junio | C80: 45448 | D80: Amalia Vèlez Tabares | E80: Transición | F80: Referido | G80: SI | H80: 45483 | J80: No admitida | L80: =IF(H80>0,H80-C80,0) -> 35 | M80: =IF(I80>0,I80-H80,0) -> 0 | N80: =IF(I80>0,I80-C80,0) -> 0
B81: Junio | C81: 45448 | D81: Olivia Pizano Morales | E81: Prejardín | F81: Referido Alicia y Jerònimo Ospina | G81: NO | K81: Tiene 1 año | L81: =IF(H81>0,H81-C81,0) -> 0 | M81: =IF(I81>0,I81-H81,0) -> 0 | N81: =IF(I81>0,I81-C81,0) -> 0
B82: Junio | C82: 45448 | D82: Macarena Agudelo Muñoz | E82: Prejardín | F82: Referido familia de Rosario | G82: NO | K82: En gestación | L82: =IF(H82>0,H82-C82,0) -> 0 | M82: =IF(I82>0,I82-H82,0) -> 0 | N82: =IF(I82>0,I82-C82,0) -> 0
B83: Junio | C83: 45448 | D83: Bejamìn Muñoz Zuluaga | E83: Prejardín | F83: Internet | G83: NO | K83: Tiene 1 año | L83: =IF(H83>0,H83-C83,0) -> 0 | M83: =IF(I83>0,I83-H83,0) -> 0 | N83: =IF(I83>0,I83-C83,0) -> 0
B84: Junio | C84: 45448 | D84: Samuel Gallo Cano | E84: Jardín | F84: Referido | G84: NO | K84: Por recomendación neuro desisten del proceso | L84: =IF(H84>0,H84-C84,0) -> 0 | M84: =IF(I84>0,I84-H84,0) -> 0 | N84: =IF(I84>0,I84-C84,0) -> 0
B85: Julio | C85: 45483 | D85: Isaac Jaramillo | E85: Prejardín | F85: Referido María Jaramillo | G85: NO | K85: Visitarán otro colegio | L85: =IF(H85>0,H85-C85,0) -> 0 | M85: =IF(I85>0,I85-H85,0) -> 0 | N85: =IF(I85>0,I85-C85,0) -> 0
B86: Julio | C86: 45492 | D86: Máximo Gómez | E86: Prejardín | F86: Referido Felipe Vallejo | G86: NO | L86: =IF(H86>0,H86-C86,0) -> 0 | M86: =IF(I86>0,I86-H86,0) -> 0 | N86: =IF(I86>0,I86-C86,0) -> 0
B87: Julio | C87: 45497 | D87: Cristopher Daza | E87: Prejardín | F87: Referido | G87: SI | J87: Reserva de cupo | K87: Cupo reservado | L87: =IF(H87>0,H87-C87,0) -> 0 | M87: =IF(I87>0,I87-H87,0) -> 0 | N87: =IF(I87>0,I87-C87,0) -> 0
B88: Julio | C88: 45497 | D88: Salomón Tirado | E88: Jardín | F88: Referido | G88: NO | K88: están revisando presupuesto | L88: =IF(H88>0,H88-C88,0) -> 0 | M88: =IF(I88>0,I88-H88,0) -> 0 | N88: =IF(I88>0,I88-C88,0) -> 0
B89: Julio | C89: 45499 | D89: Amelia Mejía Tamayo | E89: Jardín | F89: Referido Adriana Fontàn | G89: NO | K89: desea proceso pero la matricula costosa . Cita con Alex | L89: =IF(H89>0,H89-C89,0) -> 0 | M89: =IF(I89>0,I89-H89,0) -> 0 | N89: =IF(I89>0,I89-C89,0) -> 0
B90: Agosto | C90: 45525 | D90: Dayireth Giraldo | E90: Transición | F90: Referido Jhoany Ortiz | G90: SI | H90: 45684 | J90: Desistieron del proceso | L90: =IF(H90>0,H90-C90,0) -> 159 | M90: =IF(I90>0,I90-H90,0) -> 0 | N90: =IF(I90>0,I90-C90,0) -> 0
B91: Agosto | C91: 45525 | D91: Giancarlo Avendaño | E91: Prejardín | F91: Internet | G91: NO | L91: =IF(H91>0,H91-C91,0) -> 0 | M91: =IF(I91>0,I91-H91,0) -> 0 | N91: =IF(I91>0,I91-C91,0) -> 0
B92: Septiembre | C92: 45553 | D92: Kailani Antonella Restrepo | E92: Prejardín | F92: Internet | G92: NO | K92: desea proceso en 2025 mitad | L92: =IF(H92>0,H92-C92,0) -> 0 | M92: =IF(I92>0,I92-H92,0) -> 0 | N92: =IF(I92>0,I92-C92,0) -> 0
B93: Septiembre | C93: 45553 | D93: Martín mira | E93: Prejardín | F93: Redes sociales | G93: NO | K93: No desea iniciar proceso por temas ecónomicos | L93: =IF(H93>0,H93-C93,0) -> 0 | M93: =IF(I93>0,I93-H93,0) -> 0 | N93: =IF(I93>0,I93-C93,0) -> 0
B94: Septiembre | C94: 45553 | D94: Natalia Pulgar Rodríguez | E94: Prejardín | F94: Internet | G94: NO | K94: desea proceso para 1° | L94: =IF(H94>0,H94-C94,0) -> 0 | M94: =IF(I94>0,I94-H94,0) -> 0 | N94: =IF(I94>0,I94-C94,0) -> 0
B95: Octubre | C95: 45581 | D95: Eva Suárez Tamayo | E95: Jardín | F95: Referido Federico Aristizábal | G95: SI | H95: 45594 | I95: 45673 | L95: =IF(H95>0,H95-C95,0) -> 13 | M95: =IF(I95>0,I95-H95,0) -> 79 | N95: =IF(I95>0,I95-C95,0) -> 92
B96: Octubre | C96: 45595 | D96: Maria Angel Aponte Cuevas | E96: Jardín | F96: Referido | G96: NO | L96: =IF(H96>0,H96-C96,0) -> 0 | M96: =IF(I96>0,I96-H96,0) -> 0 | N96: =IF(I96>0,I96-C96,0) -> 0
B97: Octubre | C97: 45595 | D97: Benjamín Ruíz | E97: Prejardín | F97: Referido Julio Fontán | G97: NO | L97: =IF(H97>0,H97-C97,0) -> 0 | M97: =IF(I97>0,I97-H97,0) -> 0 | N97: =IF(I97>0,I97-C97,0) -> 0
B98: Noviembre | C98: 45604 | D98: Josep Wilke | E98: Transición | F98: Referido Kora Dominica | G98: SI | H98: 45677 | I98: 45699 | L98: =IF(H98>0,H98-C98,0) -> 73 | M98: =IF(I98>0,I98-H98,0) -> 22 | N98: =IF(I98>0,I98-C98,0) -> 95
B99: Noviembre | C99: 45604 | D99: Alma Wilke | E99: Prejardín | F99: Referido Kora Dominica | G99: SI | H99: 45944 | I99: 45958 | L99: =IF(H99>0,H99-C99,0) -> 340 | M99: =IF(I99>0,I99-H99,0) -> 14 | N99: =IF(I99>0,I99-C99,0) -> 354
B100: Noviembre | C100: 45609 | D100: Gabriela Castro Vanegas | E100: Prejardín | F100: Referido | G100: NO | L100: =IF(H100>0,H100-C100,0) -> 0 | M100: =IF(I100>0,I100-H100,0) -> 0 | N100: =IF(I100>0,I100-C100,0) -> 0
B101: Noviembre | C101: 45623 | D101: Michael Barajas | E101: Jardín | F101: Internet | G101: NO | L101: =IF(H101>0,H101-C101,0) -> 0 | M101: =IF(I101>0,I101-H101,0) -> 0 | N101: =IF(I101>0,I101-C101,0) -> 0
B102: Noviembre | C102: 45623 | D102: Emmanuel López | E102: Prejardín | F102: Referido Angela Botero | G102: SI | H102: 45677 | I102: 45699 | L102: =IF(H102>0,H102-C102,0) -> 54 | M102: =IF(I102>0,I102-H102,0) -> 22 | N102: =IF(I102>0,I102-C102,0) -> 76
B103: Diciembre | C103: 45637 | D103: Isaac Herrera | E103: Jardín | F103: Referido psicologa | G103: NO | L103: =IF(H103>0,H103-C103,0) -> 0 | M103: =IF(I103>0,I103-H103,0) -> 0 | N103: =IF(I103>0,I103-C103,0) -> 0
...

Sheet Datos Primaria
B1: Mes | C1: Día | D1: Estudiante | E1: Grado | F1: Como conoció el colegio | G1: Inicio proceso | H1: Pruebas | I1: Observación | J1: Matrícula | K1: Estado del proceso | L1: Observaciones | M1: Días entre cita de info e inicio de pruebas | N1: Días entre pruebas y observa | O1: Días entre inici de observa y matrícula | P1: Días entre cita de info y matrícula | Q1: =AVERAGEIF(M2:M896,">0",M2:M896) -> 54.5 | R1: =AVERAGEIF(N2:N896,">0",N2:N896) -> 22.071429 | S1: =AVERAGEIF(O2:O896,">0",O2:O896) -> 51.510204 | T1: =AVERAGEIF(P2:P896,">0",P2:P896) -> 120.04082 | V1: =AVERAGEIF(P2:P896,">0",M2:M896) -> 12.367347 | W1: =AVERAGEIF(P2:P896,">0",N2:N896) -> 6.1632653 | X1: =AVERAGEIF(P2:P896,">0",O2:O896) -> 51.510204 | Y1: =AVERAGEIF(P2:P896,">0",P2:P896) -> 120.04082
B2: Enero | C2: 44939 | D2: Salome Alvarez | E2: 4° | G2: NO | M2: =IF(H2>0,H2-C2,0) -> 0 | N2: =IF(H2>0,IF(I2>0,I2-H2,0),0) -> 0 | O2: =IF(J2>0,J2-I2,0) -> 0 | P2: =IF(J2>0,J2-C2,0) -> 0
B3: Enero | C3: 44946 | D3: Samuel Santiesteban Bernal | E3: 3° | G3: NO | M3: =IF(H3>0,H3-C3,0) -> 0 | N3: =IF(H3>0,IF(I3>0,I3-H3,0),0) -> 0 | O3: =IF(J3>0,J3-I3,0) -> 0 | P3: =IF(J3>0,J3-C3,0) -> 0
B4: Enero | C4: 44946 | D4: Felipe Canel Rubio | E4: 3° | G4: SI | I4: 45124 | J4: 45146 | M4: =IF(H4>0,H4-C4,0) -> 0 | N4: =IF(H4>0,IF(I4>0,I4-H4,0),0) -> 0 | O4: =IF(J4>0,J4-I4,0) -> 22 | P4: =IF(J4>0,J4-C4,0) -> 200
B5: Enero | C5: 44946 | D5: Sara Canel Rubio | E5: 1° | G5: SI | I5: 45124 | J5: 45146 | M5: =IF(H5>0,H5-C5,0) -> 0 | N5: =IF(H5>0,IF(I5>0,I5-H5,0),0) -> 0 | O5: =IF(J5>0,J5-I5,0) -> 22 | P5: =IF(J5>0,J5-C5,0) -> 200
B6: Enero | C6: 44946 | D6: Isabella Ayala | E6: 2° | G6: NO | M6: =IF(H6>0,H6-C6,0) -> 0 | N6: =IF(H6>0,IF(I6>0,I6-H6,0),0) -> 0 | O6: =IF(J6>0,J6-I6,0) -> 0 | P6: =IF(J6>0,J6-C6,0) -> 0
B7: Enero | C7: 44946 | D7: Maria Angel Sepulveda | E7: 1° | G7: NO | M7: =IF(H7>0,H7-C7,0) -> 0 | N7: =IF(H7>0,IF(I7>0,I7-H7,0),0) -> 0 | O7: =IF(J7>0,J7-I7,0) -> 0 | P7: =IF(J7>0,J7-C7,0) -> 0
B8: Enero | C8: 44946 | D8: Jerónimo Neira Gómez. | E8: 5° | G8: NO | M8: =IF(H8>0,H8-C8,0) -> 0 | N8: =IF(H8>0,IF(I8>0,I8-H8,0),0) -> 0 | O8: =IF(J8>0,J8-I8,0) -> 0 | P8: =IF(J8>0,J8-C8,0) -> 0
B9: Enero | C9: 44953 | D9: Luciana Vásquez baena | E9: 3° | G9: NO | M9: =IF(H9>0,H9-C9,0) -> 0 | N9: =IF(H9>0,IF(I9>0,I9-H9,0),0) -> 0 | O9: =IF(J9>0,J9-I9,0) -> 0 | P9: =IF(J9>0,J9-C9,0) -> 0
B10: Enero | C10: 44953 | D10: María Antonia Méndez | E10: 3° | G10: NO | M10: =IF(H10>0,H10-C10,0) -> 0 | N10: =IF(H10>0,IF(I10>0,I10-H10,0),0) -> 0 | O10: =IF(J10>0,J10-I10,0) -> 0 | P10: =IF(J10>0,J10-C10,0) -> 0
B11: Febrero | C11: 44959 | D11: Sara Suárez | E11: 5° | G11: NO | M11: =IF(H11>0,H11-C11,0) -> 0 | N11: =IF(H11>0,IF(I11>0,I11-H11,0),0) -> 0 | O11: =IF(J11>0,J11-I11,0) -> 0 | P11: =IF(J11>0,J11-C11,0) -> 0
B12: Febrero | C12: 44974 | D12: Matias Lopez Salazar | E12: 5° | G12: NO | M12: =IF(H12>0,H12-C12,0) -> 0 | N12: =IF(H12>0,IF(I12>0,I12-H12,0),0) -> 0 | O12: =IF(J12>0,J12-I12,0) -> 0 | P12: =IF(J12>0,J12-C12,0) -> 0
B13: Febrero | C13: 44974 | D13: Ariana Espinal | E13: 4° | G13: NO | M13: =IF(H13>0,H13-C13,0) -> 0 | N13: =IF(H13>0,IF(I13>0,I13-H13,0),0) -> 0 | O13: =IF(J13>0,J13-I13,0) -> 0 | P13: =IF(J13>0,J13-C13,0) -> 0
B14: Febrero | C14: 44967 | D14: Agustin Castaño Giraldo | E14: 1° | G14: NO | M14: =IF(H14>0,H14-C14,0) -> 0 | N14: =IF(H14>0,IF(I14>0,I14-H14,0),0) -> 0 | O14: =IF(J14>0,J14-I14,0) -> 0 | P14: =IF(J14>0,J14-C14,0) -> 0
B15: Febrero | C15: 44981 | D15: Emilio Villada | E15: 5° | G15: SI | H15: 44993 | I15: 45006 | J15: 45048 | M15: =IF(H15>0,H15-C15,0) -> 12 | N15: =IF(H15>0,IF(I15>0,I15-H15,0),0) -> 13 | O15: =IF(J15>0,J15-I15,0) -> 42 | P15: =IF(J15>0,J15-C15,0) -> 67
B16: Marzo | C16: 45014 | D16: Antonio Hoyos Cruz | E16: 1° | G16: NO | M16: =IF(H16>0,H16-C16,0) -> 0 | N16: =IF(H16>0,IF(I16>0,I16-H16,0),0) -> 0 | O16: =IF(J16>0,J16-I16,0) -> 0 | P16: =IF(J16>0,J16-C16,0) -> 0
B17: Marzo | C17: 45015 | D17: Felipe Arango Escobar | E17: 2° | G17: NO | M17: =IF(H17>0,H17-C17,0) -> 0 | N17: =IF(H17>0,IF(I17>0,I17-H17,0),0) -> 0 | O17: =IF(J17>0,J17-I17,0) -> 0 | P17: =IF(J17>0,J17-C17,0) -> 0
B18: Abril | C18: 45028 | D18: Nicolás Restrepo Escobar | E18: 3° | G18: SI | I18: 45090 | J18: 45138 | M18: =IF(H18>0,H18-C18,0) -> 0 | N18: =IF(H18>0,IF(I18>0,I18-H18,0),0) -> 0 | O18: =IF(J18>0,J18-I18,0) -> 48 | P18: =IF(J18>0,J18-C18,0) -> 110
B19: Abril | C19: 45030 | D19: Sofía Bernal Henao | E19: 2° | G19: NO | M19: =IF(H19>0,H19-C19,0) -> 0 | N19: =IF(H19>0,IF(I19>0,I19-H19,0),0) -> 0 | O19: =IF(J19>0,J19-I19,0) -> 0 | P19: =IF(J19>0,J19-C19,0) -> 0
B20: Abril | C20: 45030 | D20: Amalia Ruíz García | E20: 5° | G20: NO | M20: =IF(H20>0,H20-C20,0) -> 0 | N20: =IF(H20>0,IF(I20>0,I20-H20,0),0) -> 0 | O20: =IF(J20>0,J20-I20,0) -> 0 | P20: =IF(J20>0,J20-C20,0) -> 0
B21: Abril | C21: 45030 | D21: Juan Pablo Ramírez | E21: 4° | G21: NO | M21: =IF(H21>0,H21-C21,0) -> 0 | N21: =IF(H21>0,IF(I21>0,I21-H21,0),0) -> 0 | O21: =IF(J21>0,J21-I21,0) -> 0 | P21: =IF(J21>0,J21-C21,0) -> 0
B22: Abril | C22: 45034 | D22: Liam Buririca Parra | E22: 3° | G22: NO | M22: =IF(H22>0,H22-C22,0) -> 0 | N22: =IF(H22>0,IF(I22>0,I22-H22,0),0) -> 0 | O22: =IF(J22>0,J22-I22,0) -> 0 | P22: =IF(J22>0,J22-C22,0) -> 0
B23: Abril | C23: 45037 | D23: Ian Fernández | E23: 1° | G23: SI | I23: 45040 | K23: No admitido | M23: =IF(H23>0,H23-C23,0) -> 0 | N23: =IF(H23>0,IF(I23>0,I23-H23,0),0) -> 0 | O23: =IF(J23>0,J23-I23,0) -> 0 | P23: =IF(J23>0,J23-C23,0) -> 0
B24: Mayo | C24: 45050 | D24: Luciana Arrázola | E24: 5° | G24: NO | M24: =IF(H24>0,H24-C24,0) -> 0 | N24: =IF(H24>0,IF(I24>0,I24-H24,0),0) -> 0 | O24: =IF(J24>0,J24-I24,0) -> 0 | P24: =IF(J24>0,J24-C24,0) -> 0
B25: Mayo | C25: 45058 | D25: Antonio Ríos Villegas | E25: 3° | G25: NO | M25: =IF(H25>0,H25-C25,0) -> 0 | N25: =IF(H25>0,IF(I25>0,I25-H25,0),0) -> 0 | O25: =IF(J25>0,J25-I25,0) -> 0 | P25: =IF(J25>0,J25-C25,0) -> 0
B26: Mayo | C26: 45058 | D26: Amelia Pérez Cardona | E26: 2° | G26: SI | I26: 45061 | J26: 45083 | M26: =IF(H26>0,H26-C26,0) -> 0 | N26: =IF(H26>0,IF(I26>0,I26-H26,0),0) -> 0 | O26: =IF(J26>0,J26-I26,0) -> 22 | P26: =IF(J26>0,J26-C26,0) -> 25
B27: Mayo | C27: 45065 | D27: Ivanna Ramírez Vélez | E27: 2° | G27: SI | I27: 45076 | J27: 45100 | M27: =IF(H27>0,H27-C27,0) -> 0 | N27: =IF(H27>0,IF(I27>0,I27-H27,0),0) -> 0 | O27: =IF(J27>0,J27-I27,0) -> 24 | P27: =IF(J27>0,J27-C27,0) -> 35
B28: Junio | C28: 45084 | D28: Valerie Maturana Ruíz | E28: 5° | G28: SI | I28: 45092 | J28: 45306 | M28: =IF(H28>0,H28-C28,0) -> 0 | N28: =IF(H28>0,IF(I28>0,I28-H28,0),0) -> 0 | O28: =IF(J28>0,J28-I28,0) -> 214 | P28: =IF(J28>0,J28-C28,0) -> 222
B29: Junio | C29: 45084 | D29: Felipe Maturana Ruíz | E29: 1° | G29: NO | M29: =IF(H29>0,H29-C29,0) -> 0 | N29: =IF(H29>0,IF(I29>0,I29-H29,0),0) -> 0 | O29: =IF(J29>0,J29-I29,0) -> 0 | P29: =IF(J29>0,J29-C29,0) -> 0
B30: Junio | C30: 45084 | D30: Isabella Zapata Arango | E30: 3° | G30: NO | M30: =IF(H30>0,H30-C30,0) -> 0 | N30: =IF(H30>0,IF(I30>0,I30-H30,0),0) -> 0 | O30: =IF(J30>0,J30-I30,0) -> 0 | P30: =IF(J30>0,J30-C30,0) -> 0
B31: Junio | C31: 45084 | D31: Guadalupe Giraldo Zuluaga | E31: 5° | G31: SI | H31: 45207 | I31: 45244 | J31: 45306 | M31: =IF(H31>0,H31-C31,0) -> 123 | N31: =IF(H31>0,IF(I31>0,I31-H31,0),0) -> 37 | O31: =IF(J31>0,J31-I31,0) -> 62 | P31: =IF(J31>0,J31-C31,0) -> 222
B32: Junio | C32: 45084 | D32: Victoria Giraldo Zuluaga | E32: 2° | G32: SI | I32: 45244 | J32: 45306 | M32: =IF(H32>0,H32-C32,0) -> 0 | N32: =IF(H32>0,IF(I32>0,I32-H32,0),0) -> 0 | O32: =IF(J32>0,J32-I32,0) -> 62 | P32: =IF(J32>0,J32-C32,0) -> 222
B33: Junio | C33: 45093 | D33: Josué Rodríguez Yepes | E33: 4° | G33: SI | I33: 45118 | J33: 45231 | M33: =IF(H33>0,H33-C33,0) -> 0 | N33: =IF(H33>0,IF(I33>0,I33-H33,0),0) -> 0 | O33: =IF(J33>0,J33-I33,0) -> 113 | P33: =IF(J33>0,J33-C33,0) -> 138
B34: Junio | C34: 45093 | D34: Julieta Ospina | E34: 5° | G34: NO | M34: =IF(H34>0,H34-C34,0) -> 0 | N34: =IF(H34>0,IF(I34>0,I34-H34,0),0) -> 0 | O34: =IF(J34>0,J34-I34,0) -> 0 | P34: =IF(J34>0,J34-C34,0) -> 0
B35: Junio | C35: 45100 | D35: Ian Canizales Steel | E35: 3° | G35: NO | M35: =IF(H35>0,H35-C35,0) -> 0 | N35: =IF(H35>0,IF(I35>0,I35-H35,0),0) -> 0 | O35: =IF(J35>0,J35-I35,0) -> 0 | P35: =IF(J35>0,J35-C35,0) -> 0
B36: Junio | C36: 45100 | D36: Emma Labrador Medina | E36: 1° | G36: SI | I36: 45138 | J36: 45161 | M36: =IF(H36>0,H36-C36,0) -> 0 | N36: =IF(H36>0,IF(I36>0,I36-H36,0),0) -> 0 | O36: =IF(J36>0,J36-I36,0) -> 23 | P36: =IF(J36>0,J36-C36,0) -> 61
B37: Junio | C37: 45100 | D37: Thiago Labrador Medina | E37: 2° | G37: SI | I37: 45138 | J37: 45161 | M37: =IF(H37>0,H37-C37,0) -> 0 | N37: =IF(H37>0,IF(I37>0,I37-H37,0),0) -> 0 | O37: =IF(J37>0,J37-I37,0) -> 23 | P37: =IF(J37>0,J37-C37,0) -> 61
B38: Junio | C38: 45100 | D38: Jacobo Prieto Espinal | E38: 1° | G38: NO | M38: =IF(H38>0,H38-C38,0) -> 0 | N38: =IF(H38>0,IF(I38>0,I38-H38,0),0) -> 0 | O38: =IF(J38>0,J38-I38,0) -> 0 | P38: =IF(J38>0,J38-C38,0) -> 0
B39: Julio | C39: 45113 | D39: Juan Diego Restrepo Molina | E39: 5° | G39: NO | M39: =IF(H39>0,H39-C39,0) -> 0 | N39: =IF(H39>0,IF(I39>0,I39-H39,0),0) -> 0 | O39: =IF(J39>0,J39-I39,0) -> 0 | P39: =IF(J39>0,J39-C39,0) -> 0
B40: Julio | C40: 45114 | D40: Andrés Felipe Cassiano Sandoval | E40: 5° | G40: SI | H40: 45126 | I40: 45138 | J40: 45167 | M40: =IF(H40>0,H40-C40,0) -> 12 | N40: =IF(H40>0,IF(I40>0,I40-H40,0),0) -> 12 | O40: =IF(J40>0,J40-I40,0) -> 29 | P40: =IF(J40>0,J40-C40,0) -> 53
B41: Julio | C41: 45114 | D41: Tomás Vélez Gómez | E41: 4° | G41: NO | M41: =IF(H41>0,H41-C41,0) -> 0 | N41: =IF(H41>0,IF(I41>0,I41-H41,0),0) -> 0 | O41: =IF(J41>0,J41-I41,0) -> 0 | P41: =IF(J41>0,J41-C41,0) -> 0
B42: Julio | C42: 45114 | D42: Paula Pereira López | E42: 1° | G42: NO | M42: =IF(H42>0,H42-C42,0) -> 0 | N42: =IF(H42>0,IF(I42>0,I42-H42,0),0) -> 0 | O42: =IF(J42>0,J42-I42,0) -> 0 | P42: =IF(J42>0,J42-C42,0) -> 0
B43: Julio | C43: 45134 | D43: Santiago Aristizabal Bernal | E43: 4° | G43: NO | M43: =IF(H43>0,H43-C43,0) -> 0 | N43: =IF(H43>0,IF(I43>0,I43-H43,0),0) -> 0 | O43: =IF(J43>0,J43-I43,0) -> 0 | P43: =IF(J43>0,J43-C43,0) -> 0
B44: Julio | C44: 45128 | D44: Iker Vanegas | E44: 3° | G44: NO | M44: =IF(H44>0,H44-C44,0) -> 0 | N44: =IF(H44>0,IF(I44>0,I44-H44,0),0) -> 0 | O44: =IF(J44>0,J44-I44,0) -> 0 | P44: =IF(J44>0,J44-C44,0) -> 0
B45: Julio | C45: 45128 | D45: Vicente Gómez de Olivera | E45: 3° | G45: NO | M45: =IF(H45>0,H45-C45,0) -> 0 | N45: =IF(H45>0,IF(I45>0,I45-H45,0),0) -> 0 | O45: =IF(J45>0,J45-I45,0) -> 0 | P45: =IF(J45>0,J45-C45,0) -> 0
B46: Julio | C46: 45128 | D46: Simón Duque Hoyos | E46: 1° | G46: SI | I46: 45146 | K46: Desisten del proceso | M46: =IF(H46>0,H46-C46,0) -> 0 | N46: =IF(H46>0,IF(I46>0,I46-H46,0),0) -> 0 | O46: =IF(J46>0,J46-I46,0) -> 0 | P46: =IF(J46>0,J46-C46,0) -> 0
B47: Julio | C47: 45135 | D47: Matías Orozco Mochón | E47: 3° | G47: NO | M47: =IF(H47>0,H47-C47,0) -> 0 | N47: =IF(H47>0,IF(I47>0,I47-H47,0),0) -> 0 | O47: =IF(J47>0,J47-I47,0) -> 0 | P47: =IF(J47>0,J47-C47,0) -> 0
B48: Julio | C48: 45135 | D48: Vicente Slawek García | E48: 3° | G48: NO | M48: =IF(H48>0,H48-C48,0) -> 0 | N48: =IF(H48>0,IF(I48>0,I48-H48,0),0) -> 0 | O48: =IF(J48>0,J48-I48,0) -> 0 | P48: =IF(J48>0,J48-C48,0) -> 0
B49: Julio | C49: 45135 | D49: Julia Slawek García | E49: 1° | G49: NO | M49: =IF(H49>0,H49-C49,0) -> 0 | N49: =IF(H49>0,IF(I49>0,I49-H49,0),0) -> 0 | O49: =IF(J49>0,J49-I49,0) -> 0 | P49: =IF(J49>0,J49-C49,0) -> 0
B50: Agosto | C50: 45155 | D50: María Isabel Alzate | E50: 5° | G50: SI | H50: 45156 | I50: 45238 | J50: 45306 | M50: =IF(H50>0,H50-C50,0) -> 1 | N50: =IF(H50>0,IF(I50>0,I50-H50,0),0) -> 82 | O50: =IF(J50>0,J50-I50,0) -> 68 | P50: =IF(J50>0,J50-C50,0) -> 151
B51: Agosto | C51: 45147 | D51: Jerónimo Ospina Correa | E51: 5° | G51: SI | H51: 45191 | I51: 45197 | J51: 45328 | M51: =IF(H51>0,H51-C51,0) -> 44 | N51: =IF(H51>0,IF(I51>0,I51-H51,0),0) -> 6 | O51: =IF(J51>0,J51-I51,0) -> 131 | P51: =IF(J51>0,J51-C51,0) -> 181
B52: Agosto | C52: 45147 | D52: Alicia Ospina Correa | E52: 4° | G52: SI | I52: 45197 | J52: 45328 | M52: =IF(H52>0,H52-C52,0) -> 0 | N52: =IF(H52>0,IF(I52>0,I52-H52,0),0) -> 0 | O52: =IF(J52>0,J52-I52,0) -> 131 | P52: =IF(J52>0,J52-C52,0) -> 181
B53: Agosto | C53: 45147 | D53: leticia Valencia | E53: 1° | G53: NO | M53: =IF(H53>0,H53-C53,0) -> 0 | N53: =IF(H53>0,IF(I53>0,I53-H53,0),0) -> 0 | O53: =IF(J53>0,J53-I53,0) -> 0 | P53: =IF(J53>0,J53-C53,0) -> 0
B54: Agosto | C54: 45147 | D54: Mía Cano | E54: 4° | G54: NO | M54: =IF(H54>0,H54-C54,0) -> 0 | N54: =IF(H54>0,IF(I54>0,I54-H54,0),0) -> 0 | O54: =IF(J54>0,J54-I54,0) -> 0 | P54: =IF(J54>0,J54-C54,0) -> 0
B55: Agosto | C55: 45147 | D55: Angelo Pellarin | E55: 1° | G55: NO | M55: =IF(H55>0,H55-C55,0) -> 0 | N55: =IF(H55>0,IF(I55>0,I55-H55,0),0) -> 0 | O55: =IF(J55>0,J55-I55,0) -> 0 | P55: =IF(J55>0,J55-C55,0) -> 0
B56: Agosto | C56: 45147 | D56: Camilo Sánchez Martinez | E56: 5° | G56: NO | M56: =IF(H56>0,H56-C56,0) -> 0 | N56: =IF(H56>0,IF(I56>0,I56-H56,0),0) -> 0 | O56: =IF(J56>0,J56-I56,0) -> 0 | P56: =IF(J56>0,J56-C56,0) -> 0
B57: Agosto | C57: 45147 | D57: Luna Sánchez Martinez | E57: 2° | G57: NO | M57: =IF(H57>0,H57-C57,0) -> 0 | N57: =IF(H57>0,IF(I57>0,I57-H57,0),0) -> 0 | O57: =IF(J57>0,J57-I57,0) -> 0 | P57: =IF(J57>0,J57-C57,0) -> 0
B58: Agosto | C58: 45147 | D58: Matías Guzmán Botero | E58: 4° | G58: SI | I58: 45188 | J58: 45205 | M58: =IF(H58>0,H58-C58,0) -> 0 | N58: =IF(H58>0,IF(I58>0,I58-H58,0),0) -> 0 | O58: =IF(J58>0,J58-I58,0) -> 17 | P58: =IF(J58>0,J58-C58,0) -> 58
B59: Agosto | C59: 45149 | D59: Julieta Díez | E59: 1° | G59: NO | M59: =IF(H59>0,H59-C59,0) -> 0 | N59: =IF(H59>0,IF(I59>0,I59-H59,0),0) -> 0 | O59: =IF(J59>0,J59-I59,0) -> 0 | P59: =IF(J59>0,J59-C59,0) -> 0
B60: Agosto | C60: 45149 | D60: Martín Lopera | E60: 5° | G60: NO | M60: =IF(H60>0,H60-C60,0) -> 0 | N60: =IF(H60>0,IF(I60>0,I60-H60,0),0) -> 0 | O60: =IF(J60>0,J60-I60,0) -> 0 | P60: =IF(J60>0,J60-C60,0) -> 0
B61: Agosto | C61: 45149 | D61: Cristóbal Lopera | E61: 3° | G61: NO | M61: =IF(H61>0,H61-C61,0) -> 0 | N61: =IF(H61>0,IF(I61>0,I61-H61,0),0) -> 0 | O61: =IF(J61>0,J61-I61,0) -> 0 | P61: =IF(J61>0,J61-C61,0) -> 0
B62: Agosto | C62: 45156 | D62: Amelia Robles | E62: 1° | G62: NO | M62: =IF(H62>0,H62-C62,0) -> 0 | N62: =IF(H62>0,IF(I62>0,I62-H62,0),0) -> 0 | O62: =IF(J62>0,J62-I62,0) -> 0 | P62: =IF(J62>0,J62-C62,0) -> 0
B63: Agosto | C63: 45156 | D63: María Antonia Quintero | E63: 3° | G63: NO | M63: =IF(H63>0,H63-C63,0) -> 0 | N63: =IF(H63>0,IF(I63>0,I63-H63,0),0) -> 0 | O63: =IF(J63>0,J63-I63,0) -> 0 | P63: =IF(J63>0,J63-C63,0) -> 0
B64: Agosto | C64: 45156 | D64: Luciana Quintero | E64: 1° | G64: NO | M64: =IF(H64>0,H64-C64,0) -> 0 | N64: =IF(H64>0,IF(I64>0,I64-H64,0),0) -> 0 | O64: =IF(J64>0,J64-I64,0) -> 0 | P64: =IF(J64>0,J64-C64,0) -> 0
B65: Agosto | C65: 45161 | D65: Gabriela Garcés | E65: 1° | G65: SI | I65: 45229 | K65: Desisten del proceso | M65: =IF(H65>0,H65-C65,0) -> 0 | N65: =IF(H65>0,IF(I65>0,I65-H65,0),0) -> 0 | O65: =IF(J65>0,J65-I65,0) -> 0 | P65: =IF(J65>0,J65-C65,0) -> 0
B66: Agosto | C66: 45161 | D66: Samanta Guzmán | E66: 4° | G66: NO | M66: =IF(H66>0,H66-C66,0) -> 0 | N66: =IF(H66>0,IF(I66>0,I66-H66,0),0) -> 0 | O66: =IF(J66>0,J66-I66,0) -> 0 | P66: =IF(J66>0,J66-C66,0) -> 0
B67: Septiembre | C67: 45175 | D67: Cristóbal Mejía | E67: 3° | G67: SI | I67: 45194 | K67: Desisten del proceso , estudiante fue admitido | M67: =IF(H67>0,H67-C67,0) -> 0 | N67: =IF(H67>0,IF(I67>0,I67-H67,0),0) -> 0 | O67: =IF(J67>0,J67-I67,0) -> 0 | P67: =IF(J67>0,J67-C67,0) -> 0
B68: Septiembre | C68: 45175 | D68: Pedro Arguella | E68: 5° | G68: NO | M68: =IF(H68>0,H68-C68,0) -> 0 | N68: =IF(H68>0,IF(I68>0,I68-H68,0),0) -> 0 | O68: =IF(J68>0,J68-I68,0) -> 0 | P68: =IF(J68>0,J68-C68,0) -> 0
B69: Septiembre | C69: 45196 | D69: Abril Posada | E69: 1° | G69: NO | M69: =IF(H69>0,H69-C69,0) -> 0 | N69: =IF(H69>0,IF(I69>0,I69-H69,0),0) -> 0 | O69: =IF(J69>0,J69-I69,0) -> 0 | P69: =IF(J69>0,J69-C69,0) -> 0
B70: Septiembre | C70: 45191 | D70: Maria del Mar Velásquez | E70: 4° | G70: NO | M70: =IF(H70>0,H70-C70,0) -> 0 | N70: =IF(H70>0,IF(I70>0,I70-H70,0),0) -> 0 | O70: =IF(J70>0,J70-I70,0) -> 0 | P70: =IF(J70>0,J70-C70,0) -> 0
B71: Septiembre | C71: 45191 | D71: Jerónimo López | E71: 1° | G71: NO | M71: =IF(H71>0,H71-C71,0) -> 0 | N71: =IF(H71>0,IF(I71>0,I71-H71,0),0) -> 0 | O71: =IF(J71>0,J71-I71,0) -> 0 | P71: =IF(J71>0,J71-C71,0) -> 0
B72: Septiembre | C72: 45191 | D72: María Victoria Pérez Salazar | E72: 2° | G72: NO | M72: =IF(H72>0,H72-C72,0) -> 0 | N72: =IF(H72>0,IF(I72>0,I72-H72,0),0) -> 0 | O72: =IF(J72>0,J72-I72,0) -> 0 | P72: =IF(J72>0,J72-C72,0) -> 0
B73: Septiembre | C73: 45198 | D73: Nicolás Castaño Correa | E73: 4° | G73: NO | M73: =IF(H73>0,H73-C73,0) -> 0 | N73: =IF(H73>0,IF(I73>0,I73-H73,0),0) -> 0 | O73: =IF(J73>0,J73-I73,0) -> 0 | P73: =IF(J73>0,J73-C73,0) -> 0
B74: Septiembre | C74: 45198 | D74: Samuel Lopera Salinas | E74: 1° | G74: NO | M74: =IF(H74>0,H74-C74,0) -> 0 | N74: =IF(H74>0,IF(I74>0,I74-H74,0),0) -> 0 | O74: =IF(J74>0,J74-I74,0) -> 0 | P74: =IF(J74>0,J74-C74,0) -> 0
B75: Septiembre | C75: 45198 | D75: Atenea Montoya Ospina | E75: 3° | G75: NO | M75: =IF(H75>0,H75-C75,0) -> 0 | N75: =IF(H75>0,IF(I75>0,I75-H75,0),0) -> 0 | O75: =IF(J75>0,J75-I75,0) -> 0 | P75: =IF(J75>0,J75-C75,0) -> 0
B76: Septiembre | C76: 45198 | D76: Matías Restrepo Osorio | E76: 4° | G76: NO | M76: =IF(H76>0,H76-C76,0) -> 0 | N76: =IF(H76>0,IF(I76>0,I76-H76,0),0) -> 0 | O76: =IF(J76>0,J76-I76,0) -> 0 | P76: =IF(J76>0,J76-C76,0) -> 0
B77: Septiembre | C77: 45198 | D77: Gabriel Ángel Palacio | E77: 4° | G77: NO | M77: =IF(H77>0,H77-C77,0) -> 0 | N77: =IF(H77>0,IF(I77>0,I77-H77,0),0) -> 0 | O77: =IF(J77>0,J77-I77,0) -> 0 | P77: =IF(J77>0,J77-C77,0) -> 0
B78: Octubre | C78: 45225 | D78: Francesco Salis | E78: 4° | G78: SI | I78: 45252 | K78: No admitido | M78: =IF(H78>0,H78-C78,0) -> 0 | N78: =IF(H78>0,IF(I78>0,I78-H78,0),0) -> 0 | O78: =IF(J78>0,J78-I78,0) -> 0 | P78: =IF(J78>0,J78-C78,0) -> 0
B79: Octubre | C79: 45226 | D79: Miguel Cardona Lara | E79: 5° | G79: SI | H79: 45231 | I79: 45245 | J79: 45306 | M79: =IF(H79>0,H79-C79,0) -> 5 | N79: =IF(H79>0,IF(I79>0,I79-H79,0),0) -> 14 | O79: =IF(J79>0,J79-I79,0) -> 61 | P79: =IF(J79>0,J79-C79,0) -> 80
B80: Octubre | C80: 45226 | D80: Agustín Sánchez Gómez | E80: 2° | G80: SI | I80: 45250 | K80: Desisten del proceso , cupo otro colegio | M80: =IF(H80>0,H80-C80,0) -> 0 | N80: =IF(H80>0,IF(I80>0,I80-H80,0),0) -> 0 | O80: =IF(J80>0,J80-I80,0) -> 0 | P80: =IF(J80>0,J80-C80,0) -> 0
B81: Octubre | C81: 45226 | D81: Alicia Restrepo | E81: 4° | G81: NO | M81: =IF(H81>0,H81-C81,0) -> 0 | N81: =IF(H81>0,IF(I81>0,I81-H81,0),0) -> 0 | O81: =IF(J81>0,J81-I81,0) -> 0 | P81: =IF(J81>0,J81-C81,0) -> 0
B82: Octubre | C82: 45226 | D82: Vicente Restrepo | E82: 1° | G82: NO | M82: =IF(H82>0,H82-C82,0) -> 0 | N82: =IF(H82>0,IF(I82>0,I82-H82,0),0) -> 0 | O82: =IF(J82>0,J82-I82,0) -> 0 | P82: =IF(J82>0,J82-C82,0) -> 0
B83: Octubre | C83: 45226 | D83: Federico Naranjo Gómez | E83: 1° | G83: NO | M83: =IF(H83>0,H83-C83,0) -> 0 | N83: =IF(H83>0,IF(I83>0,I83-H83,0),0) -> 0 | O83: =IF(J83>0,J83-I83,0) -> 0 | P83: =IF(J83>0,J83-C83,0) -> 0
B84: Octubre | C84: 45226 | D84: Luciana Camacho | E84: 5° | G84: NO | M84: =IF(H84>0,H84-C84,0) -> 0 | N84: =IF(H84>0,IF(I84>0,I84-H84,0),0) -> 0 | O84: =IF(J84>0,J84-I84,0) -> 0 | P84: =IF(J84>0,J84-C84,0) -> 0
B85: Octubre | C85: 45226 | D85: Thiago Mendez | E85: 1° | G85: NO | M85: =IF(H85>0,H85-C85,0) -> 0 | N85: =IF(H85>0,IF(I85>0,I85-H85,0),0) -> 0 | O85: =IF(J85>0,J85-I85,0) -> 0 | P85: =IF(J85>0,J85-C85,0) -> 0
B86: Noviembre | C86: 45232 | D86: Juliana Arismendy Santoya | E86: 5° | G86: NO | M86: =IF(H86>0,H86-C86,0) -> 0 | N86: =IF(H86>0,IF(I86>0,I86-H86,0),0) -> 0 | O86: =IF(J86>0,J86-I86,0) -> 0 | P86: =IF(J86>0,J86-C86,0) -> 0
B87: Noviembre | C87: 45240 | D87: Eloísa leal Salazar | E87: 2° | G87: SI | I87: 45488 | J87: 45496 | K87: Proceso 2024 | M87: =IF(H87>0,H87-C87,0) -> 0 | N87: =IF(H87>0,IF(I87>0,I87-H87,0),0) -> 0 | O87: =IF(J87>0,J87-I87,0) -> 8 | P87: =IF(J87>0,J87-C87,0) -> 256
B88: Noviembre | C88: 45240 | D88: Susana Montoya Cortés | E88: 3° | G88: SI | I88: 45250 | J88: 45306 | M88: =IF(H88>0,H88-C88,0) -> 0 | N88: =IF(H88>0,IF(I88>0,I88-H88,0),0) -> 0 | O88: =IF(J88>0,J88-I88,0) -> 56 | P88: =IF(J88>0,J88-C88,0) -> 66
B89: Noviembre | C89: 45240 | D89: Camila Álvarez Frasser | E89: 2° | G89: SI | I89: 45306 | K89: No admitida | M89: =IF(H89>0,H89-C89,0) -> 0 | N89: =IF(H89>0,IF(I89>0,I89-H89,0),0) -> 0 | O89: =IF(J89>0,J89-I89,0) -> 0 | P89: =IF(J89>0,J89-C89,0) -> 0
B90: Noviembre | C90: 45240 | D90: Maximiliano Gómez Meneses | E90: 2° | G90: NO | M90: =IF(H90>0,H90-C90,0) -> 0 | N90: =IF(H90>0,IF(I90>0,I90-H90,0),0) -> 0 | O90: =IF(J90>0,J90-I90,0) -> 0 | P90: =IF(J90>0,J90-C90,0) -> 0
B91: Noviembre | C91: 45247 | D91: Nicolás Di Santo | E91: 1° | G91: SI | I91: 45308 | J91: 45328 | M91: =IF(H91>0,H91-C91,0) -> 0 | N91: =IF(H91>0,IF(I91>0,I91-H91,0),0) -> 0 | O91: =IF(J91>0,J91-I91,0) -> 20 | P91: =IF(J91>0,J91-C91,0) -> 81
B92: Noviembre | C92: 45247 | D92: Alejandro Garcés | E92: 3° | G92: NO | M92: =IF(H92>0,H92-C92,0) -> 0 | N92: =IF(H92>0,IF(I92>0,I92-H92,0),0) -> 0 | O92: =IF(J92>0,J92-I92,0) -> 0 | P92: =IF(J92>0,J92-C92,0) -> 0
B93: Noviembre | C93: 45247 | D93: Julieta Zapata | E93: 1° | G93: NO | M93: =IF(H93>0,H93-C93,0) -> 0 | N93: =IF(H93>0,IF(I93>0,I93-H93,0),0) -> 0 | O93: =IF(J93>0,J93-I93,0) -> 0 | P93: =IF(J93>0,J93-C93,0) -> 0
B94: Noviembre | C94: 45247 | D94: Mateo Zapata | E94: 3° | G94: NO | M94: =IF(H94>0,H94-C94,0) -> 0 | N94: =IF(H94>0,IF(I94>0,I94-H94,0),0) -> 0 | O94: =IF(J94>0,J94-I94,0) -> 0 | P94: =IF(J94>0,J94-C94,0) -> 0
B95: Noviembre | C95: 45252 | D95: Marcelo Rossetti Vélez | E95: 3° | G95: SI | I95: 45383 | J95: 45484 | M95: =IF(H95>0,H95-C95,0) -> 0 | N95: =IF(H95>0,IF(I95>0,I95-H95,0),0) -> 0 | O95: =IF(J95>0,J95-I95,0) -> 101 | P95: =IF(J95>0,J95-C95,0) -> 232
B96: Noviembre | C96: 45252 | D96: Pedro Montes | E96: 5° | G96: NO | M96: =IF(H96>0,H96-C96,0) -> 0 | N96: =IF(H96>0,IF(I96>0,I96-H96,0),0) -> 0 | O96: =IF(J96>0,J96-I96,0) -> 0 | P96: =IF(J96>0,J96-C96,0) -> 0
B97: Noviembre | C97: 45252 | D97: Cristóbal Pérez | E97: 1° | G97: NO | M97: =IF(H97>0,H97-C97,0) -> 0 | N97: =IF(H97>0,IF(I97>0,I97-H97,0),0) -> 0 | O97: =IF(J97>0,J97-I97,0) -> 0 | P97: =IF(J97>0,J97-C97,0) -> 0
B98: Noviembre | C98: 45252 | D98: Miguel Vélez | E98: 1° | G98: NO | M98: =IF(H98>0,H98-C98,0) -> 0 | N98: =IF(H98>0,IF(I98>0,I98-H98,0),0) -> 0 | O98: =IF(J98>0,J98-I98,0) -> 0 | P98: =IF(J98>0,J98-C98,0) -> 0
B99: Diciembre | C99: 45266 | D99: Paloma Villegas Mejía | E99: 2° | G99: SI | I99: 45589 | J99: 45672 | M99: =IF(H99>0,H99-C99,0) -> 0 | N99: =IF(H99>0,IF(I99>0,I99-H99,0),0) -> 0 | O99: =IF(J99>0,J99-I99,0) -> 83 | P99: =IF(J99>0,J99-C99,0) -> 406
B100: Diciembre | C100: 45266 | D100: Samuel Villegas Mejía | E100: 5° | G100: SI | H100: 45580 | I100: 45589 | J100: 45672 | M100: =IF(H100>0,H100-C100,0) -> 314 | N100: =IF(H100>0,IF(I100>0,I100-H100,0),0) -> 9 | O100: =IF(J100>0,J100-I100,0) -> 83 | P100: =IF(J100>0,J100-C100,0) -> 406
...

Sheet Datos Bachillerato
B1: Mes | C1: Día | D1: Estudiante | E1: Grado | F1: Como conoció el colegio | G1: Inicio proceso | H1: Pruebas | I1: Observación | J1: Matricula | K1: Estado del proceso | L1: Observaciones | M1: Días entre cita de info e inicio de pruebas | N1: Días entre pruebas y observa | O1: Días entre inici de observa y matrícula | P1: Días entre cita de info y matrícula | Q1: =AVERAGEIF(M2:M901,">0",M2:M901) -> 36.258741 | R1: =AVERAGEIF(N2:N901,">0",N2:N901) -> 27.963964 | S1: =AVERAGEIF(O2:O901,">0",O2:O901) -> 43.215385 | T1: =AVERAGEIF(P2:P901,">0",P2:P901) -> 109.84615
B2: Enero | C2: 44938 | D2: Gabriela Rodríguez | E2: 8° | G2: SI | H2: 44945 | M2: =IF(H2>0,H2-C2,0) -> 7 | N2: =IF(I2>0,I2-H2,0) -> 0 | O2: =IF(J2>0,J2-I2,0) -> 0 | P2: =IF(J2>0,J2-C2,0) -> 0
B3: Enero | C3: 44938 | D3: Maria Clara Suárez | E3: 11° | G3: SI | H3: 44943 | I3: 44956 | J3: 44980 | M3: =IF(H3>0,H3-C3,0) -> 5 | N3: =IF(I3>0,I3-H3,0) -> 13 | O3: =IF(J3>0,J3-I3,0) -> 24 | P3: =IF(J3>0,J3-C3,0) -> 42
B4: Enero | C4: 44938 | D4: Esteban Yepes Franco | E4: 9° | G4: SI | H4: 44942 | I4: 44950 | M4: =IF(H4>0,H4-C4,0) -> 4 | N4: =IF(I4>0,I4-H4,0) -> 8 | O4: =IF(J4>0,J4-I4,0) -> 0 | P4: =IF(J4>0,J4-C4,0) -> 0
B5: Enero | C5: 44938 | D5: Jerónimo Ospina Palacio | E5: 8° | G5: SI | H5: 44942 | I5: 44977 | K5: No admitido | M5: =IF(H5>0,H5-C5,0) -> 4 | N5: =IF(I5>0,I5-H5,0) -> 35 | O5: =IF(J5>0,J5-I5,0) -> 0 | P5: =IF(J5>0,J5-C5,0) -> 0
B6: Enero | C6: 44938 | D6: Alegra Aponte Montoya | E6: 6° | G6: SI | H6: 44945 | I6: 44957 | J6: 44970 | M6: =IF(H6>0,H6-C6,0) -> 7 | N6: =IF(I6>0,I6-H6,0) -> 12 | O6: =IF(J6>0,J6-I6,0) -> 13 | P6: =IF(J6>0,J6-C6,0) -> 32
B7: Enero | C7: 44938 | D7: Jerónimo Gómez Moncada | E7: 6° | G7: NO | M7: =IF(H7>0,H7-C7,0) -> 0 | N7: =IF(I7>0,I7-H7,0) -> 0 | O7: =IF(J7>0,J7-I7,0) -> 0 | P7: =IF(J7>0,J7-C7,0) -> 0
B8: Enero | C8: 44938 | D8: Maria José Tapasco Quintero | E8: 7° | G8: NO | M8: =IF(H8>0,H8-C8,0) -> 0 | N8: =IF(I8>0,I8-H8,0) -> 0 | O8: =IF(J8>0,J8-I8,0) -> 0 | P8: =IF(J8>0,J8-C8,0) -> 0
B9: Enero | C9: 44945 | D9: Sasha Figueroa | E9: 11° | G9: SI | H9: 44953 | I9: 44957 | K9: No admitido | M9: =IF(H9>0,H9-C9,0) -> 8 | N9: =IF(I9>0,I9-H9,0) -> 4 | O9: =IF(J9>0,J9-I9,0) -> 0 | P9: =IF(J9>0,J9-C9,0) -> 0
B10: Enero | C10: 44945 | D10: Matias Vallejo Aguilera | E10: 7° | G10: SI | H10: 44949 | I10: 44970 | J10: 45006 | M10: =IF(H10>0,H10-C10,0) -> 4 | N10: =IF(I10>0,I10-H10,0) -> 21 | O10: =IF(J10>0,J10-I10,0) -> 36 | P10: =IF(J10>0,J10-C10,0) -> 61
B11: Enero | C11: 44945 | D11: Gabriela Patiño Sánchez | E11: 7° | G11: SI | H11: 44950 | I11: 44959 | J11: 44971 | M11: =IF(H11>0,H11-C11,0) -> 5 | N11: =IF(I11>0,I11-H11,0) -> 9 | O11: =IF(J11>0,J11-I11,0) -> 12 | P11: =IF(J11>0,J11-C11,0) -> 26
B12: Enero | C12: 44945 | D12: Alejandro Rojas Montes | E12: 11° | G12: NO | M12: =IF(H12>0,H12-C12,0) -> 0 | N12: =IF(I12>0,I12-H12,0) -> 0 | O12: =IF(J12>0,J12-I12,0) -> 0 | P12: =IF(J12>0,J12-C12,0) -> 0
B13: Enero | C13: 44945 | D13: Antonella Valencia | E13: 9° | G13: NO | M13: =IF(H13>0,H13-C13,0) -> 0 | N13: =IF(I13>0,I13-H13,0) -> 0 | O13: =IF(J13>0,J13-I13,0) -> 0 | P13: =IF(J13>0,J13-C13,0) -> 0
B14: Enero | C14: 44945 | D14: Maria Camila Díaz | E14: 8° | G14: SI | H14: 44945 | I14: 44963 | M14: =IF(H14>0,H14-C14,0) -> 0 | N14: =IF(I14>0,I14-H14,0) -> 18 | O14: =IF(J14>0,J14-I14,0) -> 0 | P14: =IF(J14>0,J14-C14,0) -> 0
B15: Enero | C15: 44945 | D15: luciana Restrepo Walker | E15: 10° | G15: SI | H15: 44945 | I15: 44994 | K15: No admitida | M15: =IF(H15>0,H15-C15,0) -> 0 | N15: =IF(I15>0,I15-H15,0) -> 49 | O15: =IF(J15>0,J15-I15,0) -> 0 | P15: =IF(J15>0,J15-C15,0) -> 0
B16: Enero | C16: 44945 | D16: Maria Valentina Muñoz Muñoz | E16: 10° | G16: NO | M16: =IF(H16>0,H16-C16,0) -> 0 | N16: =IF(I16>0,I16-H16,0) -> 0 | O16: =IF(J16>0,J16-I16,0) -> 0 | P16: =IF(J16>0,J16-C16,0) -> 0
B17: Enero | C17: 44945 | D17: Enrique Braidy | E17: 7° | G17: NO | M17: =IF(H17>0,H17-C17,0) -> 0 | N17: =IF(I17>0,I17-H17,0) -> 0 | O17: =IF(J17>0,J17-I17,0) -> 0 | P17: =IF(J17>0,J17-C17,0) -> 0
B18: Enero | C18: 44952 | D18: Pedro Juan Cespedes | E18: 8° | G18: NO | M18: =IF(H18>0,H18-C18,0) -> 0 | N18: =IF(I18>0,I18-H18,0) -> 0 | O18: =IF(J18>0,J18-I18,0) -> 0 | P18: =IF(J18>0,J18-C18,0) -> 0
B19: Enero | C19: 44952 | D19: Amalia Jimenez Sanin | E19: 6° | G19: NO | M19: =IF(H19>0,H19-C19,0) -> 0 | N19: =IF(I19>0,I19-H19,0) -> 0 | O19: =IF(J19>0,J19-I19,0) -> 0 | P19: =IF(J19>0,J19-C19,0) -> 0
B20: Febrero | C20: 44959 | D20: María José Marulanda Fiscó | E20: 8° | G20: NO | M20: =IF(H20>0,H20-C20,0) -> 0 | N20: =IF(I20>0,I20-H20,0) -> 0 | O20: =IF(J20>0,J20-I20,0) -> 0 | P20: =IF(J20>0,J20-C20,0) -> 0
B21: Febrero | C21: 44959 | D21: Manuel Torres | E21: 9° | G21: NO | M21: =IF(H21>0,H21-C21,0) -> 0 | N21: =IF(I21>0,I21-H21,0) -> 0 | O21: =IF(J21>0,J21-I21,0) -> 0 | P21: =IF(J21>0,J21-C21,0) -> 0
B22: Febrero | C22: 44959 | D22: Andrea Carolina Verbel | E22: 10° | G22: NO | M22: =IF(H22>0,H22-C22,0) -> 0 | N22: =IF(I22>0,I22-H22,0) -> 0 | O22: =IF(J22>0,J22-I22,0) -> 0 | P22: =IF(J22>0,J22-C22,0) -> 0
B23: Febrero | C23: 44959 | D23: Manuela Velez olarte | E23: 8° | G23: NO | M23: =IF(H23>0,H23-C23,0) -> 0 | N23: =IF(I23>0,I23-H23,0) -> 0 | O23: =IF(J23>0,J23-I23,0) -> 0 | P23: =IF(J23>0,J23-C23,0) -> 0
B24: Febrero | C24: 44959 | D24: Martina Velez olarte | E24: 6° | G24: NO | M24: =IF(H24>0,H24-C24,0) -> 0 | N24: =IF(I24>0,I24-H24,0) -> 0 | O24: =IF(J24>0,J24-I24,0) -> 0 | P24: =IF(J24>0,J24-C24,0) -> 0
B25: Febrero | C25: 44966 | D25: Daniel Vélez | E25: 10° | G25: NO | M25: =IF(H25>0,H25-C25,0) -> 0 | N25: =IF(I25>0,I25-H25,0) -> 0 | O25: =IF(J25>0,J25-I25,0) -> 0 | P25: =IF(J25>0,J25-C25,0) -> 0
B26: Febrero | C26: 44966 | D26: Matías López | E26: 6° | G26: NO | M26: =IF(H26>0,H26-C26,0) -> 0 | N26: =IF(I26>0,I26-H26,0) -> 0 | O26: =IF(J26>0,J26-I26,0) -> 0 | P26: =IF(J26>0,J26-C26,0) -> 0
B27: Febrero | C27: 44966 | D27: Isabel Restrepo Botero | E27: 6° | G27: SI | H27: 44966 | I27: 44991 | J27: 45146 | M27: =IF(H27>0,H27-C27,0) -> 0 | N27: =IF(I27>0,I27-H27,0) -> 25 | O27: =IF(J27>0,J27-I27,0) -> 155 | P27: =IF(J27>0,J27-C27,0) -> 180
B28: Febrero | C28: 44966 | D28: Miguel SantaMaria Valencia | E28: 10° | G28: NO | M28: =IF(H28>0,H28-C28,0) -> 0 | N28: =IF(I28>0,I28-H28,0) -> 0 | O28: =IF(J28>0,J28-I28,0) -> 0 | P28: =IF(J28>0,J28-C28,0) -> 0
B29: Febrero | C29: 44973 | D29: Ahinoa Rondon | E29: 6° | G29: SI | H29: 44986 | I29: 44999 | J29: 45013 | M29: =IF(H29>0,H29-C29,0) -> 13 | N29: =IF(I29>0,I29-H29,0) -> 13 | O29: =IF(J29>0,J29-I29,0) -> 14 | P29: =IF(J29>0,J29-C29,0) -> 40
B30: Febrero | C30: 44973 | D30: Juan Pablo caraballo | E30: 10° | G30: SI | H30: 44978 | I30: 45026 | J30: 45050 | M30: =IF(H30>0,H30-C30,0) -> 5 | N30: =IF(I30>0,I30-H30,0) -> 48 | O30: =IF(J30>0,J30-I30,0) -> 24 | P30: =IF(J30>0,J30-C30,0) -> 77
B31: Febrero | C31: 44973 | D31: Sofia Molina Hoyos | E31: 8° | G31: NO | M31: =IF(H31>0,H31-C31,0) -> 0 | N31: =IF(I31>0,I31-H31,0) -> 0 | O31: =IF(J31>0,J31-I31,0) -> 0 | P31: =IF(J31>0,J31-C31,0) -> 0
B32: Febrero | C32: 44980 | D32: Juan Sebastián Serna Guarin | E32: 10° | G32: SI | H32: 44984 | M32: =IF(H32>0,H32-C32,0) -> 4 | N32: =IF(I32>0,I32-H32,0) -> 0 | O32: =IF(J32>0,J32-I32,0) -> 0 | P32: =IF(J32>0,J32-C32,0) -> 0
B33: Febrero | C33: 44980 | D33: Ian Dicson Salazar | E33: 8° | G33: NO | M33: =IF(H33>0,H33-C33,0) -> 0 | N33: =IF(I33>0,I33-H33,0) -> 0 | O33: =IF(J33>0,J33-I33,0) -> 0 | P33: =IF(J33>0,J33-C33,0) -> 0
B34: Febrero | C34: 44980 | D34: Juan Jacobo García Montoya | E34: 6° | G34: NO | M34: =IF(H34>0,H34-C34,0) -> 0 | N34: =IF(I34>0,I34-H34,0) -> 0 | O34: =IF(J34>0,J34-I34,0) -> 0 | P34: =IF(J34>0,J34-C34,0) -> 0
B35: Febrero | C35: 44980 | D35: Valerio Yafreda | E35: 7° | G35: NO | M35: =IF(H35>0,H35-C35,0) -> 0 | N35: =IF(I35>0,I35-H35,0) -> 0 | O35: =IF(J35>0,J35-I35,0) -> 0 | P35: =IF(J35>0,J35-C35,0) -> 0
B36: Marzo | C36: 44987 | D36: Samuel espitia Cardozo | E36: 8° | G36: NO | M36: =IF(H36>0,H36-C36,0) -> 0 | N36: =IF(I36>0,I36-H36,0) -> 0 | O36: =IF(J36>0,J36-I36,0) -> 0 | P36: =IF(J36>0,J36-C36,0) -> 0
B37: Marzo | C37: 44987 | D37: Emilio Vásquez Yepes | E37: 11° | G37: SI | H37: 44992 | M37: =IF(H37>0,H37-C37,0) -> 5 | N37: =IF(I37>0,I37-H37,0) -> 0 | O37: =IF(J37>0,J37-I37,0) -> 0 | P37: =IF(J37>0,J37-C37,0) -> 0
B38: Marzo | C38: 44987 | D38: Juan Sebastian Pulgarín | E38: 9° | G38: SI | H38: 45143 | I38: 45313 | K38: No admitido | M38: =IF(H38>0,H38-C38,0) -> 156 | N38: =IF(I38>0,I38-H38,0) -> 170 | O38: =IF(J38>0,J38-I38,0) -> 0 | P38: =IF(J38>0,J38-C38,0) -> 0
B39: Marzo | C39: 44994 | D39: Simón Aguirre | E39: 7° | G39: NO | M39: =IF(H39>0,H39-C39,0) -> 0 | N39: =IF(I39>0,I39-H39,0) -> 0 | O39: =IF(J39>0,J39-I39,0) -> 0 | P39: =IF(J39>0,J39-C39,0) -> 0
B40: Marzo | C40: 44994 | D40: Angelina Wengert | E40: 10° | G40: NO | M40: =IF(H40>0,H40-C40,0) -> 0 | N40: =IF(I40>0,I40-H40,0) -> 0 | O40: =IF(J40>0,J40-I40,0) -> 0 | P40: =IF(J40>0,J40-C40,0) -> 0
B41: Marzo | C41: 44994 | D41: Simon Gaviria Correa | E41: 8° | G41: NO | M41: =IF(H41>0,H41-C41,0) -> 0 | N41: =IF(I41>0,I41-H41,0) -> 0 | O41: =IF(J41>0,J41-I41,0) -> 0 | P41: =IF(J41>0,J41-C41,0) -> 0
B42: Marzo | C42: 44994 | D42: Sofía Loaiza Aguirre | E42: 7° | G42: NO | M42: =IF(H42>0,H42-C42,0) -> 0 | N42: =IF(I42>0,I42-H42,0) -> 0 | O42: =IF(J42>0,J42-I42,0) -> 0 | P42: =IF(J42>0,J42-C42,0) -> 0
B43: Marzo | C43: 45001 | D43: Samuel Rojas Londoño | E43: 9° | G43: SI | H43: 45006 | K43: No admitido a pasantía (se le recomienda flex) | M43: =IF(H43>0,H43-C43,0) -> 5 | N43: =IF(I43>0,I43-H43,0) -> 0 | O43: =IF(J43>0,J43-I43,0) -> 0 | P43: =IF(J43>0,J43-C43,0) -> 0
B44: Marzo | C44: 45001 | D44: Alejandro Ramirez del Castillo | E44: 11° | G44: SI | H44: 45009 | I44: 45054 | J44: 45075 | M44: =IF(H44>0,H44-C44,0) -> 8 | N44: =IF(I44>0,I44-H44,0) -> 45 | O44: =IF(J44>0,J44-I44,0) -> 21 | P44: =IF(J44>0,J44-C44,0) -> 74
B45: Marzo | C45: 45001 | D45: Sofia Restrepo Gómez | E45: 10° | G45: SI | H45: 45002 | I45: 45012 | J45: 45036 | M45: =IF(H45>0,H45-C45,0) -> 1 | N45: =IF(I45>0,I45-H45,0) -> 10 | O45: =IF(J45>0,J45-I45,0) -> 24 | P45: =IF(J45>0,J45-C45,0) -> 35
B46: Marzo | C46: 45001 | D46: Santiago Olarte Ortiz | E46: 6° | G46: NO | M46: =IF(H46>0,H46-C46,0) -> 0 | N46: =IF(I46>0,I46-H46,0) -> 0 | O46: =IF(J46>0,J46-I46,0) -> 0 | P46: =IF(J46>0,J46-C46,0) -> 0
B47: Marzo | C47: 45008 | D47: Emiliana Castrillon Tobon | E47: 8° | G47: SI | H47: 45491 | I47: 45502 | K47: Desiste del proceso | M47: =IF(H47>0,H47-C47,0) -> 483 | N47: =IF(I47>0,I47-H47,0) -> 11 | O47: =IF(J47>0,J47-I47,0) -> 0 | P47: =IF(J47>0,J47-C47,0) -> 0
B48: Marzo | C48: 45015 | D48: Juan Felipe Velásquez Buelvas | E48: 11° | G48: SI | H48: 45033 | I48: 45048 | J48: 45083 | M48: =IF(H48>0,H48-C48,0) -> 18 | N48: =IF(I48>0,I48-H48,0) -> 15 | O48: =IF(J48>0,J48-I48,0) -> 35 | P48: =IF(J48>0,J48-C48,0) -> 68
B49: Marzo | C49: 45015 | D49: Sofía Arango Escobar | E49: 6° | G49: NO | M49: =IF(H49>0,H49-C49,0) -> 0 | N49: =IF(I49>0,I49-H49,0) -> 0 | O49: =IF(J49>0,J49-I49,0) -> 0 | P49: =IF(J49>0,J49-C49,0) -> 0
B50: Abril | C50: 45029 | D50: Luisa Saldarriaga Saldarriaga | E50: 7° | G50: SI | H50: 45033 | K50: No admitida | M50: =IF(H50>0,H50-C50,0) -> 4 | N50: =IF(I50>0,I50-H50,0) -> 0 | O50: =IF(J50>0,J50-I50,0) -> 0 | P50: =IF(J50>0,J50-C50,0) -> 0
B51: Abril | C51: 45029 | D51: Matías Osorio Ramírez | E51: 7° | G51: SI | H51: 45049 | I51: 45071 | J51: 45113 | M51: =IF(H51>0,H51-C51,0) -> 20 | N51: =IF(I51>0,I51-H51,0) -> 22 | O51: =IF(J51>0,J51-I51,0) -> 42 | P51: =IF(J51>0,J51-C51,0) -> 84
B52: Abril | C52: 45029 | D52: Candelaria Correa Vargas | E52: 8° | G52: SI | H52: 45033 | I52: 45054 | K52: No admitida | M52: =IF(H52>0,H52-C52,0) -> 4 | N52: =IF(I52>0,I52-H52,0) -> 21 | O52: =IF(J52>0,J52-I52,0) -> 0 | P52: =IF(J52>0,J52-C52,0) -> 0
B53: Abril | C53: 45029 | D53: Jacobo García Tobón | E53: 8° | G53: NO | M53: =IF(H53>0,H53-C53,0) -> 0 | N53: =IF(I53>0,I53-H53,0) -> 0 | O53: =IF(J53>0,J53-I53,0) -> 0 | P53: =IF(J53>0,J53-C53,0) -> 0
B54: Abril | C54: 45030 | D54: Valentina Ramírez | E54: 7° | G54: NO | M54: =IF(H54>0,H54-C54,0) -> 0 | N54: =IF(I54>0,I54-H54,0) -> 0 | O54: =IF(J54>0,J54-I54,0) -> 0 | P54: =IF(J54>0,J54-C54,0) -> 0
B55: Abril | C55: 45036 | D55: Luis Felipe Agudelo Chalarca | E55: 10° | G55: SI | H55: 45044 | K55: Solo hizo pruebas | M55: =IF(H55>0,H55-C55,0) -> 8 | N55: =IF(I55>0,I55-H55,0) -> 0 | O55: =IF(J55>0,J55-I55,0) -> 0 | P55: =IF(J55>0,J55-C55,0) -> 0
B56: Abril | C56: 45036 | D56: Elena Vesga Lotero | E56: 6° | G56: NO | M56: =IF(H56>0,H56-C56,0) -> 0 | N56: =IF(I56>0,I56-H56,0) -> 0 | O56: =IF(J56>0,J56-I56,0) -> 0 | P56: =IF(J56>0,J56-C56,0) -> 0
B57: Abril | C57: 45036 | D57: Matías Fournier Sarmiento | E57: 6° | G57: NO | M57: =IF(H57>0,H57-C57,0) -> 0 | N57: =IF(I57>0,I57-H57,0) -> 0 | O57: =IF(J57>0,J57-I57,0) -> 0 | P57: =IF(J57>0,J57-C57,0) -> 0
B58: Mayo | C58: 45050 | D58: Isabella Arrázola | E58: 8° | G58: SI | H58: 45064 | K58: No desea continuar el proceso | M58: =IF(H58>0,H58-C58,0) -> 14 | N58: =IF(I58>0,I58-H58,0) -> 0 | O58: =IF(J58>0,J58-I58,0) -> 0 | P58: =IF(J58>0,J58-C58,0) -> 0
B59: Mayo | C59: 45050 | D59: Miranda Garnica | E59: 7° | G59: SI | H59: 45062 | I59: 45117 | J59: 45138 | K59: Matricula | M59: =IF(H59>0,H59-C59,0) -> 12 | N59: =IF(I59>0,I59-H59,0) -> 55 | O59: =IF(J59>0,J59-I59,0) -> 21 | P59: =IF(J59>0,J59-C59,0) -> 88
B60: Mayo | C60: 45050 | D60: Antonio Escobar | E60: 6° | G60: NO | M60: =IF(H60>0,H60-C60,0) -> 0 | N60: =IF(I60>0,I60-H60,0) -> 0 | O60: =IF(J60>0,J60-I60,0) -> 0 | P60: =IF(J60>0,J60-C60,0) -> 0
B61: Mayo | C61: 45050 | D61: Thomas Otálvaro Londoño | E61: 11° | G61: SI | H61: 45181 | I61: 45237 | J61: 45264 | K61: Matricula | M61: =IF(H61>0,H61-C61,0) -> 131 | N61: =IF(I61>0,I61-H61,0) -> 56 | O61: =IF(J61>0,J61-I61,0) -> 27 | P61: =IF(J61>0,J61-C61,0) -> 214
B62: Mayo | C62: 45057 | D62: Miguel Tobón Restrepo | E62: 7° | G62: NO | M62: =IF(H62>0,H62-C62,0) -> 0 | N62: =IF(I62>0,I62-H62,0) -> 0 | O62: =IF(J62>0,J62-I62,0) -> 0 | P62: =IF(J62>0,J62-C62,0) -> 0
B63: Mayo | C63: 45057 | D63: Isabella Cortés Puerta | E63: 8° | G63: NO | M63: =IF(H63>0,H63-C63,0) -> 0 | N63: =IF(I63>0,I63-H63,0) -> 0 | O63: =IF(J63>0,J63-I63,0) -> 0 | P63: =IF(J63>0,J63-C63,0) -> 0
B64: Mayo | C64: 45057 | D64: Lorenzo Sánchez Builes | E64: 8° | G64: NO | M64: =IF(H64>0,H64-C64,0) -> 0 | N64: =IF(I64>0,I64-H64,0) -> 0 | O64: =IF(J64>0,J64-I64,0) -> 0 | P64: =IF(J64>0,J64-C64,0) -> 0
B65: Mayo | C65: 45057 | D65: Nicolás Labrador Medina | E65: 7° | G65: SI | H65: 45083 | I65: 45084 | J65: 45139 | K65: Matricula | M65: =IF(H65>0,H65-C65,0) -> 26 | N65: =IF(I65>0,I65-H65,0) -> 1 | O65: =IF(J65>0,J65-I65,0) -> 55 | P65: =IF(J65>0,J65-C65,0) -> 82
B66: Mayo | C66: 45057 | D66: Nicolás Buitrago Gaviria | E66: 7° | G66: NO | M66: =IF(H66>0,H66-C66,0) -> 0 | N66: =IF(I66>0,I66-H66,0) -> 0 | O66: =IF(J66>0,J66-I66,0) -> 0 | P66: =IF(J66>0,J66-C66,0) -> 0
B67: Mayo | C67: 45064 | D67: Emiliana Chejne Posada | E67: 7° | G67: NO | M67: =IF(H67>0,H67-C67,0) -> 0 | N67: =IF(I67>0,I67-H67,0) -> 0 | O67: =IF(J67>0,J67-I67,0) -> 0 | P67: =IF(J67>0,J67-C67,0) -> 0
B68: Mayo | C68: 45064 | D68: Samuel García Castaño | E68: 9° | G68: SI | H68: 45113 | I68: 45141 | K68: Desiste del proceso | M68: =IF(H68>0,H68-C68,0) -> 49 | N68: =IF(I68>0,I68-H68,0) -> 28 | O68: =IF(J68>0,J68-I68,0) -> 0 | P68: =IF(J68>0,J68-C68,0) -> 0
B69: Mayo | C69: 45064 | D69: Sofía Jaramillo Noriega | E69: 11° | G69: SI | H69: 45075 | I69: 45082 | J69: 45153 | K69: Matricula | M69: =IF(H69>0,H69-C69,0) -> 11 | N69: =IF(I69>0,I69-H69,0) -> 7 | O69: =IF(J69>0,J69-I69,0) -> 71 | P69: =IF(J69>0,J69-C69,0) -> 89
B70: Mayo | C70: 45064 | D70: Juan Martín Patiño Arcila | E70: 6° | G70: NO | M70: =IF(H70>0,H70-C70,0) -> 0 | N70: =IF(I70>0,I70-H70,0) -> 0 | O70: =IF(J70>0,J70-I70,0) -> 0 | P70: =IF(J70>0,J70-C70,0) -> 0
B71: Junio | C71: 45078 | D71: Emiliano Castro Maldonado | E71: 6° | G71: SI | H71: 45078 | I71: 45090 | K71: No admitido | M71: =IF(H71>0,H71-C71,0) -> 0 | N71: =IF(I71>0,I71-H71,0) -> 12 | O71: =IF(J71>0,J71-I71,0) -> 0 | P71: =IF(J71>0,J71-C71,0) -> 0
B72: Junio | C72: 45078 | D72: Samuel Toro Ochoa | E72: 8° | G72: NO | M72: =IF(H72>0,H72-C72,0) -> 0 | N72: =IF(I72>0,I72-H72,0) -> 0 | O72: =IF(J72>0,J72-I72,0) -> 0 | P72: =IF(J72>0,J72-C72,0) -> 0
B73: Junio | C73: 45078 | D73: María José Villa Herrera | E73: 6° | G73: NO | M73: =IF(H73>0,H73-C73,0) -> 0 | N73: =IF(I73>0,I73-H73,0) -> 0 | O73: =IF(J73>0,J73-I73,0) -> 0 | P73: =IF(J73>0,J73-C73,0) -> 0
B74: Junio | C74: 45071 | D74: Juan José Cardona Vargas | E74: 8° | G74: SI | H74: 45072 | I74: 45124 | J74: 45149 | K74: Matricula | M74: =IF(H74>0,H74-C74,0) -> 1 | N74: =IF(I74>0,I74-H74,0) -> 52 | O74: =IF(J74>0,J74-I74,0) -> 25 | P74: =IF(J74>0,J74-C74,0) -> 78
B75: Junio | C75: 45078 | D75: Samuel Roldán Posada | E75: 9° | G75: NO | M75: =IF(H75>0,H75-C75,0) -> 0 | N75: =IF(I75>0,I75-H75,0) -> 0 | O75: =IF(J75>0,J75-I75,0) -> 0 | P75: =IF(J75>0,J75-C75,0) -> 0
B76: Junio | C76: 45085 | D76: Amalia Vera Botero | E76: 7° | G76: NO | M76: =IF(H76>0,H76-C76,0) -> 0 | N76: =IF(I76>0,I76-H76,0) -> 0 | O76: =IF(J76>0,J76-I76,0) -> 0 | P76: =IF(J76>0,J76-C76,0) -> 0
B77: Junio | C77: 45085 | D77: Martín Maya Estrada | E77: 7° | G77: NO | M77: =IF(H77>0,H77-C77,0) -> 0 | N77: =IF(I77>0,I77-H77,0) -> 0 | O77: =IF(J77>0,J77-I77,0) -> 0 | P77: =IF(J77>0,J77-C77,0) -> 0
B78: Junio | C78: 45085 | D78: Samuel Guerra Gallo | E78: 8° | G78: NO | M78: =IF(H78>0,H78-C78,0) -> 0 | N78: =IF(I78>0,I78-H78,0) -> 0 | O78: =IF(J78>0,J78-I78,0) -> 0 | P78: =IF(J78>0,J78-C78,0) -> 0
B79: Junio | C79: 45092 | D79: Miguel Ángel Benítez González | E79: 8° | G79: SI | H79: 45099 | I79: 45117 | J79: 45138 | K79: Matricula | M79: =IF(H79>0,H79-C79,0) -> 7 | N79: =IF(I79>0,I79-H79,0) -> 18 | O79: =IF(J79>0,J79-I79,0) -> 21 | P79: =IF(J79>0,J79-C79,0) -> 46
B80: Junio | C80: 45092 | D80: Jacobo García Cortés | E80: 6° | G80: SI | H80: 45117 | I80: 45124 | J80: 45148 | K80: Matricula | M80: =IF(H80>0,H80-C80,0) -> 25 | N80: =IF(I80>0,I80-H80,0) -> 7 | O80: =IF(J80>0,J80-I80,0) -> 24 | P80: =IF(J80>0,J80-C80,0) -> 56
B81: Junio | C81: 45092 | D81: Isaac Molina Botero | E81: 6° | G81: NO | M81: =IF(H81>0,H81-C81,0) -> 0 | N81: =IF(I81>0,I81-H81,0) -> 0 | O81: =IF(J81>0,J81-I81,0) -> 0 | P81: =IF(J81>0,J81-C81,0) -> 0
B82: Junio | C82: 45099 | D82: Juan Pablo Osorio Pérez | E82: 11° | G82: NO | M82: =IF(H82>0,H82-C82,0) -> 0 | N82: =IF(I82>0,I82-H82,0) -> 0 | O82: =IF(J82>0,J82-I82,0) -> 0 | P82: =IF(J82>0,J82-C82,0) -> 0
B83: Junio | C83: 45099 | D83: Luis Fernando Londoño Valencia | E83: 8° | G83: SI | H83: 45111 | I83: 45117 | K83: No admitido | M83: =IF(H83>0,H83-C83,0) -> 12 | N83: =IF(I83>0,I83-H83,0) -> 6 | O83: =IF(J83>0,J83-I83,0) -> 0 | P83: =IF(J83>0,J83-C83,0) -> 0
B84: Julio | C84: 45113 | D84: Amy Carolina Rojas Delgado | E84: 7° | G84: NO | M84: =IF(H84>0,H84-C84,0) -> 0 | N84: =IF(I84>0,I84-H84,0) -> 0 | O84: =IF(J84>0,J84-I84,0) -> 0 | P84: =IF(J84>0,J84-C84,0) -> 0
B85: Julio | C85: 45113 | D85: Maximiliano Arce Grajales | E85: 7° | G85: SI | H85: 45114 | I85: 45152 | J85: 45173 | M85: =IF(H85>0,H85-C85,0) -> 1 | N85: =IF(I85>0,I85-H85,0) -> 38 | O85: =IF(J85>0,J85-I85,0) -> 21 | P85: =IF(J85>0,J85-C85,0) -> 60
B86: Julio | C86: 45113 | D86: Sara Cardenas Beltrán | E86: 9° | G86: NO | M86: =IF(H86>0,H86-C86,0) -> 0 | N86: =IF(I86>0,I86-H86,0) -> 0 | O86: =IF(J86>0,J86-I86,0) -> 0 | P86: =IF(J86>0,J86-C86,0) -> 0
B87: Julio | C87: 45113 | D87: Juan Camilo Restrepo Molina | E87: 6° | G87: NO | M87: =IF(H87>0,H87-C87,0) -> 0 | N87: =IF(I87>0,I87-H87,0) -> 0 | O87: =IF(J87>0,J87-I87,0) -> 0 | P87: =IF(J87>0,J87-C87,0) -> 0
B88: Julio | C88: 45120 | D88: Valeria Hernández Restrepo | E88: 6° | G88: SI | H88: 45173 | I88: 45180 | K88: Desisten del proceso - fue admitida | M88: =IF(H88>0,H88-C88,0) -> 53 | N88: =IF(I88>0,I88-H88,0) -> 7 | O88: =IF(J88>0,J88-I88,0) -> 0 | P88: =IF(J88>0,J88-C88,0) -> 0
B89: Julio | C89: 45120 | D89: Agustín Echeverri López | E89: 9° | G89: SI | H89: 45128 | I89: 45138 | K89: Desisten del proceso - fue admitido | M89: =IF(H89>0,H89-C89,0) -> 8 | N89: =IF(I89>0,I89-H89,0) -> 10 | O89: =IF(J89>0,J89-I89,0) -> 0 | P89: =IF(J89>0,J89-C89,0) -> 0
B90: Julio | C90: 45120 | D90: Julián Gómez | E90: 10° | G90: NO | M90: =IF(H90>0,H90-C90,0) -> 0 | N90: =IF(I90>0,I90-H90,0) -> 0 | O90: =IF(J90>0,J90-I90,0) -> 0 | P90: =IF(J90>0,J90-C90,0) -> 0
B91: Julio | C91: 45134 | D91: Ana María Corredor | E91: 9° | G91: SI | H91: 45134 | I91: 45138 | J91: 45161 | K91: Matricula | M91: =IF(H91>0,H91-C91,0) -> 0 | N91: =IF(I91>0,I91-H91,0) -> 4 | O91: =IF(J91>0,J91-I91,0) -> 23 | P91: =IF(J91>0,J91-C91,0) -> 27
B92: Julio | C92: 45134 | D92: Susana Aristizabal Bernal | E92: 9° | G92: NO | M92: =IF(H92>0,H92-C92,0) -> 0 | N92: =IF(I92>0,I92-H92,0) -> 0 | O92: =IF(J92>0,J92-I92,0) -> 0 | P92: =IF(J92>0,J92-C92,0) -> 0
B93: Agosto | C93: 45141 | D93: Daniel Felipe Contreras | E93: 6° | G93: NO | M93: =IF(H93>0,H93-C93,0) -> 0 | N93: =IF(I93>0,I93-H93,0) -> 0 | O93: =IF(J93>0,J93-I93,0) -> 0 | P93: =IF(J93>0,J93-C93,0) -> 0
B94: Agosto | C94: 45141 | D94: Mariana Restrepo Roldán | E94: 8° | G94: SI | H94: 45147 | I94: 45154 | J94: 45173 | M94: =IF(H94>0,H94-C94,0) -> 6 | N94: =IF(I94>0,I94-H94,0) -> 7 | O94: =IF(J94>0,J94-I94,0) -> 19 | P94: =IF(J94>0,J94-C94,0) -> 32
B95: Agosto | C95: 45141 | D95: Manuela Mosquera | E95: 9° | G95: SI | H95: 45146 | I95: 45180 | J95: 45201 | M95: =IF(H95>0,H95-C95,0) -> 5 | N95: =IF(I95>0,I95-H95,0) -> 34 | O95: =IF(J95>0,J95-I95,0) -> 21 | P95: =IF(J95>0,J95-C95,0) -> 60
B96: Agosto | C96: 45141 | D96: Pedro Cano Botero | E96: 8° | G96: SI | H96: 45147 | I96: 45156 | K96: Desisten del proceso - fue admitido | M96: =IF(H96>0,H96-C96,0) -> 6 | N96: =IF(I96>0,I96-H96,0) -> 9 | O96: =IF(J96>0,J96-I96,0) -> 0 | P96: =IF(J96>0,J96-C96,0) -> 0
B97: Agosto | C97: 45148 | D97: Salomé Fernández Quiceno | E97: 8° | G97: SI | H97: 45309 | I97: 45316 | J97: 45336 | M97: =IF(H97>0,H97-C97,0) -> 161 | N97: =IF(I97>0,I97-H97,0) -> 7 | O97: =IF(J97>0,J97-I97,0) -> 20 | P97: =IF(J97>0,J97-C97,0) -> 188
B98: Agosto | C98: 45148 | D98: Camila López Ramírez | E98: 10° | G98: SI | H98: 45194 | K98: No admitida a observación | M98: =IF(H98>0,H98-C98,0) -> 46 | N98: =IF(I98>0,I98-H98,0) -> 0 | O98: =IF(J98>0,J98-I98,0) -> 0 | P98: =IF(J98>0,J98-C98,0) -> 0
B99: Agosto | C99: 45148 | D99: Santiago Céspedes Pizarro | E99: 10° | G99: SI | H99: 45154 | I99: 45166 | J99: 45180 | K99: Matricula | M99: =IF(H99>0,H99-C99,0) -> 6 | N99: =IF(I99>0,I99-H99,0) -> 12 | O99: =IF(J99>0,J99-I99,0) -> 14 | P99: =IF(J99>0,J99-C99,0) -> 32
B100: Agosto | C100: 45155 | D100: Miguel Andrés Cornejo Jiménez | E100: 10° | G100: NO | M100: =IF(H100>0,H100-C100,0) -> 0 | N100: =IF(I100>0,I100-H100,0) -> 0 | O100: =IF(J100>0,J100-I100,0) -> 0 | P100: =IF(J100>0,J100-C100,0) -> 0
...

Sheet Preescolar
B1: Citas de información por mes | I1: Citas de información acumulado por año | P1: Citas de información acumulado todos los años
B2: MES | C2: Prejardín | D2: Jardín | E2: Transición | F2: TOTAL | I2: MES | J2: Prejardín | K2: Jardín | L2: Transición | M2: TOTAL | P2: MES | Q2: Prejardín | R2: Jardín | S2: Transición | T2: TOTAL
A3: 2023 | B3: Enero | C3: =COUNTIFS('Datos Preescolar'!$E:$E,C$2,'Datos Preescolar'!$C:$C,">=01/01/2023",'Datos Preescolar'!$C:$C,"<=31/01/2023") -> 5 | D3: =COUNTIFS('Datos Preescolar'!$E:$E,D$2,'Datos Preescolar'!$C:$C,">=01/01/2023",'Datos Preescolar'!$C:$C,"<=31/01/2023") -> 0 | E3: =COUNTIFS('Datos Preescolar'!$E:$E,E$2,'Datos Preescolar'!$C:$C,">=01/01/2023",'Datos Preescolar'!$C:$C,"<=31/01/2023") -> 1 | F3: =SUM(C3:E3) -> 6 | H3: =A3 -> 2023 | I3: Enero | J3: =SUM(C$3:C3) -> 5 | K3: =SUM(D$3:D3) -> 0 | L3: =SUM(E$3:E3) -> 1 | M3: =SUM(J3:L3) -> 6 | O3: =A3 -> 2023 | P3: Enero | Q3: =SUM(C$3:C3) -> 5 | R3: =SUM(D$3:D3) -> 0 | S3: =SUM(E$3:E3) -> 1 | T3: =SUM(Q3:S3) -> 6
B4: Febrero | C4: =COUNTIFS('Datos Preescolar'!$E:$E,C$2,'Datos Preescolar'!$C:$C,">=01/02/2023",'Datos Preescolar'!$C:$C,"<=28/02/2023") -> 4 | D4: =COUNTIFS('Datos Preescolar'!$E:$E,D$2,'Datos Preescolar'!$C:$C,">=01/02/2023",'Datos Preescolar'!$C:$C,"<=28/02/2023") -> 1 | E4: =COUNTIFS('Datos Preescolar'!$E:$E,E$2,'Datos Preescolar'!$C:$C,">=01/02/2023",'Datos Preescolar'!$C:$C,"<=28/02/2023") -> 2 | F4: =SUM(C4:E4) -> 7 | I4: Febrero | J4: =SUM(C$3:C4) -> 9 | K4: =SUM(D$3:D4) -> 1 | L4: =SUM(E$3:E4) -> 3 | M4: =SUM(J4:L4) -> 13 | P4: Febrero | Q4: =SUM(C$3:C4) -> 9 | R4: =SUM(D$3:D4) -> 1 | S4: =SUM(E$3:E4) -> 3 | T4: =SUM(Q4:S4) -> 13
B5: Marzo | C5: =COUNTIFS('Datos Preescolar'!$E:$E,C$2,'Datos Preescolar'!$C:$C,">=01/03/2023",'Datos Preescolar'!$C:$C,"<=31/03/2023") -> 0 | D5: =COUNTIFS('Datos Preescolar'!$E:$E,D$2,'Datos Preescolar'!$C:$C,">=01/03/2023",'Datos Preescolar'!$C:$C,"<=31/03/2023") -> 0 | E5: =COUNTIFS('Datos Preescolar'!$E:$E,E$2,'Datos Preescolar'!$C:$C,">=01/03/2023",'Datos Preescolar'!$C:$C,"<=31/03/2023") -> 3 | F5: =SUM(C5:E5) -> 3 | I5: Marzo | J5: =SUM(C$3:C5) -> 9 | K5: =SUM(D$3:D5) -> 1 | L5: =SUM(E$3:E5) -> 6 | M5: =SUM(J5:L5) -> 16 | P5: Marzo | Q5: =SUM(C$3:C5) -> 9 | R5: =SUM(D$3:D5) -> 1 | S5: =SUM(E$3:E5) -> 6 | T5: =SUM(Q5:S5) -> 16
B6: Abril | C6: =COUNTIFS('Datos Preescolar'!$E:$E,C$2,'Datos Preescolar'!$C:$C,">=01/04/2023",'Datos Preescolar'!$C:$C,"<=30/04/2023") -> 6 | D6: =COUNTIFS('Datos Preescolar'!$E:$E,D$2,'Datos Preescolar'!$C:$C,">=01/04/2023",'Datos Preescolar'!$C:$C,"<=30/04/2023") -> 2 | E6: =COUNTIFS('Datos Preescolar'!$E:$E,E$2,'Datos Preescolar'!$C:$C,">=01/04/2023",'Datos Preescolar'!$C:$C,"<=30/04/2023") -> 0 | F6: =SUM(C6:E6) -> 8 | I6: Abril | J6: =SUM(C$3:C6) -> 15 | K6: =SUM(D$3:D6) -> 3 | L6: =SUM(E$3:E6) -> 6 | M6: =SUM(J6:L6) -> 24 | P6: Abril | Q6: =SUM(C$3:C6) -> 15 | R6: =SUM(D$3:D6) -> 3 | S6: =SUM(E$3:E6) -> 6 | T6: =SUM(Q6:S6) -> 24
B7: Mayo | C7: =COUNTIFS('Datos Preescolar'!$E:$E,C$2,'Datos Preescolar'!$C:$C,">=01/05/2023",'Datos Preescolar'!$C:$C,"<=31/05/2023") -> 3 | D7: =COUNTIFS('Datos Preescolar'!$E:$E,D$2,'Datos Preescolar'!$C:$C,">=01/05/2023",'Datos Preescolar'!$C:$C,"<=31/05/2023") -> 2 | E7: =COUNTIFS('Datos Preescolar'!$E:$E,E$2,'Datos Preescolar'!$C:$C,">=01/05/2023",'Datos Preescolar'!$C:$C,"<=31/05/2023") -> 3 | F7: =SUM(C7:E7) -> 8 | I7: Mayo | J7: =SUM(C$3:C7) -> 18 | K7: =SUM(D$3:D7) -> 5 | L7: =SUM(E$3:E7) -> 9 | M7: =SUM(J7:L7) -> 32 | P7: Mayo | Q7: =SUM(C$3:C7) -> 18 | R7: =SUM(D$3:D7) -> 5 | S7: =SUM(E$3:E7) -> 9 | T7: =SUM(Q7:S7) -> 32
B8: Junio | C8: =COUNTIFS('Datos Preescolar'!$E:$E,C$2,'Datos Preescolar'!$C:$C,">=01/06/2023",'Datos Preescolar'!$C:$C,"<=30/06/2023") -> 3 | D8: =COUNTIFS('Datos Preescolar'!$E:$E,D$2,'Datos Preescolar'!$C:$C,">=01/06/2023",'Datos Preescolar'!$C:$C,"<=30/06/2023") -> 1 | E8: =COUNTIFS('Datos Preescolar'!$E:$E,E$2,'Datos Preescolar'!$C:$C,">=01/06/2023",'Datos Preescolar'!$C:$C,"<=30/06/2023") -> 0 | F8: =SUM(C8:E8) -> 4 | I8: Junio | J8: =SUM(C$3:C8) -> 21 | K8: =SUM(D$3:D8) -> 6 | L8: =SUM(E$3:E8) -> 9 | M8: =SUM(J8:L8) -> 36 | P8: Junio | Q8: =SUM(C$3:C8) -> 21 | R8: =SUM(D$3:D8) -> 6 | S8: =SUM(E$3:E8) -> 9 | T8: =SUM(Q8:S8) -> 36
B9: Julio | C9: =COUNTIFS('Datos Preescolar'!$E:$E,C$2,'Datos Preescolar'!$C:$C,">=01/07/2023",'Datos Preescolar'!$C:$C,"<=31/07/2023") -> 1 | D9: =COUNTIFS('Datos Preescolar'!$E:$E,D$2,'Datos Preescolar'!$C:$C,">=01/07/2023",'Datos Preescolar'!$C:$C,"<=31/07/2023") -> 1 | E9: =COUNTIFS('Datos Preescolar'!$E:$E,E$2,'Datos Preescolar'!$C:$C,">=01/07/2023",'Datos Preescolar'!$C:$C,"<=31/07/2023") -> 3 | F9: =SUM(C9:E9) -> 5 | I9: Julio | J9: =SUM(C$3:C9) -> 22 | K9: =SUM(D$3:D9) -> 7 | L9: =SUM(E$3:E9) -> 12 | M9: =SUM(J9:L9) -> 41 | P9: Julio | Q9: =SUM(C$3:C9) -> 22 | R9: =SUM(D$3:D9) -> 7 | S9: =SUM(E$3:E9) -> 12 | T9: =SUM(Q9:S9) -> 41
B10: Agosto | C10: =COUNTIFS('Datos Preescolar'!$E:$E,C$2,'Datos Preescolar'!$C:$C,">=01/08/2023",'Datos Preescolar'!$C:$C,"<=31/08/2023") -> 2 | D10: =COUNTIFS('Datos Preescolar'!$E:$E,D$2,'Datos Preescolar'!$C:$C,">=01/08/2023",'Datos Preescolar'!$C:$C,"<=31/08/2023") -> 1 | E10: =COUNTIFS('Datos Preescolar'!$E:$E,E$2,'Datos Preescolar'!$C:$C,">=01/08/2023",'Datos Preescolar'!$C:$C,"<=31/08/2023") -> 4 | F10: =SUM(C10:E10) -> 7 | I10: Agosto | J10: =SUM(C$3:C10) -> 24 | K10: =SUM(D$3:D10) -> 8 | L10: =SUM(E$3:E10) -> 16 | M10: =SUM(J10:L10) -> 48 | P10: Agosto | Q10: =SUM(C$3:C10) -> 24 | R10: =SUM(D$3:D10) -> 8 | S10: =SUM(E$3:E10) -> 16 | T10: =SUM(Q10:S10) -> 48
B11: Septiembre | C11: =COUNTIFS('Datos Preescolar'!$E:$E,C$2,'Datos Preescolar'!$C:$C,">=01/09/2023",'Datos Preescolar'!$C:$C,"<=30/09/2023") -> 5 | D11: =COUNTIFS('Datos Preescolar'!$E:$E,D$2,'Datos Preescolar'!$C:$C,">=01/09/2023",'Datos Preescolar'!$C:$C,"<=30/09/2023") -> 0 | E11: =COUNTIFS('Datos Preescolar'!$E:$E,E$2,'Datos Preescolar'!$C:$C,">=01/09/2023",'Datos Preescolar'!$C:$C,"<=30/09/2023") -> 1 | F11: =SUM(C11:E11) -> 6 | I11: Septiembre | J11: =SUM(C$3:C11) -> 29 | K11: =SUM(D$3:D11) -> 8 | L11: =SUM(E$3:E11) -> 17 | M11: =SUM(J11:L11) -> 54 | P11: Septiembre | Q11: =SUM(C$3:C11) -> 29 | R11: =SUM(D$3:D11) -> 8 | S11: =SUM(E$3:E11) -> 17 | T11: =SUM(Q11:S11) -> 54
B12: Octubre | C12: =COUNTIFS('Datos Preescolar'!$E:$E,C$2,'Datos Preescolar'!$C:$C,">=01/10/2023",'Datos Preescolar'!$C:$C,"<=31/10/2023") -> 1 | D12: =COUNTIFS('Datos Preescolar'!$E:$E,D$2,'Datos Preescolar'!$C:$C,">=01/10/2023",'Datos Preescolar'!$C:$C,"<=31/10/2023") -> 1 | E12: =COUNTIFS('Datos Preescolar'!$E:$E,E$2,'Datos Preescolar'!$C:$C,">=01/10/2023",'Datos Preescolar'!$C:$C,"<=31/10/2023") -> 0 | F12: =SUM(C12:E12) -> 2 | I12: Octubre | J12: =SUM(C$3:C12) -> 30 | K12: =SUM(D$3:D12) -> 9 | L12: =SUM(E$3:E12) -> 17 | M12: =SUM(J12:L12) -> 56 | P12: Octubre | Q12: =SUM(C$3:C12) -> 30 | R12: =SUM(D$3:D12) -> 9 | S12: =SUM(E$3:E12) -> 17 | T12: =SUM(Q12:S12) -> 56
B13: Noviembre | C13: =COUNTIFS('Datos Preescolar'!$E:$E,C$2,'Datos Preescolar'!$C:$C,">=01/11/2023",'Datos Preescolar'!$C:$C,"<=30/11/2023") -> 0 | D13: =COUNTIFS('Datos Preescolar'!$E:$E,D$2,'Datos Preescolar'!$C:$C,">=01/11/2023",'Datos Preescolar'!$C:$C,"<=30/11/2023") -> 2 | E13: =COUNTIFS('Datos Preescolar'!$E:$E,E$2,'Datos Preescolar'!$C:$C,">=01/11/2023",'Datos Preescolar'!$C:$C,"<=30/11/2023") -> 1 | F13: =SUM(C13:E13) -> 3 | I13: Noviembre | J13: =SUM(C$3:C13) -> 30 | K13: =SUM(D$3:D13) -> 11 | L13: =SUM(E$3:E13) -> 18 | M13: =SUM(J13:L13) -> 59 | P13: Noviembre | Q13: =SUM(C$3:C13) -> 30 | R13: =SUM(D$3:D13) -> 11 | S13: =SUM(E$3:E13) -> 18 | T13: =SUM(Q13:S13) -> 59
B14: Diciembre | C14: =COUNTIFS('Datos Preescolar'!$E:$E,C$2,'Datos Preescolar'!$C:$C,">=01/12/2023",'Datos Preescolar'!$C:$C,"<=31/12/2023") -> 0 | D14: =COUNTIFS('Datos Preescolar'!$E:$E,D$2,'Datos Preescolar'!$C:$C,">=01/12/2023",'Datos Preescolar'!$C:$C,"<=31/12/2023") -> 0 | E14: =COUNTIFS('Datos Preescolar'!$E:$E,E$2,'Datos Preescolar'!$C:$C,">=01/12/2023",'Datos Preescolar'!$C:$C,"<=31/12/2023") -> 0 | F14: =SUM(C14:E14) -> 0 | I14: Diciembre | J14: =SUM(C$3:C14) -> 30 | K14: =SUM(D$3:D14) -> 11 | L14: =SUM(E$3:E14) -> 18 | M14: =SUM(J14:L14) -> 59 | P14: Diciembre | Q14: =SUM(C$3:C14) -> 30 | R14: =SUM(D$3:D14) -> 11 | S14: =SUM(E$3:E14) -> 18 | T14: =SUM(Q14:S14) -> 59
A15: 2024 | B15: Enero | C15: =COUNTIFS('Datos Preescolar'!$E:$E,C$2,'Datos Preescolar'!$C:$C,">=01/01/2024",'Datos Preescolar'!$C:$C,"<=31/01/2024") -> 2 | D15: =COUNTIFS('Datos Preescolar'!$E:$E,D$2,'Datos Preescolar'!$C:$C,">=01/01/2024",'Datos Preescolar'!$C:$C,"<=31/01/2024") -> 1 | E15: =COUNTIFS('Datos Preescolar'!$E:$E,E$2,'Datos Preescolar'!$C:$C,">=01/01/2024",'Datos Preescolar'!$C:$C,"<=31/01/2024") -> 2 | F15: =SUM(C15:E15) -> 5 | H15: =A15 -> 2024 | I15: Enero | J15: =SUM(C$15:C15) -> 2 | K15: =SUM(D$15:D15) -> 1 | L15: =SUM(E$15:E15) -> 2 | M15: =SUM(J15:L15) -> 5 | O15: =A15 -> 2024 | P15: Enero | Q15: =SUM(C$3:C15) -> 32 | R15: =SUM(D$3:D15) -> 12 | S15: =SUM(E$3:E15) -> 20 | T15: =SUM(Q15:S15) -> 64
B16: Febrero | C16: =COUNTIFS('Datos Preescolar'!$E:$E,C$2,'Datos Preescolar'!$C:$C,">=01/02/2024",'Datos Preescolar'!$C:$C,"<=29/02/2024") -> 3 | D16: =COUNTIFS('Datos Preescolar'!$E:$E,D$2,'Datos Preescolar'!$C:$C,">=01/02/2024",'Datos Preescolar'!$C:$C,"<=29/02/2024") -> 1 | E16: =COUNTIFS('Datos Preescolar'!$E:$E,E$2,'Datos Preescolar'!$C:$C,">=01/02/2024",'Datos Preescolar'!$C:$C,"<=29/02/2024") -> 0 | F16: =SUM(C16:E16) -> 4 | I16: Febrero | J16: =SUM(C$15:C16) -> 5 | K16: =SUM(D$15:D16) -> 2 | L16: =SUM(E$15:E16) -> 2 | M16: =SUM(J16:L16) -> 9 | P16: Febrero | Q16: =SUM(C$3:C16) -> 35 | R16: =SUM(D$3:D16) -> 13 | S16: =SUM(E$3:E16) -> 20 | T16: =SUM(Q16:S16) -> 68
B17: Marzo | C17: =COUNTIFS('Datos Preescolar'!$E:$E,C$2,'Datos Preescolar'!$C:$C,">=01/03/2024",'Datos Preescolar'!$C:$C,"<=31/03/2024") -> 0 | D17: =COUNTIFS('Datos Preescolar'!$E:$E,D$2,'Datos Preescolar'!$C:$C,">=01/03/2024",'Datos Preescolar'!$C:$C,"<=31/03/2024") -> 1 | E17: =COUNTIFS('Datos Preescolar'!$E:$E,E$2,'Datos Preescolar'!$C:$C,">=01/03/2024",'Datos Preescolar'!$C:$C,"<=31/03/2024") -> 0 | F17: =SUM(C17:E17) -> 1 | I17: Marzo | J17: =SUM(C$15:C17) -> 5 | K17: =SUM(D$15:D17) -> 3 | L17: =SUM(E$15:E17) -> 2 | M17: =SUM(J17:L17) -> 10 | P17: Marzo | Q17: =SUM(C$3:C17) -> 35 | R17: =SUM(D$3:D17) -> 14 | S17: =SUM(E$3:E17) -> 20 | T17: =SUM(Q17:S17) -> 69
B18: Abril | C18: =COUNTIFS('Datos Preescolar'!$E:$E,C$2,'Datos Preescolar'!$C:$C,">=01/04/2024",'Datos Preescolar'!$C:$C,"<=30/04/2024") -> 3 | D18: =COUNTIFS('Datos Preescolar'!$E:$E,D$2,'Datos Preescolar'!$C:$C,">=01/04/2024",'Datos Preescolar'!$C:$C,"<=30/04/2024") -> 2 | E18: =COUNTIFS('Datos Preescolar'!$E:$E,E$2,'Datos Preescolar'!$C:$C,">=01/04/2024",'Datos Preescolar'!$C:$C,"<=30/04/2024") -> 0 | F18: =SUM(C18:E18) -> 5 | I18: Abril | J18: =SUM(C$15:C18) -> 8 | K18: =SUM(D$15:D18) -> 5 | L18: =SUM(E$15:E18) -> 2 | M18: =SUM(J18:L18) -> 15 | P18: Abril | Q18: =SUM(C$3:C18) -> 38 | R18: =SUM(D$3:D18) -> 16 | S18: =SUM(E$3:E18) -> 20 | T18: =SUM(Q18:S18) -> 74
B19: Mayo | C19: =COUNTIFS('Datos Preescolar'!$E:$E,C$2,'Datos Preescolar'!$C:$C,">=01/05/2024",'Datos Preescolar'!$C:$C,"<=31/05/2024") -> 2 | D19: =COUNTIFS('Datos Preescolar'!$E:$E,D$2,'Datos Preescolar'!$C:$C,">=01/05/2024",'Datos Preescolar'!$C:$C,"<=31/05/2024") -> 2 | E19: =COUNTIFS('Datos Preescolar'!$E:$E,E$2,'Datos Preescolar'!$C:$C,">=01/05/2024",'Datos Preescolar'!$C:$C,"<=31/05/2024") -> 0 | F19: =SUM(C19:E19) -> 4 | I19: Mayo | J19: =SUM(C$15:C19) -> 10 | K19: =SUM(D$15:D19) -> 7 | L19: =SUM(E$15:E19) -> 2 | M19: =SUM(J19:L19) -> 19 | P19: Mayo | Q19: =SUM(C$3:C19) -> 40 | R19: =SUM(D$3:D19) -> 18 | S19: =SUM(E$3:E19) -> 20 | T19: =SUM(Q19:S19) -> 78
B20: Junio | C20: =COUNTIFS('Datos Preescolar'!$E:$E,C$2,'Datos Preescolar'!$C:$C,">=01/06/2024",'Datos Preescolar'!$C:$C,"<=30/06/2024") -> 3 | D20: =COUNTIFS('Datos Preescolar'!$E:$E,D$2,'Datos Preescolar'!$C:$C,">=01/06/2024",'Datos Preescolar'!$C:$C,"<=30/06/2024") -> 1 | E20: =COUNTIFS('Datos Preescolar'!$E:$E,E$2,'Datos Preescolar'!$C:$C,">=01/06/2024",'Datos Preescolar'!$C:$C,"<=30/06/2024") -> 1 | F20: =SUM(C20:E20) -> 5 | I20: Junio | J20: =SUM(C$15:C20) -> 13 | K20: =SUM(D$15:D20) -> 8 | L20: =SUM(E$15:E20) -> 3 | M20: =SUM(J20:L20) -> 24 | P20: Junio | Q20: =SUM(C$3:C20) -> 43 | R20: =SUM(D$3:D20) -> 19 | S20: =SUM(E$3:E20) -> 21 | T20: =SUM(Q20:S20) -> 83
B21: Julio | C21: =COUNTIFS('Datos Preescolar'!$E:$E,C$2,'Datos Preescolar'!$C:$C,">=01/07/2024",'Datos Preescolar'!$C:$C,"<=31/07/2024") -> 3 | D21: =COUNTIFS('Datos Preescolar'!$E:$E,D$2,'Datos Preescolar'!$C:$C,">=01/07/2024",'Datos Preescolar'!$C:$C,"<=31/07/2024") -> 2 | E21: 0 | F21: =SUM(C21:E21) -> 5 | I21: Julio | J21: =SUM(C$15:C21) -> 16 | K21: =SUM(D$15:D21) -> 10 | L21: =SUM(E$15:E21) -> 3 | M21: =SUM(J21:L21) -> 29 | P21: Julio | Q21: =SUM(C$3:C21) -> 46 | R21: =SUM(D$3:D21) -> 21 | S21: =SUM(E$3:E21) -> 21 | T21: =SUM(Q21:S21) -> 88
B22: Agosto | C22: =COUNTIFS('Datos Preescolar'!$E:$E,C$2,'Datos Preescolar'!$C:$C,">=01/08/2024",'Datos Preescolar'!$C:$C,"<=31/08/2024") -> 1 | D22: =COUNTIFS('Datos Preescolar'!$E:$E,D$2,'Datos Preescolar'!$C:$C,">=01/08/2024",'Datos Preescolar'!$C:$C,"<=31/08/2024") -> 0 | E22: =COUNTIFS('Datos Preescolar'!$E:$E,E$2,'Datos Preescolar'!$C:$C,">=01/08/2024",'Datos Preescolar'!$C:$C,"<=31/08/2024") -> 1 | F22: =SUM(C22:E22) -> 2 | I22: Agosto | J22: =SUM(C$15:C22) -> 17 | K22: =SUM(D$15:D22) -> 10 | L22: =SUM(E$15:E22) -> 4 | M22: =SUM(J22:L22) -> 31 | P22: Agosto | Q22: =SUM(C$3:C22) -> 47 | R22: =SUM(D$3:D22) -> 21 | S22: =SUM(E$3:E22) -> 22 | T22: =SUM(Q22:S22) -> 90
B23: Septiembre | C23: =COUNTIFS('Datos Preescolar'!$E:$E,C$2,'Datos Preescolar'!$C:$C,">=01/09/2024",'Datos Preescolar'!$C:$C,"<=30/09/2024") -> 3 | D23: =COUNTIFS('Datos Preescolar'!$E:$E,D$2,'Datos Preescolar'!$C:$C,">=01/09/2024",'Datos Preescolar'!$C:$C,"<=30/09/2024") -> 0 | E23: =COUNTIFS('Datos Preescolar'!$E:$E,E$2,'Datos Preescolar'!$C:$C,">=01/09/2024",'Datos Preescolar'!$C:$C,"<=30/09/2024") -> 0 | F23: =SUM(C23:E23) -> 3 | I23: Septiembre | J23: =SUM(C$15:C23) -> 20 | K23: =SUM(D$15:D23) -> 10 | L23: =SUM(E$15:E23) -> 4 | M23: =SUM(J23:L23) -> 34 | P23: Septiembre | Q23: =SUM(C$3:C23) -> 50 | R23: =SUM(D$3:D23) -> 21 | S23: =SUM(E$3:E23) -> 22 | T23: =SUM(Q23:S23) -> 93
B24: Octubre | C24: =COUNTIFS('Datos Preescolar'!$E:$E,C$2,'Datos Preescolar'!$C:$C,">=01/10/2024",'Datos Preescolar'!$C:$C,"<=31/10/2024") -> 1 | D24: =COUNTIFS('Datos Preescolar'!$E:$E,D$2,'Datos Preescolar'!$C:$C,">=01/10/2024",'Datos Preescolar'!$C:$C,"<=31/10/2024") -> 2 | E24: =COUNTIFS('Datos Preescolar'!$E:$E,E$2,'Datos Preescolar'!$C:$C,">=01/10/2024",'Datos Preescolar'!$C:$C,"<=31/10/2024") -> 0 | F24: =SUM(C24:E24) -> 3 | I24: Octubre | J24: =SUM(C$15:C24) -> 21 | K24: =SUM(D$15:D24) -> 12 | L24: =SUM(E$15:E24) -> 4 | M24: =SUM(J24:L24) -> 37 | P24: Octubre | Q24: =SUM(C$3:C24) -> 51 | R24: =SUM(D$3:D24) -> 23 | S24: =SUM(E$3:E24) -> 22 | T24: =SUM(Q24:S24) -> 96
B25: Noviembre | C25: =COUNTIFS('Datos Preescolar'!$E:$E,C$2,'Datos Preescolar'!$C:$C,">=01/11/2024",'Datos Preescolar'!$C:$C,"<=30/11/2024") -> 3 | D25: =COUNTIFS('Datos Preescolar'!$E:$E,D$2,'Datos Preescolar'!$C:$C,">=01/11/2024",'Datos Preescolar'!$C:$C,"<=30/11/2024") -> 1 | E25: =COUNTIFS('Datos Preescolar'!$E:$E,E$2,'Datos Preescolar'!$C:$C,">=01/11/2024",'Datos Preescolar'!$C:$C,"<=30/11/2024") -> 1 | F25: =SUM(C25:E25) -> 5 | I25: Noviembre | J25: =SUM(C$15:C25) -> 24 | K25: =SUM(D$15:D25) -> 13 | L25: =SUM(E$15:E25) -> 5 | M25: =SUM(J25:L25) -> 42 | P25: Noviembre | Q25: =SUM(C$3:C25) -> 54 | R25: =SUM(D$3:D25) -> 24 | S25: =SUM(E$3:E25) -> 23 | T25: =SUM(Q25:S25) -> 101
B26: Diciembre | C26: =COUNTIFS('Datos Preescolar'!$E:$E,C$2,'Datos Preescolar'!$C:$C,">=01/12/2024",'Datos Preescolar'!$C:$C,"<=31/12/2024") -> 2 | D26: =COUNTIFS('Datos Preescolar'!$E:$E,D$2,'Datos Preescolar'!$C:$C,">=01/12/2024",'Datos Preescolar'!$C:$C,"<=31/12/2024") -> 2 | E26: =COUNTIFS('Datos Preescolar'!$E:$E,E$2,'Datos Preescolar'!$C:$C,">=01/12/2024",'Datos Preescolar'!$C:$C,"<=31/12/2024") -> 0 | F26: =SUM(C26:E26) -> 4 | I26: Diciembre | J26: =SUM(C$15:C26) -> 26 | K26: =SUM(D$15:D26) -> 15 | L26: =SUM(E$15:E26) -> 5 | M26: =SUM(J26:L26) -> 46 | P26: Diciembre | Q26: =SUM(C$3:C26) -> 56 | R26: =SUM(D$3:D26) -> 26 | S26: =SUM(E$3:E26) -> 23 | T26: =SUM(Q26:S26) -> 105
A27: 2025 | B27: Enero | C27: =COUNTIFS('Datos Preescolar'!$E:$E,C$2,'Datos Preescolar'!$C:$C,">=01/01/2025",'Datos Preescolar'!$C:$C,"<=31/01/2025") -> 0 | D27: =COUNTIFS('Datos Preescolar'!$E:$E,D$2,'Datos Preescolar'!$C:$C,">=01/01/2025",'Datos Preescolar'!$C:$C,"<=31/01/2025") -> 1 | E27: =COUNTIFS('Datos Preescolar'!$E:$E,E$2,'Datos Preescolar'!$C:$C,">=01/01/2025",'Datos Preescolar'!$C:$C,"<=31/01/2025") -> 0 | F27: =SUM(C27:E27) -> 1 | H27: =A27 -> 2025 | I27: Enero | J27: =SUM(C$27:C27) -> 0 | K27: =SUM(D$27:D27) -> 1 | L27: =SUM(E$27:E27) -> 0 | M27: =SUM(J27:L27) -> 1 | O27: =A27 -> 2025 | P27: Enero | Q27: =SUM(C$3:C27) -> 56 | R27: =SUM(D$3:D27) -> 27 | S27: =SUM(E$3:E27) -> 23 | T27: =SUM(Q27:S27) -> 106
B28: Febrero | C28: =COUNTIFS('Datos Preescolar'!$E:$E,C$2,'Datos Preescolar'!$C:$C,">=01/02/2025",'Datos Preescolar'!$C:$C,"<=28/02/2025") -> 2 | D28: =COUNTIFS('Datos Preescolar'!$E:$E,D$2,'Datos Preescolar'!$C:$C,">=01/02/2025",'Datos Preescolar'!$C:$C,"<=28/02/2025") -> 2 | E28: =COUNTIFS('Datos Preescolar'!$E:$E,E$2,'Datos Preescolar'!$C:$C,">=01/02/2025",'Datos Preescolar'!$C:$C,"<=28/02/2025") -> 1 | F28: =SUM(C28:E28) -> 5 | I28: Febrero | J28: =SUM(C$27:C28) -> 2 | K28: =SUM(D$27:D28) -> 3 | L28: =SUM(E$27:E28) -> 1 | M28: =SUM(J28:L28) -> 6 | P28: Febrero | Q28: =SUM(C$3:C28) -> 58 | R28: =SUM(D$3:D28) -> 29 | S28: =SUM(E$3:E28) -> 24 | T28: =SUM(Q28:S28) -> 111
B29: Marzo | C29: =COUNTIFS('Datos Preescolar'!$E:$E,C$2,'Datos Preescolar'!$C:$C,">=01/03/2025",'Datos Preescolar'!$C:$C,"<=31/03/2025") -> 3 | D29: =COUNTIFS('Datos Preescolar'!$E:$E,D$2,'Datos Preescolar'!$C:$C,">=01/03/2025",'Datos Preescolar'!$C:$C,"<=31/03/2025") -> 2 | E29: =COUNTIFS('Datos Preescolar'!$E:$E,E$2,'Datos Preescolar'!$C:$C,">=01/03/2025",'Datos Preescolar'!$C:$C,"<=31/03/2025") -> 0 | F29: =SUM(C29:E29) -> 5 | I29: Marzo | J29: =SUM(C$27:C29) -> 5 | K29: =SUM(D$27:D29) -> 5 | L29: =SUM(E$27:E29) -> 1 | M29: =SUM(J29:L29) -> 11 | P29: Marzo | Q29: =SUM(C$3:C29) -> 61 | R29: =SUM(D$3:D29) -> 31 | S29: =SUM(E$3:E29) -> 24 | T29: =SUM(Q29:S29) -> 116
B30: Abril | C30: =COUNTIFS('Datos Preescolar'!$E:$E,C$2,'Datos Preescolar'!$C:$C,">=01/04/2025",'Datos Preescolar'!$C:$C,"<=30/04/2025") -> 3 | D30: =COUNTIFS('Datos Preescolar'!$E:$E,D$2,'Datos Preescolar'!$C:$C,">=01/04/2025",'Datos Preescolar'!$C:$C,"<=30/04/2025") -> 3 | E30: =COUNTIFS('Datos Preescolar'!$E:$E,E$2,'Datos Preescolar'!$C:$C,">=01/04/2025",'Datos Preescolar'!$C:$C,"<=30/04/2025") -> 1 | F30: =SUM(C30:E30) -> 7 | I30: Abril | J30: =SUM(C$27:C30) -> 8 | K30: =SUM(D$27:D30) -> 8 | L30: =SUM(E$27:E30) -> 2 | M30: =SUM(J30:L30) -> 18 | P30: Abril | Q30: =SUM(C$3:C30) -> 64 | R30: =SUM(D$3:D30) -> 34 | S30: =SUM(E$3:E30) -> 25 | T30: =SUM(Q30:S30) -> 123
B31: Mayo | C31: =COUNTIFS('Datos Preescolar'!$E:$E,C$2,'Datos Preescolar'!$C:$C,">=01/05/2025",'Datos Preescolar'!$C:$C,"<=31/05/2025") -> 2 | D31: =COUNTIFS('Datos Preescolar'!$E:$E,D$2,'Datos Preescolar'!$C:$C,">=01/05/2025",'Datos Preescolar'!$C:$C,"<=31/05/2025") -> 0 | E31: =COUNTIFS('Datos Preescolar'!$E:$E,E$2,'Datos Preescolar'!$C:$C,">=01/05/2025",'Datos Preescolar'!$C:$C,"<=31/05/2025") -> 0 | F31: =SUM(C31:E31) -> 2 | I31: Mayo | J31: =SUM(C$27:C31) -> 10 | K31: =SUM(D$27:D31) -> 8 | L31: =SUM(E$27:E31) -> 2 | M31: =SUM(J31:L31) -> 20 | P31: Mayo | Q31: =SUM(C$3:C31) -> 66 | R31: =SUM(D$3:D31) -> 34 | S31: =SUM(E$3:E31) -> 25 | T31: =SUM(Q31:S31) -> 125
B32: Junio | C32: =COUNTIFS('Datos Preescolar'!$E:$E,C$2,'Datos Preescolar'!$C:$C,">=01/06/2025",'Datos Preescolar'!$C:$C,"<=30/06/2025") -> 1 | D32: =COUNTIFS('Datos Preescolar'!$E:$E,D$2,'Datos Preescolar'!$C:$C,">=01/06/2025",'Datos Preescolar'!$C:$C,"<=30/06/2025") -> 2 | E32: =COUNTIFS('Datos Preescolar'!$E:$E,E$2,'Datos Preescolar'!$C:$C,">=01/06/2025",'Datos Preescolar'!$C:$C,"<=30/06/2025") -> 0 | F32: =SUM(C32:E32) -> 3 | I32: Junio | J32: =SUM(C$27:C32) -> 11 | K32: =SUM(D$27:D32) -> 10 | L32: =SUM(E$27:E32) -> 2 | M32: =SUM(J32:L32) -> 23 | P32: Junio | Q32: =SUM(C$3:C32) -> 67 | R32: =SUM(D$3:D32) -> 36 | S32: =SUM(E$3:E32) -> 25 | T32: =SUM(Q32:S32) -> 128
B33: Julio | C33: =COUNTIFS('Datos Preescolar'!$E:$E,C$2,'Datos Preescolar'!$C:$C,">=01/07/2025",'Datos Preescolar'!$C:$C,"<=31/07/2025") -> 4 | D33: =COUNTIFS('Datos Preescolar'!$E:$E,D$2,'Datos Preescolar'!$C:$C,">=01/07/2025",'Datos Preescolar'!$C:$C,"<=31/07/2025") -> 1 | E33: 0 | F33: =SUM(C33:E33) -> 5 | I33: Julio | J33: =SUM(C$27:C33) -> 15 | K33: =SUM(D$27:D33) -> 11 | L33: =SUM(E$27:E33) -> 2 | M33: =SUM(J33:L33) -> 28 | P33: Julio | Q33: =SUM(C$3:C33) -> 71 | R33: =SUM(D$3:D33) -> 37 | S33: =SUM(E$3:E33) -> 25 | T33: =SUM(Q33:S33) -> 133
B34: Agosto | C34: =COUNTIFS('Datos Preescolar'!$E:$E,C$2,'Datos Preescolar'!$C:$C,">=01/08/2025",'Datos Preescolar'!$C:$C,"<=31/08/2025") -> 2 | D34: =COUNTIFS('Datos Preescolar'!$E:$E,D$2,'Datos Preescolar'!$C:$C,">=01/08/2025",'Datos Preescolar'!$C:$C,"<=31/08/2025") -> 1 | E34: =COUNTIFS('Datos Preescolar'!$E:$E,E$2,'Datos Preescolar'!$C:$C,">=01/08/2025",'Datos Preescolar'!$C:$C,"<=31/08/2025") -> 2 | F34: =SUM(C34:E34) -> 5 | I34: Agosto | J34: =SUM(C$27:C34) -> 17 | K34: =SUM(D$27:D34) -> 12 | L34: =SUM(E$27:E34) -> 4 | M34: =SUM(J34:L34) -> 33 | P34: Agosto | Q34: =SUM(C$3:C34) -> 73 | R34: =SUM(D$3:D34) -> 38 | S34: =SUM(E$3:E34) -> 27 | T34: =SUM(Q34:S34) -> 138
B35: Septiembre | C35: =COUNTIFS('Datos Preescolar'!$E:$E,C$2,'Datos Preescolar'!$C:$C,">=01/09/2025",'Datos Preescolar'!$C:$C,"<=30/09/2025") -> 8 | D35: =COUNTIFS('Datos Preescolar'!$E:$E,D$2,'Datos Preescolar'!$C:$C,">=01/09/2025",'Datos Preescolar'!$C:$C,"<=30/09/2025") -> 4 | E35: =COUNTIFS('Datos Preescolar'!$E:$E,E$2,'Datos Preescolar'!$C:$C,">=01/09/2025",'Datos Preescolar'!$C:$C,"<=30/09/2025") -> 1 | F35: =SUM(C35:E35) -> 13 | I35: Septiembre | J35: =SUM(C$27:C35) -> 25 | K35: =SUM(D$27:D35) -> 16 | L35: =SUM(E$27:E35) -> 5 | M35: =SUM(J35:L35) -> 46 | P35: Septiembre | Q35: =SUM(C$3:C35) -> 81 | R35: =SUM(D$3:D35) -> 42 | S35: =SUM(E$3:E35) -> 28 | T35: =SUM(Q35:S35) -> 151
B36: Octubre | C36: =COUNTIFS('Datos Preescolar'!$E:$E,C$2,'Datos Preescolar'!$C:$C,">=01/10/2025",'Datos Preescolar'!$C:$C,"<=31/10/2025") -> 3 | D36: =COUNTIFS('Datos Preescolar'!$E:$E,D$2,'Datos Preescolar'!$C:$C,">=01/10/2025",'Datos Preescolar'!$C:$C,"<=31/10/2025") -> 1 | E36: =COUNTIFS('Datos Preescolar'!$E:$E,E$2,'Datos Preescolar'!$C:$C,">=01/10/2025",'Datos Preescolar'!$C:$C,"<=31/10/2025") -> 0 | F36: =SUM(C36:E36) -> 4 | I36: Octubre | J36: =SUM(C$27:C36) -> 28 | K36: =SUM(D$27:D36) -> 17 | L36: =SUM(E$27:E36) -> 5 | M36: =SUM(J36:L36) -> 50 | P36: Octubre | Q36: =SUM(C$3:C36) -> 84 | R36: =SUM(D$3:D36) -> 43 | S36: =SUM(E$3:E36) -> 28 | T36: =SUM(Q36:S36) -> 155
B37: Noviembre | C37: =COUNTIFS('Datos Preescolar'!$E:$E,C$2,'Datos Preescolar'!$C:$C,">=01/11/2025",'Datos Preescolar'!$C:$C,"<=30/11/2025") -> 4 | D37: =COUNTIFS('Datos Preescolar'!$E:$E,D$2,'Datos Preescolar'!$C:$C,">=01/11/2025",'Datos Preescolar'!$C:$C,"<=30/11/2025") -> 1 | E37: =COUNTIFS('Datos Preescolar'!$E:$E,E$2,'Datos Preescolar'!$C:$C,">=01/11/2025",'Datos Preescolar'!$C:$C,"<=30/11/2025") -> 1 | F37: =SUM(C37:E37) -> 6 | I37: Noviembre | J37: =SUM(C$27:C37) -> 32 | K37: =SUM(D$27:D37) -> 18 | L37: =SUM(E$27:E37) -> 6 | M37: =SUM(J37:L37) -> 56 | P37: Noviembre | Q37: =SUM(C$3:C37) -> 88 | R37: =SUM(D$3:D37) -> 44 | S37: =SUM(E$3:E37) -> 29 | T37: =SUM(Q37:S37) -> 161
B38: Diciembre | C38: =COUNTIFS('Datos Preescolar'!$E:$E,C$2,'Datos Preescolar'!$C:$C,">=01/12/2025",'Datos Preescolar'!$C:$C,"<=31/12/2025") -> 2 | D38: =COUNTIFS('Datos Preescolar'!$E:$E,D$2,'Datos Preescolar'!$C:$C,">=01/12/2025",'Datos Preescolar'!$C:$C,"<=31/12/2025") -> 0 | E38: =COUNTIFS('Datos Preescolar'!$E:$E,E$2,'Datos Preescolar'!$C:$C,">=01/12/2025",'Datos Preescolar'!$C:$C,"<=31/12/2025") -> 2 | F38: =SUM(C38:E38) -> 4 | I38: Diciembre | J38: =SUM(C$27:C38) -> 34 | K38: =SUM(D$27:D38) -> 18 | L38: =SUM(E$27:E38) -> 8 | M38: =SUM(J38:L38) -> 60 | P38: Diciembre | Q38: =SUM(C$3:C38) -> 90 | R38: =SUM(D$3:D38) -> 44 | S38: =SUM(E$3:E38) -> 31 | T38: =SUM(Q38:S38) -> 165
B41: Inicia observación por mes | I41: Inicia observación acumulado por año | P41: Inicia observación acumulado todos los años
B42: MES | C42: Prejardín | D42: Jardín | E42: Transición | F42: TOTAL | I42: MES | J42: Prejardín | K42: Jardín | L42: Transición | M42: TOTAL | P42: MES | Q42: Prejardín | R42: Jardín | S42: Transición | T42: TOTAL
A43: =A3 -> 2023 | B43: Enero | C43: =COUNTIFS('Datos Preescolar'!$E:$E,C$42,'Datos Preescolar'!$H:$H,">=01/01/2023",'Datos Preescolar'!$H:$H,"<=31/01/2023") -> 0 | D43: =COUNTIFS('Datos Preescolar'!$E:$E,D$42,'Datos Preescolar'!$H:$H,">=01/01/2023",'Datos Preescolar'!$H:$H,"<=31/01/2023") -> 0 | E43: =COUNTIFS('Datos Preescolar'!$E:$E,E$42,'Datos Preescolar'!$H:$H,">=01/01/2023",'Datos Preescolar'!$H:$H,"<=31/01/2023") -> 1 | F43: =SUM(C43:E43) -> 1 | H43: =A43 -> 2023 | I43: Enero | J43: =SUM(C$43:C43) -> 0 | K43: =SUM(D$43:D43) -> 0 | L43: =SUM(E$43:E43) -> 1 | M43: =SUM(J43:L43) -> 1 | O43: =A43 -> 2023 | P43: Enero | Q43: =SUM(C$43:C43) -> 0 | R43: =SUM(D$43:D43) -> 0 | S43: =SUM(E$43:E43) -> 1 | T43: =SUM(Q43:S43) -> 1
B44: Febrero | C44: =COUNTIFS('Datos Preescolar'!$E:$E,C$42,'Datos Preescolar'!$H:$H,">=01/02/2023",'Datos Preescolar'!$H:$H,"<=28/02/2023") -> 0 | D44: =COUNTIFS('Datos Preescolar'!$E:$E,D$42,'Datos Preescolar'!$H:$H,">=01/02/2023",'Datos Preescolar'!$H:$H,"<=28/02/2023") -> 0 | E44: =COUNTIFS('Datos Preescolar'!$E:$E,E$42,'Datos Preescolar'!$H:$H,">=01/02/2023",'Datos Preescolar'!$H:$H,"<=28/02/2023") -> 0 | F44: =SUM(C44:E44) -> 0 | I44: Febrero | J44: =SUM(C$43:C44) -> 0 | K44: =SUM(D$43:D44) -> 0 | L44: =SUM(E$43:E44) -> 1 | M44: =SUM(J44:L44) -> 1 | P44: Febrero | Q44: =SUM(C$43:C44) -> 0 | R44: =SUM(D$43:D44) -> 0 | S44: =SUM(E$43:E44) -> 1 | T44: =SUM(Q44:S44) -> 1
B45: Marzo | C45: =COUNTIFS('Datos Preescolar'!$E:$E,C$42,'Datos Preescolar'!$H:$H,">=01/03/2023",'Datos Preescolar'!$H:$H,"<=31/03/2023") -> 0 | D45: =COUNTIFS('Datos Preescolar'!$E:$E,D$42,'Datos Preescolar'!$H:$H,">=01/03/2023",'Datos Preescolar'!$H:$H,"<=31/03/2023") -> 0 | E45: =COUNTIFS('Datos Preescolar'!$E:$E,E$42,'Datos Preescolar'!$H:$H,">=01/03/2023",'Datos Preescolar'!$H:$H,"<=31/03/2023") -> 0 | F45: =SUM(C45:E45) -> 0 | I45: Marzo | J45: =SUM(C$43:C45) -> 0 | K45: =SUM(D$43:D45) -> 0 | L45: =SUM(E$43:E45) -> 1 | M45: =SUM(J45:L45) -> 1 | P45: Marzo | Q45: =SUM(C$43:C45) -> 0 | R45: =SUM(D$43:D45) -> 0 | S45: =SUM(E$43:E45) -> 1 | T45: =SUM(Q45:S45) -> 1
B46: Abril | C46: =COUNTIFS('Datos Preescolar'!$E:$E,C$42,'Datos Preescolar'!$H:$H,">=01/04/2023",'Datos Preescolar'!$H:$H,"<=30/04/2023") -> 0 | D46: =COUNTIFS('Datos Preescolar'!$E:$E,D$42,'Datos Preescolar'!$H:$H,">=01/04/2023",'Datos Preescolar'!$H:$H,"<=30/04/2023") -> 0 | E46: =COUNTIFS('Datos Preescolar'!$E:$E,E$42,'Datos Preescolar'!$H:$H,">=01/04/2023",'Datos Preescolar'!$H:$H,"<=30/04/2023") -> 0 | F46: =SUM(C46:E46) -> 0 | I46: Abril | J46: =SUM(C$43:C46) -> 0 | K46: =SUM(D$43:D46) -> 0 | L46: =SUM(E$43:E46) -> 1 | M46: =SUM(J46:L46) -> 1 | P46: Abril | Q46: =SUM(C$43:C46) -> 0 | R46: =SUM(D$43:D46) -> 0 | S46: =SUM(E$43:E46) -> 1 | T46: =SUM(Q46:S46) -> 1
B47: Mayo | C47: =COUNTIFS('Datos Preescolar'!$E:$E,C$42,'Datos Preescolar'!$H:$H,">=01/05/2023",'Datos Preescolar'!$H:$H,"<=31/05/2023") -> 0 | D47: =COUNTIFS('Datos Preescolar'!$E:$E,D$42,'Datos Preescolar'!$H:$H,">=01/05/2023",'Datos Preescolar'!$H:$H,"<=31/05/2023") -> 0 | E47: =COUNTIFS('Datos Preescolar'!$E:$E,E$42,'Datos Preescolar'!$H:$H,">=01/05/2023",'Datos Preescolar'!$H:$H,"<=31/05/2023") -> 0 | F47: =SUM(C47:E47) -> 0 | I47: Mayo | J47: =SUM(C$43:C47) -> 0 | K47: =SUM(D$43:D47) -> 0 | L47: =SUM(E$43:E47) -> 1 | M47: =SUM(J47:L47) -> 1 | P47: Mayo | Q47: =SUM(C$43:C47) -> 0 | R47: =SUM(D$43:D47) -> 0 | S47: =SUM(E$43:E47) -> 1 | T47: =SUM(Q47:S47) -> 1
B48: Junio | C48: =COUNTIFS('Datos Preescolar'!$E:$E,C$42,'Datos Preescolar'!$H:$H,">=01/06/2023",'Datos Preescolar'!$H:$H,"<=30/06/2023") -> 0 | D48: =COUNTIFS('Datos Preescolar'!$E:$E,D$42,'Datos Preescolar'!$H:$H,">=01/06/2023",'Datos Preescolar'!$H:$H,"<=30/06/2023") -> 0 | E48: =COUNTIFS('Datos Preescolar'!$E:$E,E$42,'Datos Preescolar'!$H:$H,">=01/06/2023",'Datos Preescolar'!$H:$H,"<=30/06/2023") -> 0 | F48: =SUM(C48:E48) -> 0 | I48: Junio | J48: =SUM(C$43:C48) -> 0 | K48: =SUM(D$43:D48) -> 0 | L48: =SUM(E$43:E48) -> 1 | M48: =SUM(J48:L48) -> 1 | P48: Junio | Q48: =SUM(C$43:C48) -> 0 | R48: =SUM(D$43:D48) -> 0 | S48: =SUM(E$43:E48) -> 1 | T48: =SUM(Q48:S48) -> 1
B49: Julio | C49: =COUNTIFS('Datos Preescolar'!$E:$E,C$42,'Datos Preescolar'!$H:$H,">=01/07/2023",'Datos Preescolar'!$H:$H,"<=31/07/2023") -> 1 | D49: =COUNTIFS('Datos Preescolar'!$E:$E,D$42,'Datos Preescolar'!$H:$H,">=01/07/2023",'Datos Preescolar'!$H:$H,"<=31/07/2023") -> 1 | E49: =COUNTIFS('Datos Preescolar'!$E:$E,E$42,'Datos Preescolar'!$H:$H,">=01/07/2023",'Datos Preescolar'!$H:$H,"<=31/07/2023") -> 1 | F49: =SUM(C49:E49) -> 3 | I49: Julio | J49: =SUM(C$43:C49) -> 1 | K49: =SUM(D$43:D49) -> 1 | L49: =SUM(E$43:E49) -> 2 | M49: =SUM(J49:L49) -> 4 | P49: Julio | Q49: =SUM(C$43:C49) -> 1 | R49: =SUM(D$43:D49) -> 1 | S49: =SUM(E$43:E49) -> 2 | T49: =SUM(Q49:S49) -> 4
B50: Agosto | C50: =COUNTIFS('Datos Preescolar'!$E:$E,C$42,'Datos Preescolar'!$H:$H,">=01/08/2023",'Datos Preescolar'!$H:$H,"<=31/08/2023") -> 0 | D50: =COUNTIFS('Datos Preescolar'!$E:$E,D$42,'Datos Preescolar'!$H:$H,">=01/08/2023",'Datos Preescolar'!$H:$H,"<=31/08/2023") -> 0 | E50: =COUNTIFS('Datos Preescolar'!$E:$E,E$42,'Datos Preescolar'!$H:$H,">=01/08/2023",'Datos Preescolar'!$H:$H,"<=31/08/2023") -> 0 | F50: =SUM(C50:E50) -> 0 | I50: Agosto | J50: =SUM(C$43:C50) -> 1 | K50: =SUM(D$43:D50) -> 1 | L50: =SUM(E$43:E50) -> 2 | M50: =SUM(J50:L50) -> 4 | P50: Agosto | Q50: =SUM(C$43:C50) -> 1 | R50: =SUM(D$43:D50) -> 1 | S50: =SUM(E$43:E50) -> 2 | T50: =SUM(Q50:S50) -> 4
B51: Septiembre | C51: =COUNTIFS('Datos Preescolar'!$E:$E,C$42,'Datos Preescolar'!$H:$H,">=01/09/2023",'Datos Preescolar'!$H:$H,"<=30/09/2023") -> 0 | D51: =COUNTIFS('Datos Preescolar'!$E:$E,D$42,'Datos Preescolar'!$H:$H,">=01/09/2023",'Datos Preescolar'!$H:$H,"<=30/09/2023") -> 0 | E51: =COUNTIFS('Datos Preescolar'!$E:$E,E$42,'Datos Preescolar'!$H:$H,">=01/09/2023",'Datos Preescolar'!$H:$H,"<=30/09/2023") -> 0 | F51: =SUM(C51:E51) -> 0 | I51: Septiembre | J51: =SUM(C$43:C51) -> 1 | K51: =SUM(D$43:D51) -> 1 | L51: =SUM(E$43:E51) -> 2 | M51: =SUM(J51:L51) -> 4 | P51: Septiembre | Q51: =SUM(C$43:C51) -> 1 | R51: =SUM(D$43:D51) -> 1 | S51: =SUM(E$43:E51) -> 2 | T51: =SUM(Q51:S51) -> 4
B52: Octubre | C52: =COUNTIFS('Datos Preescolar'!$E:$E,C$42,'Datos Preescolar'!$H:$H,">=01/10/2023",'Datos Preescolar'!$H:$H,"<=31/10/2023") -> 1 | D52: =COUNTIFS('Datos Preescolar'!$E:$E,D$42,'Datos Preescolar'!$H:$H,">=01/10/2023",'Datos Preescolar'!$H:$H,"<=31/10/2023") -> 0 | E52: =COUNTIFS('Datos Preescolar'!$E:$E,E$42,'Datos Preescolar'!$H:$H,">=01/10/2023",'Datos Preescolar'!$H:$H,"<=31/10/2023") -> 3 | F52: =SUM(C52:E52) -> 4 | I52: Octubre | J52: =SUM(C$43:C52) -> 2 | K52: =SUM(D$43:D52) -> 1 | L52: =SUM(E$43:E52) -> 5 | M52: =SUM(J52:L52) -> 8 | P52: Octubre | Q52: =SUM(C$43:C52) -> 2 | R52: =SUM(D$43:D52) -> 1 | S52: =SUM(E$43:E52) -> 5 | T52: =SUM(Q52:S52) -> 8
B53: Noviembre | C53: =COUNTIFS('Datos Preescolar'!$E:$E,C$42,'Datos Preescolar'!$H:$H,">=01/11/2023",'Datos Preescolar'!$H:$H,"<=30/11/2023") -> 0 | D53: =COUNTIFS('Datos Preescolar'!$E:$E,D$42,'Datos Preescolar'!$H:$H,">=01/11/2023",'Datos Preescolar'!$H:$H,"<=30/11/2023") -> 0 | E53: =COUNTIFS('Datos Preescolar'!$E:$E,E$42,'Datos Preescolar'!$H:$H,">=01/11/2023",'Datos Preescolar'!$H:$H,"<=30/11/2023") -> 0 | F53: =SUM(C53:E53) -> 0 | I53: Noviembre | J53: =SUM(C$43:C53) -> 2 | K53: =SUM(D$43:D53) -> 1 | L53: =SUM(E$43:E53) -> 5 | M53: =SUM(J53:L53) -> 8 | P53: Noviembre | Q53: =SUM(C$43:C53) -> 2 | R53: =SUM(D$43:D53) -> 1 | S53: =SUM(E$43:E53) -> 5 | T53: =SUM(Q53:S53) -> 8
B54: Diciembre | C54: =COUNTIFS('Datos Preescolar'!$E:$E,C$42,'Datos Preescolar'!$H:$H,">=01/12/2023",'Datos Preescolar'!$H:$H,"<=31/12/2023") -> 0 | D54: =COUNTIFS('Datos Preescolar'!$E:$E,D$42,'Datos Preescolar'!$H:$H,">=01/12/2023",'Datos Preescolar'!$H:$H,"<=31/12/2023") -> 0 | E54: =COUNTIFS('Datos Preescolar'!$E:$E,E$42,'Datos Preescolar'!$H:$H,">=01/12/2023",'Datos Preescolar'!$H:$H,"<=31/12/2023") -> 0 | F54: =SUM(C54:E54) -> 0 | I54: Diciembre | J54: =SUM(C$43:C54) -> 2 | K54: =SUM(D$43:D54) -> 1 | L54: =SUM(E$43:E54) -> 5 | M54: =SUM(J54:L54) -> 8 | P54: Diciembre | Q54: =SUM(C$43:C54) -> 2 | R54: =SUM(D$43:D54) -> 1 | S54: =SUM(E$43:E54) -> 5 | T54: =SUM(Q54:S54) -> 8
A55: =A15 -> 2024 | B55: Enero | C55: =COUNTIFS('Datos Preescolar'!$E:$E,C$42,'Datos Preescolar'!$H:$H,">=01/01/2024",'Datos Preescolar'!$H:$H,"<=31/01/2024") -> 0 | D55: =COUNTIFS('Datos Preescolar'!$E:$E,D$42,'Datos Preescolar'!$H:$H,">=01/01/2024",'Datos Preescolar'!$H:$H,"<=31/01/2024") -> 0 | E55: =COUNTIFS('Datos Preescolar'!$E:$E,E$42,'Datos Preescolar'!$H:$H,">=01/01/2024",'Datos Preescolar'!$H:$H,"<=31/01/2024") -> 1 | F55: =SUM(C55:E55) -> 1 | H55: =A55 -> 2024 | I55: Enero | J55: =SUM(C$55:C55) -> 0 | K55: =SUM(D$55:D55) -> 0 | L55: =SUM(E$55:E55) -> 1 | M55: =SUM(J55:L55) -> 1 | O55: =A55 -> 2024 | P55: Enero | Q55: =SUM(C$43:C55) -> 2 | R55: =SUM(D$43:D55) -> 1 | S55: =SUM(E$43:E55) -> 6 | T55: =SUM(Q55:S55) -> 9
B56: Febrero | C56: =COUNTIFS('Datos Preescolar'!$E:$E,C$42,'Datos Preescolar'!$H:$H,">=01/02/2024",'Datos Preescolar'!$H:$H,"<=29/02/2024") -> 0 | D56: =COUNTIFS('Datos Preescolar'!$E:$E,D$42,'Datos Preescolar'!$H:$H,">=01/02/2024",'Datos Preescolar'!$H:$H,"<=29/02/2024") -> 0 | E56: =COUNTIFS('Datos Preescolar'!$E:$E,E$42,'Datos Preescolar'!$H:$H,">=01/02/2024",'Datos Preescolar'!$H:$H,"<=29/02/2024") -> 0 | F56: =SUM(C56:E56) -> 0 | I56: Febrero | J56: =SUM(C$55:C56) -> 0 | K56: =SUM(D$55:D56) -> 0 | L56: =SUM(E$55:E56) -> 1 | M56: =SUM(J56:L56) -> 1 | P56: Febrero | Q56: =SUM(C$43:C56) -> 2 | R56: =SUM(D$43:D56) -> 1 | S56: =SUM(E$43:E56) -> 6 | T56: =SUM(Q56:S56) -> 9
B57: Marzo | C57: =COUNTIFS('Datos Preescolar'!$E:$E,C$42,'Datos Preescolar'!$H:$H,">=01/03/2024",'Datos Preescolar'!$H:$H,"<=31/03/2024") -> 0 | D57: =COUNTIFS('Datos Preescolar'!$E:$E,D$42,'Datos Preescolar'!$H:$H,">=01/03/2024",'Datos Preescolar'!$H:$H,"<=31/03/2024") -> 0 | E57: =COUNTIFS('Datos Preescolar'!$E:$E,E$42,'Datos Preescolar'!$H:$H,">=01/03/2024",'Datos Preescolar'!$H:$H,"<=31/03/2024") -> 0 | F57: =SUM(C57:E57) -> 0 | I57: Marzo | J57: =SUM(C$55:C57) -> 0 | K57: =SUM(D$55:D57) -> 0 | L57: =SUM(E$55:E57) -> 1 | M57: =SUM(J57:L57) -> 1 | P57: Marzo | Q57: =SUM(C$43:C57) -> 2 | R57: =SUM(D$43:D57) -> 1 | S57: =SUM(E$43:E57) -> 6 | T57: =SUM(Q57:S57) -> 9
B58: Abril | C58: =COUNTIFS('Datos Preescolar'!$E:$E,C$42,'Datos Preescolar'!$H:$H,">=01/04/2024",'Datos Preescolar'!$H:$H,"<=30/04/2024") -> 0 | D58: =COUNTIFS('Datos Preescolar'!$E:$E,D$42,'Datos Preescolar'!$H:$H,">=01/04/2024",'Datos Preescolar'!$H:$H,"<=30/04/2024") -> 0 | E58: =COUNTIFS('Datos Preescolar'!$E:$E,E$42,'Datos Preescolar'!$H:$H,">=01/04/2024",'Datos Preescolar'!$H:$H,"<=30/04/2024") -> 0 | F58: =SUM(C58:E58) -> 0 | I58: Abril | J58: =SUM(C$55:C58) -> 0 | K58: =SUM(D$55:D58) -> 0 | L58: =SUM(E$55:E58) -> 1 | M58: =SUM(J58:L58) -> 1 | P58: Abril | Q58: =SUM(C$43:C58) -> 2 | R58: =SUM(D$43:D58) -> 1 | S58: =SUM(E$43:E58) -> 6 | T58: =SUM(Q58:S58) -> 9
B59: Mayo | C59: =COUNTIFS('Datos Preescolar'!$E:$E,C$42,'Datos Preescolar'!$H:$H,">=01/05/2024",'Datos Preescolar'!$H:$H,"<=31/05/2024") -> 0 | D59: =COUNTIFS('Datos Preescolar'!$E:$E,D$42,'Datos Preescolar'!$H:$H,">=01/05/2024",'Datos Preescolar'!$H:$H,"<=31/05/2024") -> 0 | E59: =COUNTIFS('Datos Preescolar'!$E:$E,E$42,'Datos Preescolar'!$H:$H,">=01/05/2024",'Datos Preescolar'!$H:$H,"<=31/05/2024") -> 0 | F59: =SUM(C59:E59) -> 0 | I59: Mayo | J59: =SUM(C$55:C59) -> 0 | K59: =SUM(D$55:D59) -> 0 | L59: =SUM(E$55:E59) -> 1 | M59: =SUM(J59:L59) -> 1 | P59: Mayo | Q59: =SUM(C$43:C59) -> 2 | R59: =SUM(D$43:D59) -> 1 | S59: =SUM(E$43:E59) -> 6 | T59: =SUM(Q59:S59) -> 9
B60: Junio | C60: =COUNTIFS('Datos Preescolar'!$E:$E,C$42,'Datos Preescolar'!$H:$H,">=01/06/2024",'Datos Preescolar'!$H:$H,"<=30/06/2024") -> 0 | D60: =COUNTIFS('Datos Preescolar'!$E:$E,D$42,'Datos Preescolar'!$H:$H,">=01/06/2024",'Datos Preescolar'!$H:$H,"<=30/06/2024") -> 0 | E60: =COUNTIFS('Datos Preescolar'!$E:$E,E$42,'Datos Preescolar'!$H:$H,">=01/06/2024",'Datos Preescolar'!$H:$H,"<=30/06/2024") -> 0 | F60: =SUM(C60:E60) -> 0 | I60: Junio | J60: =SUM(C$55:C60) -> 0 | K60: =SUM(D$55:D60) -> 0 | L60: =SUM(E$55:E60) -> 1 | M60: =SUM(J60:L60) -> 1 | P60: Junio | Q60: =SUM(C$43:C60) -> 2 | R60: =SUM(D$43:D60) -> 1 | S60: =SUM(E$43:E60) -> 6 | T60: =SUM(Q60:S60) -> 9
B61: Julio | C61: =COUNTIFS('Datos Preescolar'!$E:$E,C$42,'Datos Preescolar'!$H:$H,">=01/07/2024",'Datos Preescolar'!$H:$H,"<=31/07/2024") -> 0 | D61: =COUNTIFS('Datos Preescolar'!$E:$E,D$42,'Datos Preescolar'!$H:$H,">=01/07/2024",'Datos Preescolar'!$H:$H,"<=31/07/2024") -> 1 | E61: =COUNTIFS('Datos Preescolar'!$E:$E,E$42,'Datos Preescolar'!$H:$H,">=01/07/2024",'Datos Preescolar'!$H:$H,"<=31/07/2024") -> 1 | F61: =SUM(C61:E61) -> 2 | I61: Julio | J61: =SUM(C$55:C61) -> 0 | K61: =SUM(D$55:D61) -> 1 | L61: =SUM(E$55:E61) -> 2 | M61: =SUM(J61:L61) -> 3 | P61: Julio | Q61: =SUM(C$43:C61) -> 2 | R61: =SUM(D$43:D61) -> 2 | S61: =SUM(E$43:E61) -> 7 | T61: =SUM(Q61:S61) -> 11
B62: Agosto | C62: =COUNTIFS('Datos Preescolar'!$E:$E,C$42,'Datos Preescolar'!$H:$H,">=01/08/2024",'Datos Preescolar'!$H:$H,"<=31/08/2024") -> 0 | D62: =COUNTIFS('Datos Preescolar'!$E:$E,D$42,'Datos Preescolar'!$H:$H,">=01/08/2024",'Datos Preescolar'!$H:$H,"<=31/08/2024") -> 1 | E62: =COUNTIFS('Datos Preescolar'!$E:$E,E$42,'Datos Preescolar'!$H:$H,">=01/08/2024",'Datos Preescolar'!$H:$H,"<=31/08/2024") -> 0 | F62: =SUM(C62:E62) -> 1 | I62: Agosto | J62: =SUM(C$55:C62) -> 0 | K62: =SUM(D$55:D62) -> 2 | L62: =SUM(E$55:E62) -> 2 | M62: =SUM(J62:L62) -> 4 | P62: Agosto | Q62: =SUM(C$43:C62) -> 2 | R62: =SUM(D$43:D62) -> 3 | S62: =SUM(E$43:E62) -> 7 | T62: =SUM(Q62:S62) -> 12
B63: Septiembre | C63: =COUNTIFS('Datos Preescolar'!$E:$E,C$42,'Datos Preescolar'!$H:$H,">=01/09/2024",'Datos Preescolar'!$H:$H,"<=30/09/2024") -> 0 | D63: =COUNTIFS('Datos Preescolar'!$E:$E,D$42,'Datos Preescolar'!$H:$H,">=01/09/2024",'Datos Preescolar'!$H:$H,"<=30/09/2024") -> 0 | E63: =COUNTIFS('Datos Preescolar'!$E:$E,E$42,'Datos Preescolar'!$H:$H,">=01/09/2024",'Datos Preescolar'!$H:$H,"<=30/09/2024") -> 0 | F63: =SUM(C63:E63) -> 0 | I63: Septiembre | J63: =SUM(C$55:C63) -> 0 | K63: =SUM(D$55:D63) -> 2 | L63: =SUM(E$55:E63) -> 2 | M63: =SUM(J63:L63) -> 4 | P63: Septiembre | Q63: =SUM(C$43:C63) -> 2 | R63: =SUM(D$43:D63) -> 3 | S63: =SUM(E$43:E63) -> 7 | T63: =SUM(Q63:S63) -> 12
B64: Octubre | C64: =COUNTIFS('Datos Preescolar'!$E:$E,C$42,'Datos Preescolar'!$H:$H,">=01/10/2024",'Datos Preescolar'!$H:$H,"<=31/10/2024") -> 0 | D64: =COUNTIFS('Datos Preescolar'!$E:$E,D$42,'Datos Preescolar'!$H:$H,">=01/10/2024",'Datos Preescolar'!$H:$H,"<=31/10/2024") -> 1 | E64: =COUNTIFS('Datos Preescolar'!$E:$E,E$42,'Datos Preescolar'!$H:$H,">=01/10/2024",'Datos Preescolar'!$H:$H,"<=31/10/2024") -> 0 | F64: =SUM(C64:E64) -> 1 | I64: Octubre | J64: =SUM(C$55:C64) -> 0 | K64: =SUM(D$55:D64) -> 3 | L64: =SUM(E$55:E64) -> 2 | M64: =SUM(J64:L64) -> 5 | P64: Octubre | Q64: =SUM(C$43:C64) -> 2 | R64: =SUM(D$43:D64) -> 4 | S64: =SUM(E$43:E64) -> 7 | T64: =SUM(Q64:S64) -> 13
B65: Noviembre | C65: =COUNTIFS('Datos Preescolar'!$E:$E,C$42,'Datos Preescolar'!$H:$H,">=01/11/2024",'Datos Preescolar'!$H:$H,"<=30/11/2024") -> 2 | D65: =COUNTIFS('Datos Preescolar'!$E:$E,D$42,'Datos Preescolar'!$H:$H,">=01/11/2024",'Datos Preescolar'!$H:$H,"<=30/11/2024") -> 0 | E65: =COUNTIFS('Datos Preescolar'!$E:$E,E$42,'Datos Preescolar'!$H:$H,">=01/11/2024",'Datos Preescolar'!$H:$H,"<=30/11/2024") -> 0 | F65: =SUM(C65:E65) -> 2 | I65: Noviembre | J65: =SUM(C$55:C65) -> 2 | K65: =SUM(D$55:D65) -> 3 | L65: =SUM(E$55:E65) -> 2 | M65: =SUM(J65:L65) -> 7 | P65: Noviembre | Q65: =SUM(C$43:C65) -> 4 | R65: =SUM(D$43:D65) -> 4 | S65: =SUM(E$43:E65) -> 7 | T65: =SUM(Q65:S65) -> 15
B66: Diciembre | C66: =COUNTIFS('Datos Preescolar'!$E:$E,C$42,'Datos Preescolar'!$H:$H,">=01/12/2024",'Datos Preescolar'!$H:$H,"<=31/12/2024") -> 0 | D66: =COUNTIFS('Datos Preescolar'!$E:$E,D$42,'Datos Preescolar'!$H:$H,">=01/12/2024",'Datos Preescolar'!$H:$H,"<=31/12/2024") -> 0 | E66: =COUNTIFS('Datos Preescolar'!$E:$E,E$42,'Datos Preescolar'!$H:$H,">=01/12/2024",'Datos Preescolar'!$H:$H,"<=31/12/2024") -> 0 | F66: =SUM(C66:E66) -> 0 | I66: Diciembre | J66: =SUM(C$55:C66) -> 2 | K66: =SUM(D$55:D66) -> 3 | L66: =SUM(E$55:E66) -> 2 | M66: =SUM(J66:L66) -> 7 | P66: Diciembre | Q66: =SUM(C$43:C66) -> 4 | R66: =SUM(D$43:D66) -> 4 | S66: =SUM(E$43:E66) -> 7 | T66: =SUM(Q66:S66) -> 15
A67: =A27 -> 2025 | B67: Enero | C67: =COUNTIFS('Datos Preescolar'!$E:$E,C$42,'Datos Preescolar'!$H:$H,">=01/01/2025",'Datos Preescolar'!$H:$H,"<=31/01/2025") -> 1 | D67: =COUNTIFS('Datos Preescolar'!$E:$E,D$42,'Datos Preescolar'!$H:$H,">=01/01/2025",'Datos Preescolar'!$H:$H,"<=31/01/2025") -> 1 | E67: =COUNTIFS('Datos Preescolar'!$E:$E,E$42,'Datos Preescolar'!$H:$H,">=01/01/2025",'Datos Preescolar'!$H:$H,"<=31/01/2025") -> 3 | F67: =SUM(C67:E67) -> 5 | H67: =A67 -> 2025 | I67: Enero | J67: =SUM(C$67:C67) -> 1 | K67: =SUM(D$67:D67) -> 1 | L67: =SUM(E$67:E67) -> 3 | M67: =SUM(J67:L67) -> 5 | O67: =A67 -> 2025 | P67: Enero | Q67: =SUM(C$43:C67) -> 5 | R67: =SUM(D$43:D67) -> 5 | S67: =SUM(E$43:E67) -> 10 | T67: =SUM(Q67:S67) -> 20
B68: Febrero | C68: =COUNTIFS('Datos Preescolar'!$E:$E,C$42,'Datos Preescolar'!$H:$H,">=01/02/2025",'Datos Preescolar'!$H:$H,"<=28/02/2025") -> 0 | D68: =COUNTIFS('Datos Preescolar'!$E:$E,D$42,'Datos Preescolar'!$H:$H,">=01/02/2025",'Datos Preescolar'!$H:$H,"<=28/02/2025") -> 0 | E68: =COUNTIFS('Datos Preescolar'!$E:$E,E$42,'Datos Preescolar'!$H:$H,">=01/02/2025",'Datos Preescolar'!$H:$H,"<=28/02/2025") -> 0 | F68: =SUM(C68:E68) -> 0 | I68: Febrero | J68: =SUM(C$67:C68) -> 1 | K68: =SUM(D$67:D68) -> 1 | L68: =SUM(E$67:E68) -> 3 | M68: =SUM(J68:L68) -> 5 | P68: Febrero | Q68: =SUM(C$43:C68) -> 5 | R68: =SUM(D$43:D68) -> 5 | S68: =SUM(E$43:E68) -> 10 | T68: =SUM(Q68:S68) -> 20
B69: Marzo | C69: =COUNTIFS('Datos Preescolar'!$E:$E,C$42,'Datos Preescolar'!$H:$H,">=01/03/2025",'Datos Preescolar'!$H:$H,"<=31/03/2025") -> 0 | D69: =COUNTIFS('Datos Preescolar'!$E:$E,D$42,'Datos Preescolar'!$H:$H,">=01/03/2025",'Datos Preescolar'!$H:$H,"<=31/03/2025") -> 0 | E69: =COUNTIFS('Datos Preescolar'!$E:$E,E$42,'Datos Preescolar'!$H:$H,">=01/03/2025",'Datos Preescolar'!$H:$H,"<=31/03/2025") -> 0 | F69: =SUM(C69:E69) -> 0 | I69: Marzo | J69: =SUM(C$67:C69) -> 1 | K69: =SUM(D$67:D69) -> 1 | L69: =SUM(E$67:E69) -> 3 | M69: =SUM(J69:L69) -> 5 | P69: Marzo | Q69: =SUM(C$43:C69) -> 5 | R69: =SUM(D$43:D69) -> 5 | S69: =SUM(E$43:E69) -> 10 | T69: =SUM(Q69:S69) -> 20
B70: Abril | C70: =COUNTIFS('Datos Preescolar'!$E:$E,C$42,'Datos Preescolar'!$H:$H,">=01/04/2025",'Datos Preescolar'!$H:$H,"<=30/04/2025") -> 0 | D70: =COUNTIFS('Datos Preescolar'!$E:$E,D$42,'Datos Preescolar'!$H:$H,">=01/04/2025",'Datos Preescolar'!$H:$H,"<=30/04/2025") -> 1 | E70: =COUNTIFS('Datos Preescolar'!$E:$E,E$42,'Datos Preescolar'!$H:$H,">=01/04/2025",'Datos Preescolar'!$H:$H,"<=30/04/2025") -> 0 | F70: =SUM(C70:E70) -> 1 | I70: Abril | J70: =SUM(C$67:C70) -> 1 | K70: =SUM(D$67:D70) -> 2 | L70: =SUM(E$67:E70) -> 3 | M70: =SUM(J70:L70) -> 6 | P70: Abril | Q70: =SUM(C$43:C70) -> 5 | R70: =SUM(D$43:D70) -> 6 | S70: =SUM(E$43:E70) -> 10 | T70: =SUM(Q70:S70) -> 21
B71: Mayo | C71: =COUNTIFS('Datos Preescolar'!$E:$E,C$42,'Datos Preescolar'!$H:$H,">=01/05/2025",'Datos Preescolar'!$H:$H,"<=31/05/2025") -> 0 | D71: =COUNTIFS('Datos Preescolar'!$E:$E,D$42,'Datos Preescolar'!$H:$H,">=01/05/2025",'Datos Preescolar'!$H:$H,"<=31/05/2025") -> 0 | E71: =COUNTIFS('Datos Preescolar'!$E:$E,E$42,'Datos Preescolar'!$H:$H,">=01/05/2025",'Datos Preescolar'!$H:$H,"<=31/05/2025") -> 1 | F71: =SUM(C71:E71) -> 1 | I71: Mayo | J71: =SUM(C$67:C71) -> 1 | K71: =SUM(D$67:D71) -> 2 | L71: =SUM(E$67:E71) -> 4 | M71: =SUM(J71:L71) -> 7 | P71: Mayo | Q71: =SUM(C$43:C71) -> 5 | R71: =SUM(D$43:D71) -> 6 | S71: =SUM(E$43:E71) -> 11 | T71: =SUM(Q71:S71) -> 22
B72: Junio | C72: =COUNTIFS('Datos Preescolar'!$E:$E,C$42,'Datos Preescolar'!$H:$H,">=01/06/2025",'Datos Preescolar'!$H:$H,"<=30/06/2025") -> 0 | D72: =COUNTIFS('Datos Preescolar'!$E:$E,D$42,'Datos Preescolar'!$H:$H,">=01/06/2025",'Datos Preescolar'!$H:$H,"<=30/06/2025") -> 0 | E72: =COUNTIFS('Datos Preescolar'!$E:$E,E$42,'Datos Preescolar'!$H:$H,">=01/06/2025",'Datos Preescolar'!$H:$H,"<=30/06/2025") -> 0 | F72: =SUM(C72:E72) -> 0 | I72: Junio | J72: =SUM(C$67:C72) -> 1 | K72: =SUM(D$67:D72) -> 2 | L72: =SUM(E$67:E72) -> 4 | M72: =SUM(J72:L72) -> 7 | P72: Junio | Q72: =SUM(C$43:C72) -> 5 | R72: =SUM(D$43:D72) -> 6 | S72: =SUM(E$43:E72) -> 11 | T72: =SUM(Q72:S72) -> 22
B73: Julio | C73: =COUNTIFS('Datos Preescolar'!$E:$E,C$42,'Datos Preescolar'!$H:$H,">=01/07/2025",'Datos Preescolar'!$H:$H,"<=31/07/2025") -> 1 | D73: =COUNTIFS('Datos Preescolar'!$E:$E,D$42,'Datos Preescolar'!$H:$H,">=01/07/2025",'Datos Preescolar'!$H:$H,"<=31/07/2025") -> 1 | E73: =COUNTIFS('Datos Preescolar'!$E:$E,E$42,'Datos Preescolar'!$H:$H,">=01/07/2025",'Datos Preescolar'!$H:$H,"<=31/07/2025") -> 0 | F73: =SUM(C73:E73) -> 2 | I73: Julio | J73: =SUM(C$67:C73) -> 2 | K73: =SUM(D$67:D73) -> 3 | L73: =SUM(E$67:E73) -> 4 | M73: =SUM(J73:L73) -> 9 | P73: Julio | Q73: =SUM(C$43:C73) -> 6 | R73: =SUM(D$43:D73) -> 7 | S73: =SUM(E$43:E73) -> 11 | T73: =SUM(Q73:S73) -> 24
B74: Agosto | C74: =COUNTIFS('Datos Preescolar'!$E:$E,C$42,'Datos Preescolar'!$H:$H,">=01/08/2025",'Datos Preescolar'!$H:$H,"<=31/08/2025") -> 0 | D74: =COUNTIFS('Datos Preescolar'!$E:$E,D$42,'Datos Preescolar'!$H:$H,">=01/08/2025",'Datos Preescolar'!$H:$H,"<=31/08/2025") -> 0 | E74: =COUNTIFS('Datos Preescolar'!$E:$E,E$42,'Datos Preescolar'!$H:$H,">=01/08/2025",'Datos Preescolar'!$H:$H,"<=31/08/2025") -> 0 | F74: =SUM(C74:E74) -> 0 | I74: Agosto | J74: =SUM(C$67:C74) -> 2 | K74: =SUM(D$67:D74) -> 3 | L74: =SUM(E$67:E74) -> 4 | M74: =SUM(J74:L74) -> 9 | P74: Agosto | Q74: =SUM(C$43:C74) -> 6 | R74: =SUM(D$43:D74) -> 7 | S74: =SUM(E$43:E74) -> 11 | T74: =SUM(Q74:S74) -> 24
B75: Septiembre | C75: =COUNTIFS('Datos Preescolar'!$E:$E,C$42,'Datos Preescolar'!$H:$H,">=01/09/2025",'Datos Preescolar'!$H:$H,"<=30/09/2025") -> 0 | D75: =COUNTIFS('Datos Preescolar'!$E:$E,D$42,'Datos Preescolar'!$H:$H,">=01/09/2025",'Datos Preescolar'!$H:$H,"<=30/09/2025") -> 1 | E75: =COUNTIFS('Datos Preescolar'!$E:$E,E$42,'Datos Preescolar'!$H:$H,">=01/09/2025",'Datos Preescolar'!$H:$H,"<=30/09/2025") -> 1 | F75: =SUM(C75:E75) -> 2 | I75: Septiembre | J75: =SUM(C$67:C75) -> 2 | K75: =SUM(D$67:D75) -> 4 | L75: =SUM(E$67:E75) -> 5 | M75: =SUM(J75:L75) -> 11 | P75: Septiembre | Q75: =SUM(C$43:C75) -> 6 | R75: =SUM(D$43:D75) -> 8 | S75: =SUM(E$43:E75) -> 12 | T75: =SUM(Q75:S75) -> 26
B76: Octubre | C76: =COUNTIFS('Datos Preescolar'!$E:$E,C$42,'Datos Preescolar'!$H:$H,">=01/10/2025",'Datos Preescolar'!$H:$H,"<=31/10/2025") -> 1 | D76: =COUNTIFS('Datos Preescolar'!$E:$E,D$42,'Datos Preescolar'!$H:$H,">=01/10/2025",'Datos Preescolar'!$H:$H,"<=31/10/2025") -> 1 | E76: =COUNTIFS('Datos Preescolar'!$E:$E,E$42,'Datos Preescolar'!$H:$H,">=01/10/2025",'Datos Preescolar'!$H:$H,"<=31/10/2025") -> 1 | F76: =SUM(C76:E76) -> 3 | I76: Octubre | J76: =SUM(C$67:C76) -> 3 | K76: =SUM(D$67:D76) -> 5 | L76: =SUM(E$67:E76) -> 6 | M76: =SUM(J76:L76) -> 14 | P76: Octubre | Q76: =SUM(C$43:C76) -> 7 | R76: =SUM(D$43:D76) -> 9 | S76: =SUM(E$43:E76) -> 13 | T76: =SUM(Q76:S76) -> 29
B77: Noviembre | C77: =COUNTIFS('Datos Preescolar'!$E:$E,C$42,'Datos Preescolar'!$H:$H,">=01/11/2025",'Datos Preescolar'!$H:$H,"<=30/11/2025") -> 0 | D77: =COUNTIFS('Datos Preescolar'!$E:$E,D$42,'Datos Preescolar'!$H:$H,">=01/11/2025",'Datos Preescolar'!$H:$H,"<=30/11/2025") -> 0 | E77: =COUNTIFS('Datos Preescolar'!$E:$E,E$42,'Datos Preescolar'!$H:$H,">=01/11/2025",'Datos Preescolar'!$H:$H,"<=30/11/2025") -> 0 | F77: =SUM(C77:E77) -> 0 | I77: Noviembre | J77: =SUM(C$67:C77) -> 3 | K77: =SUM(D$67:D77) -> 5 | L77: =SUM(E$67:E77) -> 6 | M77: =SUM(J77:L77) -> 14 | P77: Noviembre | Q77: =SUM(C$43:C77) -> 7 | R77: =SUM(D$43:D77) -> 9 | S77: =SUM(E$43:E77) -> 13 | T77: =SUM(Q77:S77) -> 29
B78: Diciembre | C78: =COUNTIFS('Datos Preescolar'!$E:$E,C$42,'Datos Preescolar'!$H:$H,">=01/12/2025",'Datos Preescolar'!$H:$H,"<=31/12/2025") -> 0 | D78: =COUNTIFS('Datos Preescolar'!$E:$E,D$42,'Datos Preescolar'!$H:$H,">=01/12/2025",'Datos Preescolar'!$H:$H,"<=31/12/2025") -> 0 | E78: =COUNTIFS('Datos Preescolar'!$E:$E,E$42,'Datos Preescolar'!$H:$H,">=01/12/2025",'Datos Preescolar'!$H:$H,"<=31/12/2025") -> 0 | F78: =SUM(C78:E78) -> 0 | I78: Diciembre | J78: =SUM(C$67:C78) -> 3 | K78: =SUM(D$67:D78) -> 5 | L78: =SUM(E$67:E78) -> 6 | M78: =SUM(J78:L78) -> 14 | P78: Diciembre | Q78: =SUM(C$43:C78) -> 7 | R78: =SUM(D$43:D78) -> 9 | S78: =SUM(E$43:E78) -> 13 | T78: =SUM(Q78:S78) -> 29
B81: Matrículas por mes | I81: Matrículas acumulado por año | P81: Matrículas acumulado todos los años
B82: MES | C82: Prejardín | D82: Jardín | E82: Transición | F82: TOTAL | I82: MES | J82: Prejardín | K82: Jardín | L82: Transición | M82: TOTAL | P82: MES | Q82: Prejardín | R82: Jardín | S82: Transición | T82: TOTAL
A83: =A3 -> 2023 | B83: Enero | C83: =COUNTIFS('Datos Preescolar'!$E:$E,C$82,'Datos Preescolar'!$I:$I,">=01/01/2023",'Datos Preescolar'!$I:$I,"<=31/01/2023") -> 0 | D83: =COUNTIFS('Datos Preescolar'!$E:$E,D$82,'Datos Preescolar'!$I:$I,">=01/01/2023",'Datos Preescolar'!$I:$I,"<=31/01/2023") -> 0 | E83: =COUNTIFS('Datos Preescolar'!$E:$E,E$82,'Datos Preescolar'!$I:$I,">=01/01/2023",'Datos Preescolar'!$I:$I,"<=31/01/2023") -> 0 | F83: =SUM(C83:E83) -> 0 | H83: =A83 -> 2023 | I83: Enero | J83: =SUM(C$83:C83) -> 0 | K83: =SUM(D$83:D83) -> 0 | L83: =SUM(E$83:E83) -> 0 | M83: =SUM(J83:L83) -> 0 | O83: =A83 -> 2023 | P83: Enero | Q83: =SUM(C$83:C83) -> 0 | R83: =SUM(D$83:D83) -> 0 | S83: =SUM(E$83:E83) -> 0 | T83: =SUM(Q83:S83) -> 0
B84: Febrero | C84: =COUNTIFS('Datos Preescolar'!$E:$E,C$82,'Datos Preescolar'!$I:$I,">=01/02/2023",'Datos Preescolar'!$I:$I,"<=28/02/2023") -> 0 | D84: =COUNTIFS('Datos Preescolar'!$E:$E,D$82,'Datos Preescolar'!$I:$I,">=01/02/2023",'Datos Preescolar'!$I:$I,"<=28/02/2023") -> 0 | E84: =COUNTIFS('Datos Preescolar'!$E:$E,E$82,'Datos Preescolar'!$I:$I,">=01/02/2023",'Datos Preescolar'!$I:$I,"<=28/02/2023") -> 1 | F84: =SUM(C84:E84) -> 1 | I84: Febrero | J84: =SUM(C$83:C84) -> 0 | K84: =SUM(D$83:D84) -> 0 | L84: =SUM(E$83:E84) -> 1 | M84: =SUM(J84:L84) -> 1 | P84: Febrero | Q84: =SUM(C$83:C84) -> 0 | R84: =SUM(D$83:D84) -> 0 | S84: =SUM(E$83:E84) -> 1 | T84: =SUM(Q84:S84) -> 1
B85: Marzo | C85: =COUNTIFS('Datos Preescolar'!$E:$E,C$82,'Datos Preescolar'!$I:$I,">=01/03/2023",'Datos Preescolar'!$I:$I,"<=31/03/2023") -> 0 | D85: =COUNTIFS('Datos Preescolar'!$E:$E,D$82,'Datos Preescolar'!$I:$I,">=01/03/2023",'Datos Preescolar'!$I:$I,"<=31/03/2023") -> 0 | E85: =COUNTIFS('Datos Preescolar'!$E:$E,E$82,'Datos Preescolar'!$I:$I,">=01/03/2023",'Datos Preescolar'!$I:$I,"<=31/03/2023") -> 0 | F85: =SUM(C85:E85) -> 0 | I85: Marzo | J85: =SUM(C$83:C85) -> 0 | K85: =SUM(D$83:D85) -> 0 | L85: =SUM(E$83:E85) -> 1 | M85: =SUM(J85:L85) -> 1 | P85: Marzo | Q85: =SUM(C$83:C85) -> 0 | R85: =SUM(D$83:D85) -> 0 | S85: =SUM(E$83:E85) -> 1 | T85: =SUM(Q85:S85) -> 1
B86: Abril | C86: =COUNTIFS('Datos Preescolar'!$E:$E,C$82,'Datos Preescolar'!$I:$I,">=01/04/2023",'Datos Preescolar'!$I:$I,"<=30/04/2023") -> 0 | D86: =COUNTIFS('Datos Preescolar'!$E:$E,D$82,'Datos Preescolar'!$I:$I,">=01/04/2023",'Datos Preescolar'!$I:$I,"<=30/04/2023") -> 0 | E86: =COUNTIFS('Datos Preescolar'!$E:$E,E$82,'Datos Preescolar'!$I:$I,">=01/04/2023",'Datos Preescolar'!$I:$I,"<=30/04/2023") -> 0 | F86: =SUM(C86:E86) -> 0 | I86: Abril | J86: =SUM(C$83:C86) -> 0 | K86: =SUM(D$83:D86) -> 0 | L86: =SUM(E$83:E86) -> 1 | M86: =SUM(J86:L86) -> 1 | P86: Abril | Q86: =SUM(C$83:C86) -> 0 | R86: =SUM(D$83:D86) -> 0 | S86: =SUM(E$83:E86) -> 1 | T86: =SUM(Q86:S86) -> 1
B87: Mayo | C87: =COUNTIFS('Datos Preescolar'!$E:$E,C$82,'Datos Preescolar'!$I:$I,">=01/05/2023",'Datos Preescolar'!$I:$I,"<=31/05/2023") -> 0 | D87: =COUNTIFS('Datos Preescolar'!$E:$E,D$82,'Datos Preescolar'!$I:$I,">=01/05/2023",'Datos Preescolar'!$I:$I,"<=31/05/2023") -> 0 | E87: =COUNTIFS('Datos Preescolar'!$E:$E,E$82,'Datos Preescolar'!$I:$I,">=01/05/2023",'Datos Preescolar'!$I:$I,"<=31/05/2023") -> 0 | F87: =SUM(C87:E87) -> 0 | I87: Mayo | J87: =SUM(C$83:C87) -> 0 | K87: =SUM(D$83:D87) -> 0 | L87: =SUM(E$83:E87) -> 1 | M87: =SUM(J87:L87) -> 1 | P87: Mayo | Q87: =SUM(C$83:C87) -> 0 | R87: =SUM(D$83:D87) -> 0 | S87: =SUM(E$83:E87) -> 1 | T87: =SUM(Q87:S87) -> 1
B88: Junio | C88: =COUNTIFS('Datos Preescolar'!$E:$E,C$82,'Datos Preescolar'!$I:$I,">=01/06/2023",'Datos Preescolar'!$I:$I,"<=30/06/2023") -> 0 | D88: =COUNTIFS('Datos Preescolar'!$E:$E,D$82,'Datos Preescolar'!$I:$I,">=01/06/2023",'Datos Preescolar'!$I:$I,"<=30/06/2023") -> 0 | E88: =COUNTIFS('Datos Preescolar'!$E:$E,E$82,'Datos Preescolar'!$I:$I,">=01/06/2023",'Datos Preescolar'!$I:$I,"<=30/06/2023") -> 0 | F88: =SUM(C88:E88) -> 0 | I88: Junio | J88: =SUM(C$83:C88) -> 0 | K88: =SUM(D$83:D88) -> 0 | L88: =SUM(E$83:E88) -> 1 | M88: =SUM(J88:L88) -> 1 | P88: Junio | Q88: =SUM(C$83:C88) -> 0 | R88: =SUM(D$83:D88) -> 0 | S88: =SUM(E$83:E88) -> 1 | T88: =SUM(Q88:S88) -> 1
B89: Julio | C89: =COUNTIFS('Datos Preescolar'!$E:$E,C$82,'Datos Preescolar'!$I:$I,">=01/07/2023",'Datos Preescolar'!$I:$I,"<=31/07/2023") -> 1 | D89: =COUNTIFS('Datos Preescolar'!$E:$E,D$82,'Datos Preescolar'!$I:$I,">=01/07/2023",'Datos Preescolar'!$I:$I,"<=31/07/2023") -> 0 | E89: =COUNTIFS('Datos Preescolar'!$E:$E,E$82,'Datos Preescolar'!$I:$I,">=01/07/2023",'Datos Preescolar'!$I:$I,"<=31/07/2023") -> 1 | F89: =SUM(C89:E89) -> 2 | I89: Julio | J89: =SUM(C$83:C89) -> 1 | K89: =SUM(D$83:D89) -> 0 | L89: =SUM(E$83:E89) -> 2 | M89: =SUM(J89:L89) -> 3 | P89: Julio | Q89: =SUM(C$83:C89) -> 1 | R89: =SUM(D$83:D89) -> 0 | S89: =SUM(E$83:E89) -> 2 | T89: =SUM(Q89:S89) -> 3
B90: Agosto | C90: =COUNTIFS('Datos Preescolar'!$E:$E,C$82,'Datos Preescolar'!$I:$I,">=01/08/2023",'Datos Preescolar'!$I:$I,"<=31/08/2023") -> 0 | D90: =COUNTIFS('Datos Preescolar'!$E:$E,D$82,'Datos Preescolar'!$I:$I,">=01/08/2023",'Datos Preescolar'!$I:$I,"<=31/08/2023") -> 1 | E90: =COUNTIFS('Datos Preescolar'!$E:$E,E$82,'Datos Preescolar'!$I:$I,">=01/08/2023",'Datos Preescolar'!$I:$I,"<=31/08/2023") -> 0 | F90: =SUM(C90:E90) -> 1 | I90: Agosto | J90: =SUM(C$83:C90) -> 1 | K90: =SUM(D$83:D90) -> 1 | L90: =SUM(E$83:E90) -> 2 | M90: =SUM(J90:L90) -> 4 | P90: Agosto | Q90: =SUM(C$83:C90) -> 1 | R90: =SUM(D$83:D90) -> 1 | S90: =SUM(E$83:E90) -> 2 | T90: =SUM(Q90:S90) -> 4
B91: Septiembre | C91: =COUNTIFS('Datos Preescolar'!$E:$E,C$82,'Datos Preescolar'!$I:$I,">=01/09/2023",'Datos Preescolar'!$I:$I,"<=30/09/2023") -> 0 | D91: =COUNTIFS('Datos Preescolar'!$E:$E,D$82,'Datos Preescolar'!$I:$I,">=01/09/2023",'Datos Preescolar'!$I:$I,"<=30/09/2023") -> 0 | E91: =COUNTIFS('Datos Preescolar'!$E:$E,E$82,'Datos Preescolar'!$I:$I,">=01/09/2023",'Datos Preescolar'!$I:$I,"<=30/09/2023") -> 0 | F91: =SUM(C91:E91) -> 0 | I91: Septiembre | J91: =SUM(C$83:C91) -> 1 | K91: =SUM(D$83:D91) -> 1 | L91: =SUM(E$83:E91) -> 2 | M91: =SUM(J91:L91) -> 4 | P91: Septiembre | Q91: =SUM(C$83:C91) -> 1 | R91: =SUM(D$83:D91) -> 1 | S91: =SUM(E$83:E91) -> 2 | T91: =SUM(Q91:S91) -> 4
B92: Octubre | C92: =COUNTIFS('Datos Preescolar'!$E:$E,C$82,'Datos Preescolar'!$I:$I,">=01/10/2023",'Datos Preescolar'!$I:$I,"<=31/10/2023") -> 0 | D92: =COUNTIFS('Datos Preescolar'!$E:$E,D$82,'Datos Preescolar'!$I:$I,">=01/10/2023",'Datos Preescolar'!$I:$I,"<=31/10/2023") -> 0 | E92: =COUNTIFS('Datos Preescolar'!$E:$E,E$82,'Datos Preescolar'!$I:$I,">=01/10/2023",'Datos Preescolar'!$I:$I,"<=31/10/2023") -> 0 | F92: =SUM(C92:E92) -> 0 | I92: Octubre | J92: =SUM(C$83:C92) -> 1 | K92: =SUM(D$83:D92) -> 1 | L92: =SUM(E$83:E92) -> 2 | M92: =SUM(J92:L92) -> 4 | P92: Octubre | Q92: =SUM(C$83:C92) -> 1 | R92: =SUM(D$83:D92) -> 1 | S92: =SUM(E$83:E92) -> 2 | T92: =SUM(Q92:S92) -> 4
B93: Noviembre | C93: =COUNTIFS('Datos Preescolar'!$E:$E,C$82,'Datos Preescolar'!$I:$I,">=01/11/2023",'Datos Preescolar'!$I:$I,"<=30/11/2023") -> 0 | D93: =COUNTIFS('Datos Preescolar'!$E:$E,D$82,'Datos Preescolar'!$I:$I,">=01/11/2023",'Datos Preescolar'!$I:$I,"<=30/11/2023") -> 0 | E93: =COUNTIFS('Datos Preescolar'!$E:$E,E$82,'Datos Preescolar'!$I:$I,">=01/11/2023",'Datos Preescolar'!$I:$I,"<=30/11/2023") -> 0 | F93: =SUM(C93:E93) -> 0 | I93: Noviembre | J93: =SUM(C$83:C93) -> 1 | K93: =SUM(D$83:D93) -> 1 | L93: =SUM(E$83:E93) -> 2 | M93: =SUM(J93:L93) -> 4 | P93: Noviembre | Q93: =SUM(C$83:C93) -> 1 | R93: =SUM(D$83:D93) -> 1 | S93: =SUM(E$83:E93) -> 2 | T93: =SUM(Q93:S93) -> 4
B94: Diciembre | C94: =COUNTIFS('Datos Preescolar'!$E:$E,C$82,'Datos Preescolar'!$I:$I,">=01/12/2023",'Datos Preescolar'!$I:$I,"<=31/12/2023") -> 0 | D94: =COUNTIFS('Datos Preescolar'!$E:$E,D$82,'Datos Preescolar'!$I:$I,">=01/12/2023",'Datos Preescolar'!$I:$I,"<=31/12/2023") -> 0 | E94: =COUNTIFS('Datos Preescolar'!$E:$E,E$82,'Datos Preescolar'!$I:$I,">=01/12/2023",'Datos Preescolar'!$I:$I,"<=31/12/2023") -> 0 | F94: =SUM(C94:E94) -> 0 | I94: Diciembre | J94: =SUM(C$83:C94) -> 1 | K94: =SUM(D$83:D94) -> 1 | L94: =SUM(E$83:E94) -> 2 | M94: =SUM(J94:L94) -> 4 | P94: Diciembre | Q94: =SUM(C$83:C94) -> 1 | R94: =SUM(D$83:D94) -> 1 | S94: =SUM(E$83:E94) -> 2 | T94: =SUM(Q94:S94) -> 4
A95: =A15 -> 2024 | B95: Enero | C95: =COUNTIFS('Datos Preescolar'!$E:$E,C$82,'Datos Preescolar'!$I:$I,">=01/01/2024",'Datos Preescolar'!$I:$I,"<=31/01/2024") -> 1 | D95: =COUNTIFS('Datos Preescolar'!$E:$E,D$82,'Datos Preescolar'!$I:$I,">=01/01/2024",'Datos Preescolar'!$I:$I,"<=31/01/2024") -> 0 | E95: =COUNTIFS('Datos Preescolar'!$E:$E,E$82,'Datos Preescolar'!$I:$I,">=01/01/2024",'Datos Preescolar'!$I:$I,"<=31/01/2024") -> 2 | F95: =SUM(C95:E95) -> 3 | H95: =A95 -> 2024 | I95: Enero | J95: =SUM(C$95:C95) -> 1 | K95: =SUM(D$95:D95) -> 0 | L95: =SUM(E$95:E95) -> 2 | M95: =SUM(J95:L95) -> 3 | O95: =A95 -> 2024 | P95: Enero | Q95: =SUM(C$83:C95) -> 2 | R95: =SUM(D$83:D95) -> 1 | S95: =SUM(E$83:E95) -> 4 | T95: =SUM(Q95:S95) -> 7
B96: Febrero | C96: =COUNTIFS('Datos Preescolar'!$E:$E,C$82,'Datos Preescolar'!$I:$I,">=01/02/2024",'Datos Preescolar'!$I:$I,"<=29/02/2024") -> 0 | D96: =COUNTIFS('Datos Preescolar'!$E:$E,D$82,'Datos Preescolar'!$I:$I,">=01/02/2024",'Datos Preescolar'!$I:$I,"<=29/02/2024") -> 0 | E96: =COUNTIFS('Datos Preescolar'!$E:$E,E$82,'Datos Preescolar'!$I:$I,">=01/02/2024",'Datos Preescolar'!$I:$I,"<=29/02/2024") -> 1 | F96: =SUM(C96:E96) -> 1 | I96: Febrero | J96: =SUM(C$95:C96) -> 1 | K96: =SUM(D$95:D96) -> 0 | L96: =SUM(E$95:E96) -> 3 | M96: =SUM(J96:L96) -> 4 | P96: Febrero | Q96: =SUM(C$83:C96) -> 2 | R96: =SUM(D$83:D96) -> 1 | S96: =SUM(E$83:E96) -> 5 | T96: =SUM(Q96:S96) -> 8
B97: Marzo | C97: =COUNTIFS('Datos Preescolar'!$E:$E,C$82,'Datos Preescolar'!$I:$I,">=01/03/2024",'Datos Preescolar'!$I:$I,"<=31/03/2024") -> 0 | D97: =COUNTIFS('Datos Preescolar'!$E:$E,D$82,'Datos Preescolar'!$I:$I,">=01/03/2024",'Datos Preescolar'!$I:$I,"<=31/03/2024") -> 0 | E97: =COUNTIFS('Datos Preescolar'!$E:$E,E$82,'Datos Preescolar'!$I:$I,">=01/03/2024",'Datos Preescolar'!$I:$I,"<=31/03/2024") -> 0 | F97: =SUM(C97:E97) -> 0 | I97: Marzo | J97: =SUM(C$95:C97) -> 1 | K97: =SUM(D$95:D97) -> 0 | L97: =SUM(E$95:E97) -> 3 | M97: =SUM(J97:L97) -> 4 | P97: Marzo | Q97: =SUM(C$83:C97) -> 2 | R97: =SUM(D$83:D97) -> 1 | S97: =SUM(E$83:E97) -> 5 | T97: =SUM(Q97:S97) -> 8
B98: Abril | C98: =COUNTIFS('Datos Preescolar'!$E:$E,C$82,'Datos Preescolar'!$I:$I,">=01/04/2024",'Datos Preescolar'!$I:$I,"<=30/04/2024") -> 0 | D98: =COUNTIFS('Datos Preescolar'!$E:$E,D$82,'Datos Preescolar'!$I:$I,">=01/04/2024",'Datos Preescolar'!$I:$I,"<=30/04/2024") -> 0 | E98: =COUNTIFS('Datos Preescolar'!$E:$E,E$82,'Datos Preescolar'!$I:$I,">=01/04/2024",'Datos Preescolar'!$I:$I,"<=30/04/2024") -> 0 | F98: =SUM(C98:E98) -> 0 | I98: Abril | J98: =SUM(C$95:C98) -> 1 | K98: =SUM(D$95:D98) -> 0 | L98: =SUM(E$95:E98) -> 3 | M98: =SUM(J98:L98) -> 4 | P98: Abril | Q98: =SUM(C$83:C98) -> 2 | R98: =SUM(D$83:D98) -> 1 | S98: =SUM(E$83:E98) -> 5 | T98: =SUM(Q98:S98) -> 8
B99: Mayo | C99: =COUNTIFS('Datos Preescolar'!$E:$E,C$82,'Datos Preescolar'!$I:$I,">=01/05/2024",'Datos Preescolar'!$I:$I,"<=31/05/2024") -> 0 | D99: =COUNTIFS('Datos Preescolar'!$E:$E,D$82,'Datos Preescolar'!$I:$I,">=01/05/2024",'Datos Preescolar'!$I:$I,"<=31/05/2024") -> 0 | E99: =COUNTIFS('Datos Preescolar'!$E:$E,E$82,'Datos Preescolar'!$I:$I,">=01/05/2024",'Datos Preescolar'!$I:$I,"<=31/05/2024") -> 0 | F99: =SUM(C99:E99) -> 0 | I99: Mayo | J99: =SUM(C$95:C99) -> 1 | K99: =SUM(D$95:D99) -> 0 | L99: =SUM(E$95:E99) -> 3 | M99: =SUM(J99:L99) -> 4 | P99: Mayo | Q99: =SUM(C$83:C99) -> 2 | R99: =SUM(D$83:D99) -> 1 | S99: =SUM(E$83:E99) -> 5 | T99: =SUM(Q99:S99) -> 8
B100: Junio | C100: =COUNTIFS('Datos Preescolar'!$E:$E,C$82,'Datos Preescolar'!$I:$I,">=01/06/2024",'Datos Preescolar'!$I:$I,"<=30/06/2024") -> 0 | D100: =COUNTIFS('Datos Preescolar'!$E:$E,D$82,'Datos Preescolar'!$I:$I,">=01/06/2024",'Datos Preescolar'!$I:$I,"<=30/06/2024") -> 0 | E100: =COUNTIFS('Datos Preescolar'!$E:$E,E$82,'Datos Preescolar'!$I:$I,">=01/06/2024",'Datos Preescolar'!$I:$I,"<=30/06/2024") -> 0 | F100: =SUM(C100:E100) -> 0 | I100: Junio | J100: =SUM(C$95:C100) -> 1 | K100: =SUM(D$95:D100) -> 0 | L100: =SUM(E$95:E100) -> 3 | M100: =SUM(J100:L100) -> 4 | P100: Junio | Q100: =SUM(C$83:C100) -> 2 | R100: =SUM(D$83:D100) -> 1 | S100: =SUM(E$83:E100) -> 5 | T100: =SUM(Q100:S100) -> 8
B101: Julio | C101: =COUNTIFS('Datos Preescolar'!$E:$E,C$82,'Datos Preescolar'!$I:$I,">=01/07/2024",'Datos Preescolar'!$I:$I,"<=31/07/2024") -> 0 | D101: =COUNTIFS('Datos Preescolar'!$E:$E,D$82,'Datos Preescolar'!$I:$I,">=01/07/2024",'Datos Preescolar'!$I:$I,"<=31/07/2024") -> 0 | E101: =COUNTIFS('Datos Preescolar'!$E:$E,E$82,'Datos Preescolar'!$I:$I,">=01/07/2024",'Datos Preescolar'!$I:$I,"<=31/07/2024") -> 0 | F101: =SUM(C101:E101) -> 0 | I101: Julio | J101: =SUM(C$95:C101) -> 1 | K101: =SUM(D$95:D101) -> 0 | L101: =SUM(E$95:E101) -> 3 | M101: =SUM(J101:L101) -> 4 | P101: Julio | Q101: =SUM(C$83:C101) -> 2 | R101: =SUM(D$83:D101) -> 1 | S101: =SUM(E$83:E101) -> 5 | T101: =SUM(Q101:S101) -> 8
B102: Agosto | C102: =COUNTIFS('Datos Preescolar'!$E:$E,C$82,'Datos Preescolar'!$I:$I,">=01/08/2024",'Datos Preescolar'!$I:$I,"<=31/08/2024") -> 0 | D102: =COUNTIFS('Datos Preescolar'!$E:$E,D$82,'Datos Preescolar'!$I:$I,">=01/08/2024",'Datos Preescolar'!$I:$I,"<=31/08/2024") -> 0 | E102: =COUNTIFS('Datos Preescolar'!$E:$E,E$82,'Datos Preescolar'!$I:$I,">=01/08/2024",'Datos Preescolar'!$I:$I,"<=31/08/2024") -> 0 | F102: =SUM(C102:E102) -> 0 | I102: Agosto | J102: =SUM(C$95:C102) -> 1 | K102: =SUM(D$95:D102) -> 0 | L102: =SUM(E$95:E102) -> 3 | M102: =SUM(J102:L102) -> 4 | P102: Agosto | Q102: =SUM(C$83:C102) -> 2 | R102: =SUM(D$83:D102) -> 1 | S102: =SUM(E$83:E102) -> 5 | T102: =SUM(Q102:S102) -> 8
B103: Septiembre | C103: =COUNTIFS('Datos Preescolar'!$E:$E,C$82,'Datos Preescolar'!$I:$I,">=01/09/2024",'Datos Preescolar'!$I:$I,"<=30/09/2024") -> 0 | D103: =COUNTIFS('Datos Preescolar'!$E:$E,D$82,'Datos Preescolar'!$I:$I,">=01/09/2024",'Datos Preescolar'!$I:$I,"<=30/09/2024") -> 1 | E103: =COUNTIFS('Datos Preescolar'!$E:$E,E$82,'Datos Preescolar'!$I:$I,">=01/09/2024",'Datos Preescolar'!$I:$I,"<=30/09/2024") -> 0 | F103: =SUM(C103:E103) -> 1 | I103: Septiembre | J103: =SUM(C$95:C103) -> 1 | K103: =SUM(D$95:D103) -> 1 | L103: =SUM(E$95:E103) -> 3 | M103: =SUM(J103:L103) -> 5 | P103: Septiembre | Q103: =SUM(C$83:C103) -> 2 | R103: =SUM(D$83:D103) -> 2 | S103: =SUM(E$83:E103) -> 5 | T103: =SUM(Q103:S103) -> 9
B104: Octubre | C104: =COUNTIFS('Datos Preescolar'!$E:$E,C$82,'Datos Preescolar'!$I:$I,">=01/10/2024",'Datos Preescolar'!$I:$I,"<=31/10/2024") -> 0 | D104: =COUNTIFS('Datos Preescolar'!$E:$E,D$82,'Datos Preescolar'!$I:$I,">=01/10/2024",'Datos Preescolar'!$I:$I,"<=31/10/2024") -> 0 | E104: =COUNTIFS('Datos Preescolar'!$E:$E,E$82,'Datos Preescolar'!$I:$I,">=01/10/2024",'Datos Preescolar'!$I:$I,"<=31/10/2024") -> 0 | F104: =SUM(C104:E104) -> 0 | I104: Octubre | J104: =SUM(C$95:C104) -> 1 | K104: =SUM(D$95:D104) -> 1 | L104: =SUM(E$95:E104) -> 3 | M104: =SUM(J104:L104) -> 5 | P104: Octubre | Q104: =SUM(C$83:C104) -> 2 | R104: =SUM(D$83:D104) -> 2 | S104: =SUM(E$83:E104) -> 5 | T104: =SUM(Q104:S104) -> 9
...

Sheet Primaria
B1: Citas de información por mes | K1: Citas de información acumulado por año | T1: Citas de información acumulado todos los años
B2: MES | C2: 1° | D2: 2° | E2: 3° | F2: 4° | G2: 5° | H2: TOTAL | K2: MES | L2: 1° | M2: 2° | N2: 3° | O2: 4° | P2: 5° | Q2: TOTAL | T2: MES | U2: 1° | V2: 2° | W2: 3° | X2: 4° | Y2: 5° | Z2: TOTAL
A3: 2023 | B3: Enero | C3: =COUNTIFS('Datos Primaria'!$E:$E,C$2,'Datos Primaria'!$C:$C,">=01/01/2023",'Datos Primaria'!$C:$C,"<=31/01/2023") -> 2 | D3: =COUNTIFS('Datos Primaria'!$E:$E,D$2,'Datos Primaria'!$C:$C,">=01/01/2023",'Datos Primaria'!$C:$C,"<=31/01/2023") -> 1 | E3: =COUNTIFS('Datos Primaria'!$E:$E,E$2,'Datos Primaria'!$C:$C,">=01/01/2023",'Datos Primaria'!$C:$C,"<=31/01/2023") -> 4 | F3: =COUNTIFS('Datos Primaria'!$E:$E,F$2,'Datos Primaria'!$C:$C,">=01/01/2023",'Datos Primaria'!$C:$C,"<=31/01/2023") -> 1 | G3: =COUNTIFS('Datos Primaria'!$E:$E,G$2,'Datos Primaria'!$C:$C,">=01/01/2023",'Datos Primaria'!$C:$C,"<=31/01/2023") -> 1 | H3: =SUM(C3:G3) -> 9 | J3: =A3 -> 2023 | K3: Enero | L3: =SUM(C$3:C3) -> 2 | M3: =SUM(D$3:D3) -> 1 | N3: =SUM(E$3:E3) -> 4 | O3: =SUM(F$3:F3) -> 1 | P3: =SUM(G$3:G3) -> 1 | Q3: =SUM(L3:P3) -> 9 | S3: =A3 -> 2023 | T3: Enero | U3: =SUM(C$3:C3) -> 2 | V3: =SUM(D$3:D3) -> 1 | W3: =SUM(E$3:E3) -> 4 | X3: =SUM(F$3:F3) -> 1 | Y3: =SUM(G$3:G3) -> 1 | Z3: =SUM(U3:Y3) -> 9
B4: Febrero | C4: =COUNTIFS('Datos Primaria'!$E:$E,C$2,'Datos Primaria'!$C:$C,">=01/02/2023",'Datos Primaria'!$C:$C,"<=28/02/2023") -> 1 | D4: =COUNTIFS('Datos Primaria'!$E:$E,D$2,'Datos Primaria'!$C:$C,">=01/02/2023",'Datos Primaria'!$C:$C,"<=28/02/2023") -> 0 | E4: =COUNTIFS('Datos Primaria'!$E:$E,E$2,'Datos Primaria'!$C:$C,">=01/02/2023",'Datos Primaria'!$C:$C,"<=28/02/2023") -> 0 | F4: =COUNTIFS('Datos Primaria'!$E:$E,F$2,'Datos Primaria'!$C:$C,">=01/02/2023",'Datos Primaria'!$C:$C,"<=28/02/2023") -> 1 | G4: =COUNTIFS('Datos Primaria'!$E:$E,G$2,'Datos Primaria'!$C:$C,">=01/02/2023",'Datos Primaria'!$C:$C,"<=28/02/2023") -> 3 | H4: =SUM(C4:G4) -> 5 | K4: Febrero | L4: =SUM(C$3:C4) -> 3 | M4: =SUM(D$3:D4) -> 1 | N4: =SUM(E$3:E4) -> 4 | O4: =SUM(F$3:F4) -> 2 | P4: =SUM(G$3:G4) -> 4 | Q4: =SUM(L4:P4) -> 14 | T4: Febrero | U4: =SUM(C$3:C4) -> 3 | V4: =SUM(D$3:D4) -> 1 | W4: =SUM(E$3:E4) -> 4 | X4: =SUM(F$3:F4) -> 2 | Y4: =SUM(G$3:G4) -> 4 | Z4: =SUM(U4:Y4) -> 14
B5: Marzo | C5: =COUNTIFS('Datos Primaria'!$E:$E,C$2,'Datos Primaria'!$C:$C,">=01/03/2023",'Datos Primaria'!$C:$C,"<=31/03/2023") -> 1 | D5: =COUNTIFS('Datos Primaria'!$E:$E,D$2,'Datos Primaria'!$C:$C,">=01/03/2023",'Datos Primaria'!$C:$C,"<=31/03/2023") -> 1 | E5: =COUNTIFS('Datos Primaria'!$E:$E,E$2,'Datos Primaria'!$C:$C,">=01/03/2023",'Datos Primaria'!$C:$C,"<=31/03/2023") -> 0 | F5: =COUNTIFS('Datos Primaria'!$E:$E,F$2,'Datos Primaria'!$C:$C,">=01/03/2023",'Datos Primaria'!$C:$C,"<=31/03/2023") -> 0 | G5: =COUNTIFS('Datos Primaria'!$E:$E,G$2,'Datos Primaria'!$C:$C,">=01/03/2023",'Datos Primaria'!$C:$C,"<=31/03/2023") -> 0 | H5: =SUM(C5:G5) -> 2 | K5: Marzo | L5: =SUM(C$3:C5) -> 4 | M5: =SUM(D$3:D5) -> 2 | N5: =SUM(E$3:E5) -> 4 | O5: =SUM(F$3:F5) -> 2 | P5: =SUM(G$3:G5) -> 4 | Q5: =SUM(L5:P5) -> 16 | T5: Marzo | U5: =SUM(C$3:C5) -> 4 | V5: =SUM(D$3:D5) -> 2 | W5: =SUM(E$3:E5) -> 4 | X5: =SUM(F$3:F5) -> 2 | Y5: =SUM(G$3:G5) -> 4 | Z5: =SUM(U5:Y5) -> 16
B6: Abril | C6: =COUNTIFS('Datos Primaria'!$E:$E,C$2,'Datos Primaria'!$C:$C,">=01/04/2023",'Datos Primaria'!$C:$C,"<=30/04/2023") -> 1 | D6: =COUNTIFS('Datos Primaria'!$E:$E,D$2,'Datos Primaria'!$C:$C,">=01/04/2023",'Datos Primaria'!$C:$C,"<=30/04/2023") -> 1 | E6: =COUNTIFS('Datos Primaria'!$E:$E,E$2,'Datos Primaria'!$C:$C,">=01/04/2023",'Datos Primaria'!$C:$C,"<=30/04/2023") -> 2 | F6: =COUNTIFS('Datos Primaria'!$E:$E,F$2,'Datos Primaria'!$C:$C,">=01/04/2023",'Datos Primaria'!$C:$C,"<=30/04/2023") -> 1 | G6: =COUNTIFS('Datos Primaria'!$E:$E,G$2,'Datos Primaria'!$C:$C,">=01/04/2023",'Datos Primaria'!$C:$C,"<=30/04/2023") -> 1 | H6: =SUM(C6:G6) -> 6 | K6: Abril | L6: =SUM(C$3:C6) -> 5 | M6: =SUM(D$3:D6) -> 3 | N6: =SUM(E$3:E6) -> 6 | O6: =SUM(F$3:F6) -> 3 | P6: =SUM(G$3:G6) -> 5 | Q6: =SUM(L6:P6) -> 22 | T6: Abril | U6: =SUM(C$3:C6) -> 5 | V6: =SUM(D$3:D6) -> 3 | W6: =SUM(E$3:E6) -> 6 | X6: =SUM(F$3:F6) -> 3 | Y6: =SUM(G$3:G6) -> 5 | Z6: =SUM(U6:Y6) -> 22
B7: Mayo | C7: =COUNTIFS('Datos Primaria'!$E:$E,C$2,'Datos Primaria'!$C:$C,">=01/05/2023",'Datos Primaria'!$C:$C,"<=31/05/2023") -> 0 | D7: =COUNTIFS('Datos Primaria'!$E:$E,D$2,'Datos Primaria'!$C:$C,">=01/05/2023",'Datos Primaria'!$C:$C,"<=31/05/2023") -> 2 | E7: =COUNTIFS('Datos Primaria'!$E:$E,E$2,'Datos Primaria'!$C:$C,">=01/05/2023",'Datos Primaria'!$C:$C,"<=31/05/2023") -> 1 | F7: =COUNTIFS('Datos Primaria'!$E:$E,F$2,'Datos Primaria'!$C:$C,">=01/05/2023",'Datos Primaria'!$C:$C,"<=31/05/2023") -> 0 | G7: =COUNTIFS('Datos Primaria'!$E:$E,G$2,'Datos Primaria'!$C:$C,">=01/05/2023",'Datos Primaria'!$C:$C,"<=31/05/2023") -> 1 | H7: =SUM(C7:G7) -> 4 | K7: Mayo | L7: =SUM(C$3:C7) -> 5 | M7: =SUM(D$3:D7) -> 5 | N7: =SUM(E$3:E7) -> 7 | O7: =SUM(F$3:F7) -> 3 | P7: =SUM(G$3:G7) -> 6 | Q7: =SUM(L7:P7) -> 26 | T7: Mayo | U7: =SUM(C$3:C7) -> 5 | V7: =SUM(D$3:D7) -> 5 | W7: =SUM(E$3:E7) -> 7 | X7: =SUM(F$3:F7) -> 3 | Y7: =SUM(G$3:G7) -> 6 | Z7: =SUM(U7:Y7) -> 26
B8: Junio | C8: =COUNTIFS('Datos Primaria'!$E:$E,C$2,'Datos Primaria'!$C:$C,">=01/06/2023",'Datos Primaria'!$C:$C,"<=30/06/2023") -> 3 | D8: =COUNTIFS('Datos Primaria'!$E:$E,D$2,'Datos Primaria'!$C:$C,">=01/06/2023",'Datos Primaria'!$C:$C,"<=30/06/2023") -> 2 | E8: =COUNTIFS('Datos Primaria'!$E:$E,E$2,'Datos Primaria'!$C:$C,">=01/06/2023",'Datos Primaria'!$C:$C,"<=30/06/2023") -> 2 | F8: =COUNTIFS('Datos Primaria'!$E:$E,F$2,'Datos Primaria'!$C:$C,">=01/06/2023",'Datos Primaria'!$C:$C,"<=30/06/2023") -> 1 | G8: =COUNTIFS('Datos Primaria'!$E:$E,G$2,'Datos Primaria'!$C:$C,">=01/06/2023",'Datos Primaria'!$C:$C,"<=30/06/2023") -> 3 | H8: =SUM(C8:G8) -> 11 | K8: Junio | L8: =SUM(C$3:C8) -> 8 | M8: =SUM(D$3:D8) -> 7 | N8: =SUM(E$3:E8) -> 9 | O8: =SUM(F$3:F8) -> 4 | P8: =SUM(G$3:G8) -> 9 | Q8: =SUM(L8:P8) -> 37 | T8: Junio | U8: =SUM(C$3:C8) -> 8 | V8: =SUM(D$3:D8) -> 7 | W8: =SUM(E$3:E8) -> 9 | X8: =SUM(F$3:F8) -> 4 | Y8: =SUM(G$3:G8) -> 9 | Z8: =SUM(U8:Y8) -> 37
B9: Julio | C9: =COUNTIFS('Datos Primaria'!$E:$E,C$2,'Datos Primaria'!$C:$C,">=01/07/2023",'Datos Primaria'!$C:$C,"<=31/07/2023") -> 3 | D9: =COUNTIFS('Datos Primaria'!$E:$E,D$2,'Datos Primaria'!$C:$C,">=01/07/2023",'Datos Primaria'!$C:$C,"<=31/07/2023") -> 0 | E9: =COUNTIFS('Datos Primaria'!$E:$E,E$2,'Datos Primaria'!$C:$C,">=01/07/2023",'Datos Primaria'!$C:$C,"<=31/07/2023") -> 4 | F9: =COUNTIFS('Datos Primaria'!$E:$E,F$2,'Datos Primaria'!$C:$C,">=01/07/2023",'Datos Primaria'!$C:$C,"<=31/07/2023") -> 2 | G9: =COUNTIFS('Datos Primaria'!$E:$E,G$2,'Datos Primaria'!$C:$C,">=01/07/2023",'Datos Primaria'!$C:$C,"<=31/07/2023") -> 2 | H9: =SUM(C9:G9) -> 11 | K9: Julio | L9: =SUM(C$3:C9) -> 11 | M9: =SUM(D$3:D9) -> 7 | N9: =SUM(E$3:E9) -> 13 | O9: =SUM(F$3:F9) -> 6 | P9: =SUM(G$3:G9) -> 11 | Q9: =SUM(L9:P9) -> 48 | T9: Julio | U9: =SUM(C$3:C9) -> 11 | V9: =SUM(D$3:D9) -> 7 | W9: =SUM(E$3:E9) -> 13 | X9: =SUM(F$3:F9) -> 6 | Y9: =SUM(G$3:G9) -> 11 | Z9: =SUM(U9:Y9) -> 48
B10: Agosto | C10: =COUNTIFS('Datos Primaria'!$E:$E,C$2,'Datos Primaria'!$C:$C,">=01/08/2023",'Datos Primaria'!$C:$C,"<=31/08/2023") -> 6 | D10: =COUNTIFS('Datos Primaria'!$E:$E,D$2,'Datos Primaria'!$C:$C,">=01/08/2023",'Datos Primaria'!$C:$C,"<=31/08/2023") -> 1 | E10: =COUNTIFS('Datos Primaria'!$E:$E,E$2,'Datos Primaria'!$C:$C,">=01/08/2023",'Datos Primaria'!$C:$C,"<=31/08/2023") -> 2 | F10: =COUNTIFS('Datos Primaria'!$E:$E,F$2,'Datos Primaria'!$C:$C,">=01/08/2023",'Datos Primaria'!$C:$C,"<=31/08/2023") -> 4 | G10: =COUNTIFS('Datos Primaria'!$E:$E,G$2,'Datos Primaria'!$C:$C,">=01/08/2023",'Datos Primaria'!$C:$C,"<=31/08/2023") -> 4 | H10: =SUM(C10:G10) -> 17 | K10: Agosto | L10: =SUM(C$3:C10) -> 17 | M10: =SUM(D$3:D10) -> 8 | N10: =SUM(E$3:E10) -> 15 | O10: =SUM(F$3:F10) -> 10 | P10: =SUM(G$3:G10) -> 15 | Q10: =SUM(L10:P10) -> 65 | T10: Agosto | U10: =SUM(C$3:C10) -> 17 | V10: =SUM(D$3:D10) -> 8 | W10: =SUM(E$3:E10) -> 15 | X10: =SUM(F$3:F10) -> 10 | Y10: =SUM(G$3:G10) -> 15 | Z10: =SUM(U10:Y10) -> 65
B11: Septiembre | C11: =COUNTIFS('Datos Primaria'!$E:$E,C$2,'Datos Primaria'!$C:$C,">=01/09/2023",'Datos Primaria'!$C:$C,"<=30/09/2023") -> 3 | D11: =COUNTIFS('Datos Primaria'!$E:$E,D$2,'Datos Primaria'!$C:$C,">=01/09/2023",'Datos Primaria'!$C:$C,"<=30/09/2023") -> 1 | E11: =COUNTIFS('Datos Primaria'!$E:$E,E$2,'Datos Primaria'!$C:$C,">=01/09/2023",'Datos Primaria'!$C:$C,"<=30/09/2023") -> 2 | F11: =COUNTIFS('Datos Primaria'!$E:$E,F$2,'Datos Primaria'!$C:$C,">=01/09/2023",'Datos Primaria'!$C:$C,"<=30/09/2023") -> 4 | G11: =COUNTIFS('Datos Primaria'!$E:$E,G$2,'Datos Primaria'!$C:$C,">=01/09/2023",'Datos Primaria'!$C:$C,"<=30/09/2023") -> 1 | H11: =SUM(C11:G11) -> 11 | K11: Septiembre | L11: =SUM(C$3:C11) -> 20 | M11: =SUM(D$3:D11) -> 9 | N11: =SUM(E$3:E11) -> 17 | O11: =SUM(F$3:F11) -> 14 | P11: =SUM(G$3:G11) -> 16 | Q11: =SUM(L11:P11) -> 76 | T11: Septiembre | U11: =SUM(C$3:C11) -> 20 | V11: =SUM(D$3:D11) -> 9 | W11: =SUM(E$3:E11) -> 17 | X11: =SUM(F$3:F11) -> 14 | Y11: =SUM(G$3:G11) -> 16 | Z11: =SUM(U11:Y11) -> 76
B12: Octubre | C12: =COUNTIFS('Datos Primaria'!$E:$E,C$2,'Datos Primaria'!$C:$C,">=01/10/2023",'Datos Primaria'!$C:$C,"<=31/10/2023") -> 3 | D12: =COUNTIFS('Datos Primaria'!$E:$E,D$2,'Datos Primaria'!$C:$C,">=01/10/2023",'Datos Primaria'!$C:$C,"<=31/10/2023") -> 1 | E12: =COUNTIFS('Datos Primaria'!$E:$E,E$2,'Datos Primaria'!$C:$C,">=01/10/2023",'Datos Primaria'!$C:$C,"<=31/10/2023") -> 0 | F12: =COUNTIFS('Datos Primaria'!$E:$E,F$2,'Datos Primaria'!$C:$C,">=01/10/2023",'Datos Primaria'!$C:$C,"<=31/10/2023") -> 2 | G12: =COUNTIFS('Datos Primaria'!$E:$E,G$2,'Datos Primaria'!$C:$C,">=01/10/2023",'Datos Primaria'!$C:$C,"<=31/10/2023") -> 2 | H12: =SUM(C12:G12) -> 8 | K12: Octubre | L12: =SUM(C$3:C12) -> 23 | M12: =SUM(D$3:D12) -> 10 | N12: =SUM(E$3:E12) -> 17 | O12: =SUM(F$3:F12) -> 16 | P12: =SUM(G$3:G12) -> 18 | Q12: =SUM(L12:P12) -> 84 | T12: Octubre | U12: =SUM(C$3:C12) -> 23 | V12: =SUM(D$3:D12) -> 10 | W12: =SUM(E$3:E12) -> 17 | X12: =SUM(F$3:F12) -> 16 | Y12: =SUM(G$3:G12) -> 18 | Z12: =SUM(U12:Y12) -> 84
B13: Noviembre | C13: =COUNTIFS('Datos Primaria'!$E:$E,C$2,'Datos Primaria'!$C:$C,">=01/11/2023",'Datos Primaria'!$C:$C,"<=30/11/2023") -> 4 | D13: =COUNTIFS('Datos Primaria'!$E:$E,D$2,'Datos Primaria'!$C:$C,">=01/11/2023",'Datos Primaria'!$C:$C,"<=30/11/2023") -> 3 | E13: =COUNTIFS('Datos Primaria'!$E:$E,E$2,'Datos Primaria'!$C:$C,">=01/11/2023",'Datos Primaria'!$C:$C,"<=30/11/2023") -> 4 | F13: =COUNTIFS('Datos Primaria'!$E:$E,F$2,'Datos Primaria'!$C:$C,">=01/11/2023",'Datos Primaria'!$C:$C,"<=30/11/2023") -> 0 | G13: =COUNTIFS('Datos Primaria'!$E:$E,G$2,'Datos Primaria'!$C:$C,">=01/11/2023",'Datos Primaria'!$C:$C,"<=30/11/2023") -> 2 | H13: =SUM(C13:G13) -> 13 | K13: Noviembre | L13: =SUM(C$3:C13) -> 27 | M13: =SUM(D$3:D13) -> 13 | N13: =SUM(E$3:E13) -> 21 | O13: =SUM(F$3:F13) -> 16 | P13: =SUM(G$3:G13) -> 20 | Q13: =SUM(L13:P13) -> 97 | T13: Noviembre | U13: =SUM(C$3:C13) -> 27 | V13: =SUM(D$3:D13) -> 13 | W13: =SUM(E$3:E13) -> 21 | X13: =SUM(F$3:F13) -> 16 | Y13: =SUM(G$3:G13) -> 20 | Z13: =SUM(U13:Y13) -> 97
B14: Diciembre | C14: =COUNTIFS('Datos Primaria'!$E:$E,C$2,'Datos Primaria'!$C:$C,">=01/12/2023",'Datos Primaria'!$C:$C,"<=31/12/2023") -> 0 | D14: =COUNTIFS('Datos Primaria'!$E:$E,D$2,'Datos Primaria'!$C:$C,">=01/12/2023",'Datos Primaria'!$C:$C,"<=31/12/2023") -> 1 | E14: =COUNTIFS('Datos Primaria'!$E:$E,E$2,'Datos Primaria'!$C:$C,">=01/12/2023",'Datos Primaria'!$C:$C,"<=31/12/2023") -> 0 | F14: =COUNTIFS('Datos Primaria'!$E:$E,F$2,'Datos Primaria'!$C:$C,">=01/12/2023",'Datos Primaria'!$C:$C,"<=31/12/2023") -> 0 | G14: =COUNTIFS('Datos Primaria'!$E:$E,G$2,'Datos Primaria'!$C:$C,">=01/12/2023",'Datos Primaria'!$C:$C,"<=31/12/2023") -> 1 | H14: =SUM(C14:G14) -> 2 | K14: Diciembre | L14: =SUM(C$3:C14) -> 27 | M14: =SUM(D$3:D14) -> 14 | N14: =SUM(E$3:E14) -> 21 | O14: =SUM(F$3:F14) -> 16 | P14: =SUM(G$3:G14) -> 21 | Q14: =SUM(L14:P14) -> 99 | T14: Diciembre | U14: =SUM(C$3:C14) -> 27 | V14: =SUM(D$3:D14) -> 14 | W14: =SUM(E$3:E14) -> 21 | X14: =SUM(F$3:F14) -> 16 | Y14: =SUM(G$3:G14) -> 21 | Z14: =SUM(U14:Y14) -> 99
A15: 2024 | B15: Enero | C15: =COUNTIFS('Datos Primaria'!$E:$E,C$2,'Datos Primaria'!$C:$C,">=01/01/2024",'Datos Primaria'!$C:$C,"<=31/01/2024") -> 2 | D15: =COUNTIFS('Datos Primaria'!$E:$E,D$2,'Datos Primaria'!$C:$C,">=01/01/2024",'Datos Primaria'!$C:$C,"<=31/01/2024") -> 2 | E15: =COUNTIFS('Datos Primaria'!$E:$E,E$2,'Datos Primaria'!$C:$C,">=01/01/2024",'Datos Primaria'!$C:$C,"<=31/01/2024") -> 1 | F15: =COUNTIFS('Datos Primaria'!$E:$E,F$2,'Datos Primaria'!$C:$C,">=01/01/2024",'Datos Primaria'!$C:$C,"<=31/01/2024") -> 3 | G15: =COUNTIFS('Datos Primaria'!$E:$E,G$2,'Datos Primaria'!$C:$C,">=01/01/2024",'Datos Primaria'!$C:$C,"<=31/01/2024") -> 0 | H15: =SUM(C15:G15) -> 8 | J15: =A15 -> 2024 | K15: Enero | L15: =SUM(C$15:C15) -> 2 | M15: =SUM(D$15:D15) -> 2 | N15: =SUM(E$15:E15) -> 1 | O15: =SUM(F$15:F15) -> 3 | P15: =SUM(G$15:G15) -> 0 | Q15: =SUM(L15:P15) -> 8 | S15: =A15 -> 2024 | T15: Enero | U15: =SUM(C$3:C15) -> 29 | V15: =SUM(D$3:D15) -> 16 | W15: =SUM(E$3:E15) -> 22 | X15: =SUM(F$3:F15) -> 19 | Y15: =SUM(G$3:G15) -> 21 | Z15: =SUM(U15:Y15) -> 107
B16: Febrero | C16: =COUNTIFS('Datos Primaria'!$E:$E,C$2,'Datos Primaria'!$C:$C,">=01/02/2024",'Datos Primaria'!$C:$C,"<=29/02/2024") -> 1 | D16: =COUNTIFS('Datos Primaria'!$E:$E,D$2,'Datos Primaria'!$C:$C,">=01/02/2024",'Datos Primaria'!$C:$C,"<=29/02/2024") -> 0 | E16: =COUNTIFS('Datos Primaria'!$E:$E,E$2,'Datos Primaria'!$C:$C,">=01/02/2024",'Datos Primaria'!$C:$C,"<=29/02/2024") -> 0 | F16: =COUNTIFS('Datos Primaria'!$E:$E,F$2,'Datos Primaria'!$C:$C,">=01/02/2024",'Datos Primaria'!$C:$C,"<=29/02/2024") -> 1 | G16: =COUNTIFS('Datos Primaria'!$E:$E,G$2,'Datos Primaria'!$C:$C,">=01/02/2024",'Datos Primaria'!$C:$C,"<=29/02/2024") -> 0 | H16: =SUM(C16:G16) -> 2 | K16: Febrero | L16: =SUM(C$15:C16) -> 3 | M16: =SUM(D$15:D16) -> 2 | N16: =SUM(E$15:E16) -> 1 | O16: =SUM(F$15:F16) -> 4 | P16: =SUM(G$15:G16) -> 0 | Q16: =SUM(L16:P16) -> 10 | T16: Febrero | U16: =SUM(C$3:C16) -> 30 | V16: =SUM(D$3:D16) -> 16 | W16: =SUM(E$3:E16) -> 22 | X16: =SUM(F$3:F16) -> 20 | Y16: =SUM(G$3:G16) -> 21 | Z16: =SUM(U16:Y16) -> 109
B17: Marzo | C17: =COUNTIFS('Datos Primaria'!$E:$E,C$2,'Datos Primaria'!$C:$C,">=01/03/2024",'Datos Primaria'!$C:$C,"<=31/03/2024") -> 0 | D17: =COUNTIFS('Datos Primaria'!$E:$E,D$2,'Datos Primaria'!$C:$C,">=01/03/2024",'Datos Primaria'!$C:$C,"<=31/03/2024") -> 1 | E17: =COUNTIFS('Datos Primaria'!$E:$E,E$2,'Datos Primaria'!$C:$C,">=01/03/2024",'Datos Primaria'!$C:$C,"<=31/03/2024") -> 0 | F17: =COUNTIFS('Datos Primaria'!$E:$E,F$2,'Datos Primaria'!$C:$C,">=01/03/2024",'Datos Primaria'!$C:$C,"<=31/03/2024") -> 2 | G17: =COUNTIFS('Datos Primaria'!$E:$E,G$2,'Datos Primaria'!$C:$C,">=01/03/2024",'Datos Primaria'!$C:$C,"<=31/03/2024") -> 0 | H17: =SUM(C17:G17) -> 3 | K17: Marzo | L17: =SUM(C$15:C17) -> 3 | M17: =SUM(D$15:D17) -> 3 | N17: =SUM(E$15:E17) -> 1 | O17: =SUM(F$15:F17) -> 6 | P17: =SUM(G$15:G17) -> 0 | Q17: =SUM(L17:P17) -> 13 | T17: Marzo | U17: =SUM(C$3:C17) -> 30 | V17: =SUM(D$3:D17) -> 17 | W17: =SUM(E$3:E17) -> 22 | X17: =SUM(F$3:F17) -> 22 | Y17: =SUM(G$3:G17) -> 21 | Z17: =SUM(U17:Y17) -> 112
B18: Abril | C18: =COUNTIFS('Datos Primaria'!$E:$E,C$2,'Datos Primaria'!$C:$C,">=01/04/2024",'Datos Primaria'!$C:$C,"<=30/04/2024") -> 0 | D18: =COUNTIFS('Datos Primaria'!$E:$E,D$2,'Datos Primaria'!$C:$C,">=01/04/2024",'Datos Primaria'!$C:$C,"<=30/04/2024") -> 3 | E18: =COUNTIFS('Datos Primaria'!$E:$E,E$2,'Datos Primaria'!$C:$C,">=01/04/2024",'Datos Primaria'!$C:$C,"<=30/04/2024") -> 2 | F18: =COUNTIFS('Datos Primaria'!$E:$E,F$2,'Datos Primaria'!$C:$C,">=01/04/2024",'Datos Primaria'!$C:$C,"<=30/04/2024") -> 0 | G18: =COUNTIFS('Datos Primaria'!$E:$E,G$2,'Datos Primaria'!$C:$C,">=01/04/2024",'Datos Primaria'!$C:$C,"<=30/04/2024") -> 1 | H18: =SUM(C18:G18) -> 6 | K18: Abril | L18: =SUM(C$15:C18) -> 3 | M18: =SUM(D$15:D18) -> 6 | N18: =SUM(E$15:E18) -> 3 | O18: =SUM(F$15:F18) -> 6 | P18: =SUM(G$15:G18) -> 1 | Q18: =SUM(L18:P18) -> 19 | T18: Abril | U18: =SUM(C$3:C18) -> 30 | V18: =SUM(D$3:D18) -> 20 | W18: =SUM(E$3:E18) -> 24 | X18: =SUM(F$3:F18) -> 22 | Y18: =SUM(G$3:G18) -> 22 | Z18: =SUM(U18:Y18) -> 118
B19: Mayo | C19: =COUNTIFS('Datos Primaria'!$E:$E,C$2,'Datos Primaria'!$C:$C,">=01/05/2024",'Datos Primaria'!$C:$C,"<=31/05/2024") -> 0 | D19: =COUNTIFS('Datos Primaria'!$E:$E,D$2,'Datos Primaria'!$C:$C,">=01/05/2024",'Datos Primaria'!$C:$C,"<=31/05/2024") -> 3 | E19: =COUNTIFS('Datos Primaria'!$E:$E,E$2,'Datos Primaria'!$C:$C,">=01/05/2024",'Datos Primaria'!$C:$C,"<=31/05/2024") -> 2 | F19: =COUNTIFS('Datos Primaria'!$E:$E,F$2,'Datos Primaria'!$C:$C,">=01/05/2024",'Datos Primaria'!$C:$C,"<=31/05/2024") -> 1 | G19: =COUNTIFS('Datos Primaria'!$E:$E,G$2,'Datos Primaria'!$C:$C,">=01/05/2024",'Datos Primaria'!$C:$C,"<=31/05/2024") -> 1 | H19: =SUM(C19:G19) -> 7 | K19: Mayo | L19: =SUM(C$15:C19) -> 3 | M19: =SUM(D$15:D19) -> 9 | N19: =SUM(E$15:E19) -> 5 | O19: =SUM(F$15:F19) -> 7 | P19: =SUM(G$15:G19) -> 2 | Q19: =SUM(L19:P19) -> 26 | T19: Mayo | U19: =SUM(C$3:C19) -> 30 | V19: =SUM(D$3:D19) -> 23 | W19: =SUM(E$3:E19) -> 26 | X19: =SUM(F$3:F19) -> 23 | Y19: =SUM(G$3:G19) -> 23 | Z19: =SUM(U19:Y19) -> 125
B20: Junio | C20: =COUNTIFS('Datos Primaria'!$E:$E,C$2,'Datos Primaria'!$C:$C,">=01/06/2024",'Datos Primaria'!$C:$C,"<=30/06/2024") -> 1 | D20: =COUNTIFS('Datos Primaria'!$E:$E,D$2,'Datos Primaria'!$C:$C,">=01/06/2024",'Datos Primaria'!$C:$C,"<=30/06/2024") -> 0 | E20: =COUNTIFS('Datos Primaria'!$E:$E,E$2,'Datos Primaria'!$C:$C,">=01/06/2024",'Datos Primaria'!$C:$C,"<=30/06/2024") -> 2 | F20: =COUNTIFS('Datos Primaria'!$E:$E,F$2,'Datos Primaria'!$C:$C,">=01/06/2024",'Datos Primaria'!$C:$C,"<=30/06/2024") -> 2 | G20: =COUNTIFS('Datos Primaria'!$E:$E,G$2,'Datos Primaria'!$C:$C,">=01/06/2024",'Datos Primaria'!$C:$C,"<=30/06/2024") -> 0 | H20: =SUM(C20:G20) -> 5 | K20: Junio | L20: =SUM(C$15:C20) -> 4 | M20: =SUM(D$15:D20) -> 9 | N20: =SUM(E$15:E20) -> 7 | O20: =SUM(F$15:F20) -> 9 | P20: =SUM(G$15:G20) -> 2 | Q20: =SUM(L20:P20) -> 31 | T20: Junio | U20: =SUM(C$3:C20) -> 31 | V20: =SUM(D$3:D20) -> 23 | W20: =SUM(E$3:E20) -> 28 | X20: =SUM(F$3:F20) -> 25 | Y20: =SUM(G$3:G20) -> 23 | Z20: =SUM(U20:Y20) -> 130
B21: Julio | C21: =COUNTIFS('Datos Primaria'!$E:$E,C$2,'Datos Primaria'!$C:$C,">=01/07/2024",'Datos Primaria'!$C:$C,"<=31/07/2024") -> 2 | D21: =COUNTIFS('Datos Primaria'!$E:$E,D$2,'Datos Primaria'!$C:$C,">=01/07/2024",'Datos Primaria'!$C:$C,"<=31/07/2024") -> 1 | E21: =COUNTIFS('Datos Primaria'!$E:$E,E$2,'Datos Primaria'!$C:$C,">=01/07/2024",'Datos Primaria'!$C:$C,"<=31/07/2024") -> 1 | F21: =COUNTIFS('Datos Primaria'!$E:$E,F$2,'Datos Primaria'!$C:$C,">=01/07/2024",'Datos Primaria'!$C:$C,"<=31/07/2024") -> 2 | G21: =COUNTIFS('Datos Primaria'!$E:$E,G$2,'Datos Primaria'!$C:$C,">=01/07/2024",'Datos Primaria'!$C:$C,"<=31/07/2024") -> 2 | H21: =SUM(C21:G21) -> 8 | K21: Julio | L21: =SUM(C$15:C21) -> 6 | M21: =SUM(D$15:D21) -> 10 | N21: =SUM(E$15:E21) -> 8 | O21: =SUM(F$15:F21) -> 11 | P21: =SUM(G$15:G21) -> 4 | Q21: =SUM(L21:P21) -> 39 | T21: Julio | U21: =SUM(C$3:C21) -> 33 | V21: =SUM(D$3:D21) -> 24 | W21: =SUM(E$3:E21) -> 29 | X21: =SUM(F$3:F21) -> 27 | Y21: =SUM(G$3:G21) -> 25 | Z21: =SUM(U21:Y21) -> 138
B22: Agosto | C22: =COUNTIFS('Datos Primaria'!$E:$E,C$2,'Datos Primaria'!$C:$C,">=01/08/2024",'Datos Primaria'!$C:$C,"<=31/08/2024") -> 3 | D22: =COUNTIFS('Datos Primaria'!$E:$E,D$2,'Datos Primaria'!$C:$C,">=01/08/2024",'Datos Primaria'!$C:$C,"<=31/08/2024") -> 0 | E22: =COUNTIFS('Datos Primaria'!$E:$E,E$2,'Datos Primaria'!$C:$C,">=01/08/2024",'Datos Primaria'!$C:$C,"<=31/08/2024") -> 1 | F22: =COUNTIFS('Datos Primaria'!$E:$E,F$2,'Datos Primaria'!$C:$C,">=01/08/2024",'Datos Primaria'!$C:$C,"<=31/08/2024") -> 1 | G22: =COUNTIFS('Datos Primaria'!$E:$E,G$2,'Datos Primaria'!$C:$C,">=01/08/2024",'Datos Primaria'!$C:$C,"<=31/08/2024") -> 4 | H22: =SUM(C22:G22) -> 9 | K22: Agosto | L22: =SUM(C$15:C22) -> 9 | M22: =SUM(D$15:D22) -> 10 | N22: =SUM(E$15:E22) -> 9 | O22: =SUM(F$15:F22) -> 12 | P22: =SUM(G$15:G22) -> 8 | Q22: =SUM(L22:P22) -> 48 | T22: Agosto | U22: =SUM(C$3:C22) -> 36 | V22: =SUM(D$3:D22) -> 24 | W22: =SUM(E$3:E22) -> 30 | X22: =SUM(F$3:F22) -> 28 | Y22: =SUM(G$3:G22) -> 29 | Z22: =SUM(U22:Y22) -> 147
B23: Septiembre | C23: =COUNTIFS('Datos Primaria'!$E:$E,C$2,'Datos Primaria'!$C:$C,">=01/09/2024",'Datos Primaria'!$C:$C,"<=30/09/2024") -> 0 | D23: =COUNTIFS('Datos Primaria'!$E:$E,D$2,'Datos Primaria'!$C:$C,">=01/09/2024",'Datos Primaria'!$C:$C,"<=30/09/2024") -> 0 | E23: =COUNTIFS('Datos Primaria'!$E:$E,E$2,'Datos Primaria'!$C:$C,">=01/09/2024",'Datos Primaria'!$C:$C,"<=30/09/2024") -> 1 | F23: =COUNTIFS('Datos Primaria'!$E:$E,F$2,'Datos Primaria'!$C:$C,">=01/09/2024",'Datos Primaria'!$C:$C,"<=30/09/2024") -> 1 | G23: =COUNTIFS('Datos Primaria'!$E:$E,G$2,'Datos Primaria'!$C:$C,">=01/09/2024",'Datos Primaria'!$C:$C,"<=30/09/2024") -> 2 | H23: =SUM(C23:G23) -> 4 | K23: Septiembre | L23: =SUM(C$15:C23) -> 9 | M23: =SUM(D$15:D23) -> 10 | N23: =SUM(E$15:E23) -> 10 | O23: =SUM(F$15:F23) -> 13 | P23: =SUM(G$15:G23) -> 10 | Q23: =SUM(L23:P23) -> 52 | T23: Septiembre | U23: =SUM(C$3:C23) -> 36 | V23: =SUM(D$3:D23) -> 24 | W23: =SUM(E$3:E23) -> 31 | X23: =SUM(F$3:F23) -> 29 | Y23: =SUM(G$3:G23) -> 31 | Z23: =SUM(U23:Y23) -> 151
B24: Octubre | C24: =COUNTIFS('Datos Primaria'!$E:$E,C$2,'Datos Primaria'!$C:$C,">=01/10/2024",'Datos Primaria'!$C:$C,"<=31/10/2024") -> 1 | D24: =COUNTIFS('Datos Primaria'!$E:$E,D$2,'Datos Primaria'!$C:$C,">=01/10/2024",'Datos Primaria'!$C:$C,"<=31/10/2024") -> 1 | E24: =COUNTIFS('Datos Primaria'!$E:$E,E$2,'Datos Primaria'!$C:$C,">=01/10/2024",'Datos Primaria'!$C:$C,"<=31/10/2024") -> 2 | F24: =COUNTIFS('Datos Primaria'!$E:$E,F$2,'Datos Primaria'!$C:$C,">=01/10/2024",'Datos Primaria'!$C:$C,"<=31/10/2024") -> 2 | G24: =COUNTIFS('Datos Primaria'!$E:$E,G$2,'Datos Primaria'!$C:$C,">=01/10/2024",'Datos Primaria'!$C:$C,"<=31/10/2024") -> 1 | H24: =SUM(C24:G24) -> 7 | K24: Octubre | L24: =SUM(C$15:C24) -> 10 | M24: =SUM(D$15:D24) -> 11 | N24: =SUM(E$15:E24) -> 12 | O24: =SUM(F$15:F24) -> 15 | P24: =SUM(G$15:G24) -> 11 | Q24: =SUM(L24:P24) -> 59 | T24: Octubre | U24: =SUM(C$3:C24) -> 37 | V24: =SUM(D$3:D24) -> 25 | W24: =SUM(E$3:E24) -> 33 | X24: =SUM(F$3:F24) -> 31 | Y24: =SUM(G$3:G24) -> 32 | Z24: =SUM(U24:Y24) -> 158
B25: Noviembre | C25: =COUNTIFS('Datos Primaria'!$E:$E,C$2,'Datos Primaria'!$C:$C,">=01/11/2024",'Datos Primaria'!$C:$C,"<=30/11/2024") -> 1 | D25: =COUNTIFS('Datos Primaria'!$E:$E,D$2,'Datos Primaria'!$C:$C,">=01/11/2024",'Datos Primaria'!$C:$C,"<=30/11/2024") -> 2 | E25: =COUNTIFS('Datos Primaria'!$E:$E,E$2,'Datos Primaria'!$C:$C,">=01/11/2024",'Datos Primaria'!$C:$C,"<=30/11/2024") -> 2 | F25: =COUNTIFS('Datos Primaria'!$E:$E,F$2,'Datos Primaria'!$C:$C,">=01/11/2024",'Datos Primaria'!$C:$C,"<=30/11/2024") -> 3 | G25: =COUNTIFS('Datos Primaria'!$E:$E,G$2,'Datos Primaria'!$C:$C,">=01/11/2024",'Datos Primaria'!$C:$C,"<=30/11/2024") -> 5 | H25: =SUM(C25:G25) -> 13 | K25: Noviembre | L25: =SUM(C$15:C25) -> 11 | M25: =SUM(D$15:D25) -> 13 | N25: =SUM(E$15:E25) -> 14 | O25: =SUM(F$15:F25) -> 18 | P25: =SUM(G$15:G25) -> 16 | Q25: =SUM(L25:P25) -> 72 | T25: Noviembre | U25: =SUM(C$3:C25) -> 38 | V25: =SUM(D$3:D25) -> 27 | W25: =SUM(E$3:E25) -> 35 | X25: =SUM(F$3:F25) -> 34 | Y25: =SUM(G$3:G25) -> 37 | Z25: =SUM(U25:Y25) -> 171
B26: Diciembre | C26: =COUNTIFS('Datos Primaria'!$E:$E,C$2,'Datos Primaria'!$C:$C,">=01/12/2024",'Datos Primaria'!$C:$C,"<=31/12/2024") -> 0 | D26: =COUNTIFS('Datos Primaria'!$E:$E,D$2,'Datos Primaria'!$C:$C,">=01/12/2024",'Datos Primaria'!$C:$C,"<=31/12/2024") -> 0 | E26: =COUNTIFS('Datos Primaria'!$E:$E,E$2,'Datos Primaria'!$C:$C,">=01/12/2024",'Datos Primaria'!$C:$C,"<=31/12/2024") -> 1 | F26: =COUNTIFS('Datos Primaria'!$E:$E,F$2,'Datos Primaria'!$C:$C,">=01/12/2024",'Datos Primaria'!$C:$C,"<=31/12/2024") -> 0 | G26: =COUNTIFS('Datos Primaria'!$E:$E,G$2,'Datos Primaria'!$C:$C,">=01/12/2024",'Datos Primaria'!$C:$C,"<=31/12/2024") -> 0 | H26: =SUM(C26:G26) -> 1 | K26: Diciembre | L26: =SUM(C$15:C26) -> 11 | M26: =SUM(D$15:D26) -> 13 | N26: =SUM(E$15:E26) -> 15 | O26: =SUM(F$15:F26) -> 18 | P26: =SUM(G$15:G26) -> 16 | Q26: =SUM(L26:P26) -> 73 | T26: Diciembre | U26: =SUM(C$3:C26) -> 38 | V26: =SUM(D$3:D26) -> 27 | W26: =SUM(E$3:E26) -> 36 | X26: =SUM(F$3:F26) -> 34 | Y26: =SUM(G$3:G26) -> 37 | Z26: =SUM(U26:Y26) -> 172
A27: 2025 | B27: Enero | C27: =COUNTIFS('Datos Primaria'!$E:$E,C$2,'Datos Primaria'!$C:$C,">=01/01/2025",'Datos Primaria'!$C:$C,"<=31/01/2025") -> 4 | D27: =COUNTIFS('Datos Primaria'!$E:$E,D$2,'Datos Primaria'!$C:$C,">=01/01/2025",'Datos Primaria'!$C:$C,"<=31/01/2025") -> 1 | E27: =COUNTIFS('Datos Primaria'!$E:$E,E$2,'Datos Primaria'!$C:$C,">=01/01/2025",'Datos Primaria'!$C:$C,"<=31/01/2025") -> 4 | F27: =COUNTIFS('Datos Primaria'!$E:$E,F$2,'Datos Primaria'!$C:$C,">=01/01/2025",'Datos Primaria'!$C:$C,"<=31/01/2025") -> 4 | G27: =COUNTIFS('Datos Primaria'!$E:$E,G$2,'Datos Primaria'!$C:$C,">=01/01/2025",'Datos Primaria'!$C:$C,"<=31/01/2025") -> 1 | H27: =SUM(C27:G27) -> 14 | J27: =A27 -> 2025 | K27: Enero | L27: =SUM(C$27:C27) -> 4 | M27: =SUM(D$27:D27) -> 1 | N27: =SUM(E$27:E27) -> 4 | O27: =SUM(F$27:F27) -> 4 | P27: =SUM(G$27:G27) -> 1 | Q27: =SUM(L27:P27) -> 14 | S27: =A27 -> 2025 | T27: Enero | U27: =SUM(C$3:C27) -> 42 | V27: =SUM(D$3:D27) -> 28 | W27: =SUM(E$3:E27) -> 40 | X27: =SUM(F$3:F27) -> 38 | Y27: =SUM(G$3:G27) -> 38 | Z27: =SUM(U27:Y27) -> 186
B28: Febrero | C28: =COUNTIFS('Datos Primaria'!$E:$E,C$2,'Datos Primaria'!$C:$C,">=01/02/2025",'Datos Primaria'!$C:$C,"<=28/02/2025") -> 1 | D28: =COUNTIFS('Datos Primaria'!$E:$E,D$2,'Datos Primaria'!$C:$C,">=01/02/2025",'Datos Primaria'!$C:$C,"<=28/02/2025") -> 1 | E28: =COUNTIFS('Datos Primaria'!$E:$E,E$2,'Datos Primaria'!$C:$C,">=01/02/2025",'Datos Primaria'!$C:$C,"<=28/02/2025") -> 1 | F28: =COUNTIFS('Datos Primaria'!$E:$E,F$2,'Datos Primaria'!$C:$C,">=01/02/2025",'Datos Primaria'!$C:$C,"<=28/02/2025") -> 3 | G28: =COUNTIFS('Datos Primaria'!$E:$E,G$2,'Datos Primaria'!$C:$C,">=01/02/2025",'Datos Primaria'!$C:$C,"<=28/02/2025") -> 2 | H28: =SUM(C28:G28) -> 8 | K28: Febrero | L28: =SUM(C$27:C28) -> 5 | M28: =SUM(D$27:D28) -> 2 | N28: =SUM(E$27:E28) -> 5 | O28: =SUM(F$27:F28) -> 7 | P28: =SUM(G$27:G28) -> 3 | Q28: =SUM(L28:P28) -> 22 | T28: Febrero | U28: =SUM(C$3:C28) -> 43 | V28: =SUM(D$3:D28) -> 29 | W28: =SUM(E$3:E28) -> 41 | X28: =SUM(F$3:F28) -> 41 | Y28: =SUM(G$3:G28) -> 40 | Z28: =SUM(U28:Y28) -> 194
B29: Marzo | C29: =COUNTIFS('Datos Primaria'!$E:$E,C$2,'Datos Primaria'!$C:$C,">=01/03/2025",'Datos Primaria'!$C:$C,"<=31/03/2025") -> 0 | D29: =COUNTIFS('Datos Primaria'!$E:$E,D$2,'Datos Primaria'!$C:$C,">=01/03/2025",'Datos Primaria'!$C:$C,"<=31/03/2025") -> 1 | E29: =COUNTIFS('Datos Primaria'!$E:$E,E$2,'Datos Primaria'!$C:$C,">=01/03/2025",'Datos Primaria'!$C:$C,"<=31/03/2025") -> 1 | F29: =COUNTIFS('Datos Primaria'!$E:$E,F$2,'Datos Primaria'!$C:$C,">=01/03/2025",'Datos Primaria'!$C:$C,"<=31/03/2025") -> 1 | G29: =COUNTIFS('Datos Primaria'!$E:$E,G$2,'Datos Primaria'!$C:$C,">=01/03/2025",'Datos Primaria'!$C:$C,"<=31/03/2025") -> 2 | H29: =SUM(C29:G29) -> 5 | K29: Marzo | L29: =SUM(C$27:C29) -> 5 | M29: =SUM(D$27:D29) -> 3 | N29: =SUM(E$27:E29) -> 6 | O29: =SUM(F$27:F29) -> 8 | P29: =SUM(G$27:G29) -> 5 | Q29: =SUM(L29:P29) -> 27 | T29: Marzo | U29: =SUM(C$3:C29) -> 43 | V29: =SUM(D$3:D29) -> 30 | W29: =SUM(E$3:E29) -> 42 | X29: =SUM(F$3:F29) -> 42 | Y29: =SUM(G$3:G29) -> 42 | Z29: =SUM(U29:Y29) -> 199
B30: Abril | C30: =COUNTIFS('Datos Primaria'!$E:$E,C$2,'Datos Primaria'!$C:$C,">=01/04/2025",'Datos Primaria'!$C:$C,"<=30/04/2025") -> 1 | D30: =COUNTIFS('Datos Primaria'!$E:$E,D$2,'Datos Primaria'!$C:$C,">=01/04/2025",'Datos Primaria'!$C:$C,"<=30/04/2025") -> 6 | E30: =COUNTIFS('Datos Primaria'!$E:$E,E$2,'Datos Primaria'!$C:$C,">=01/04/2025",'Datos Primaria'!$C:$C,"<=30/04/2025") -> 2 | F30: =COUNTIFS('Datos Primaria'!$E:$E,F$2,'Datos Primaria'!$C:$C,">=01/04/2025",'Datos Primaria'!$C:$C,"<=30/04/2025") -> 1 | G30: =COUNTIFS('Datos Primaria'!$E:$E,G$2,'Datos Primaria'!$C:$C,">=01/04/2025",'Datos Primaria'!$C:$C,"<=30/04/2025") -> 4 | H30: =SUM(C30:G30) -> 14 | K30: Abril | L30: =SUM(C$27:C30) -> 6 | M30: =SUM(D$27:D30) -> 9 | N30: =SUM(E$27:E30) -> 8 | O30: =SUM(F$27:F30) -> 9 | P30: =SUM(G$27:G30) -> 9 | Q30: =SUM(L30:P30) -> 41 | T30: Abril | U30: =SUM(C$3:C30) -> 44 | V30: =SUM(D$3:D30) -> 36 | W30: =SUM(E$3:E30) -> 44 | X30: =SUM(F$3:F30) -> 43 | Y30: =SUM(G$3:G30) -> 46 | Z30: =SUM(U30:Y30) -> 213
B31: Mayo | C31: =COUNTIFS('Datos Primaria'!$E:$E,C$2,'Datos Primaria'!$C:$C,">=01/05/2025",'Datos Primaria'!$C:$C,"<=31/05/2025") -> 4 | D31: =COUNTIFS('Datos Primaria'!$E:$E,D$2,'Datos Primaria'!$C:$C,">=01/05/2025",'Datos Primaria'!$C:$C,"<=31/05/2025") -> 4 | E31: =COUNTIFS('Datos Primaria'!$E:$E,E$2,'Datos Primaria'!$C:$C,">=01/05/2025",'Datos Primaria'!$C:$C,"<=31/05/2025") -> 4 | F31: =COUNTIFS('Datos Primaria'!$E:$E,F$2,'Datos Primaria'!$C:$C,">=01/05/2025",'Datos Primaria'!$C:$C,"<=31/05/2025") -> 2 | G31: =COUNTIFS('Datos Primaria'!$E:$E,G$2,'Datos Primaria'!$C:$C,">=01/05/2025",'Datos Primaria'!$C:$C,"<=31/05/2025") -> 1 | H31: =SUM(C31:G31) -> 15 | K31: Mayo | L31: =SUM(C$27:C31) -> 10 | M31: =SUM(D$27:D31) -> 13 | N31: =SUM(E$27:E31) -> 12 | O31: =SUM(F$27:F31) -> 11 | P31: =SUM(G$27:G31) -> 10 | Q31: =SUM(L31:P31) -> 56 | T31: Mayo | U31: =SUM(C$3:C31) -> 48 | V31: =SUM(D$3:D31) -> 40 | W31: =SUM(E$3:E31) -> 48 | X31: =SUM(F$3:F31) -> 45 | Y31: =SUM(G$3:G31) -> 47 | Z31: =SUM(U31:Y31) -> 228
B32: Junio | C32: =COUNTIFS('Datos Primaria'!$E:$E,C$2,'Datos Primaria'!$C:$C,">=01/06/2025",'Datos Primaria'!$C:$C,"<=30/06/2025") -> 3 | D32: =COUNTIFS('Datos Primaria'!$E:$E,D$2,'Datos Primaria'!$C:$C,">=01/06/2025",'Datos Primaria'!$C:$C,"<=30/06/2025") -> 1 | E32: =COUNTIFS('Datos Primaria'!$E:$E,E$2,'Datos Primaria'!$C:$C,">=01/06/2025",'Datos Primaria'!$C:$C,"<=30/06/2025") -> 1 | F32: =COUNTIFS('Datos Primaria'!$E:$E,F$2,'Datos Primaria'!$C:$C,">=01/06/2025",'Datos Primaria'!$C:$C,"<=30/06/2025") -> 3 | G32: =COUNTIFS('Datos Primaria'!$E:$E,G$2,'Datos Primaria'!$C:$C,">=01/06/2025",'Datos Primaria'!$C:$C,"<=30/06/2025") -> 0 | H32: =SUM(C32:G32) -> 8 | K32: Junio | L32: =SUM(C$27:C32) -> 13 | M32: =SUM(D$27:D32) -> 14 | N32: =SUM(E$27:E32) -> 13 | O32: =SUM(F$27:F32) -> 14 | P32: =SUM(G$27:G32) -> 10 | Q32: =SUM(L32:P32) -> 64 | T32: Junio | U32: =SUM(C$3:C32) -> 51 | V32: =SUM(D$3:D32) -> 41 | W32: =SUM(E$3:E32) -> 49 | X32: =SUM(F$3:F32) -> 48 | Y32: =SUM(G$3:G32) -> 47 | Z32: =SUM(U32:Y32) -> 236
B33: Julio | C33: =COUNTIFS('Datos Primaria'!$E:$E,C$2,'Datos Primaria'!$C:$C,">=01/07/2025",'Datos Primaria'!$C:$C,"<=31/07/2025") -> 1 | D33: =COUNTIFS('Datos Primaria'!$E:$E,D$2,'Datos Primaria'!$C:$C,">=01/07/2025",'Datos Primaria'!$C:$C,"<=31/07/2025") -> 0 | E33: =COUNTIFS('Datos Primaria'!$E:$E,E$2,'Datos Primaria'!$C:$C,">=01/07/2025",'Datos Primaria'!$C:$C,"<=31/07/2025") -> 4 | F33: =COUNTIFS('Datos Primaria'!$E:$E,F$2,'Datos Primaria'!$C:$C,">=01/07/2025",'Datos Primaria'!$C:$C,"<=31/07/2025") -> 0 | G33: =COUNTIFS('Datos Primaria'!$E:$E,G$2,'Datos Primaria'!$C:$C,">=01/07/2025",'Datos Primaria'!$C:$C,"<=31/07/2025") -> 2 | H33: =SUM(C33:G33) -> 7 | K33: Julio | L33: =SUM(C$27:C33) -> 14 | M33: =SUM(D$27:D33) -> 14 | N33: =SUM(E$27:E33) -> 17 | O33: =SUM(F$27:F33) -> 14 | P33: =SUM(G$27:G33) -> 12 | Q33: =SUM(L33:P33) -> 71 | T33: Julio | U33: =SUM(C$3:C33) -> 52 | V33: =SUM(D$3:D33) -> 41 | W33: =SUM(E$3:E33) -> 53 | X33: =SUM(F$3:F33) -> 48 | Y33: =SUM(G$3:G33) -> 49 | Z33: =SUM(U33:Y33) -> 243
B34: Agosto | C34: =COUNTIFS('Datos Primaria'!$E:$E,C$2,'Datos Primaria'!$C:$C,">=01/08/2025",'Datos Primaria'!$C:$C,"<=31/08/2025") -> 4 | D34: =COUNTIFS('Datos Primaria'!$E:$E,D$2,'Datos Primaria'!$C:$C,">=01/08/2025",'Datos Primaria'!$C:$C,"<=31/08/2025") -> 0 | E34: =COUNTIFS('Datos Primaria'!$E:$E,E$2,'Datos Primaria'!$C:$C,">=01/08/2025",'Datos Primaria'!$C:$C,"<=31/08/2025") -> 1 | F34: =COUNTIFS('Datos Primaria'!$E:$E,F$2,'Datos Primaria'!$C:$C,">=01/08/2025",'Datos Primaria'!$C:$C,"<=31/08/2025") -> 1 | G34: =COUNTIFS('Datos Primaria'!$E:$E,G$2,'Datos Primaria'!$C:$C,">=01/08/2025",'Datos Primaria'!$C:$C,"<=31/08/2025") -> 3 | H34: =SUM(C34:G34) -> 9 | K34: Agosto | L34: =SUM(C$27:C34) -> 18 | M34: =SUM(D$27:D34) -> 14 | N34: =SUM(E$27:E34) -> 18 | O34: =SUM(F$27:F34) -> 15 | P34: =SUM(G$27:G34) -> 15 | Q34: =SUM(L34:P34) -> 80 | T34: Agosto | U34: =SUM(C$3:C34) -> 56 | V34: =SUM(D$3:D34) -> 41 | W34: =SUM(E$3:E34) -> 54 | X34: =SUM(F$3:F34) -> 49 | Y34: =SUM(G$3:G34) -> 52 | Z34: =SUM(U34:Y34) -> 252
B35: Septiembre | C35: =COUNTIFS('Datos Primaria'!$E:$E,C$2,'Datos Primaria'!$C:$C,">=01/09/2025",'Datos Primaria'!$C:$C,"<=30/09/2025") -> 2 | D35: =COUNTIFS('Datos Primaria'!$E:$E,D$2,'Datos Primaria'!$C:$C,">=01/09/2025",'Datos Primaria'!$C:$C,"<=30/09/2025") -> 3 | E35: =COUNTIFS('Datos Primaria'!$E:$E,E$2,'Datos Primaria'!$C:$C,">=01/09/2025",'Datos Primaria'!$C:$C,"<=30/09/2025") -> 0 | F35: =COUNTIFS('Datos Primaria'!$E:$E,F$2,'Datos Primaria'!$C:$C,">=01/09/2025",'Datos Primaria'!$C:$C,"<=30/09/2025") -> 2 | G35: =COUNTIFS('Datos Primaria'!$E:$E,G$2,'Datos Primaria'!$C:$C,">=01/09/2025",'Datos Primaria'!$C:$C,"<=30/09/2025") -> 2 | H35: =SUM(C35:G35) -> 9 | K35: Septiembre | L35: =SUM(C$27:C35) -> 20 | M35: =SUM(D$27:D35) -> 17 | N35: =SUM(E$27:E35) -> 18 | O35: =SUM(F$27:F35) -> 17 | P35: =SUM(G$27:G35) -> 17 | Q35: =SUM(L35:P35) -> 89 | T35: Septiembre | U35: =SUM(C$3:C35) -> 58 | V35: =SUM(D$3:D35) -> 44 | W35: =SUM(E$3:E35) -> 54 | X35: =SUM(F$3:F35) -> 51 | Y35: =SUM(G$3:G35) -> 54 | Z35: =SUM(U35:Y35) -> 261
B36: Octubre | C36: =COUNTIFS('Datos Primaria'!$E:$E,C$2,'Datos Primaria'!$C:$C,">=01/10/2025",'Datos Primaria'!$C:$C,"<=31/10/2025") -> 1 | D36: =COUNTIFS('Datos Primaria'!$E:$E,D$2,'Datos Primaria'!$C:$C,">=01/10/2025",'Datos Primaria'!$C:$C,"<=31/10/2025") -> 2 | E36: =COUNTIFS('Datos Primaria'!$E:$E,E$2,'Datos Primaria'!$C:$C,">=01/10/2025",'Datos Primaria'!$C:$C,"<=31/10/2025") -> 2 | F36: =COUNTIFS('Datos Primaria'!$E:$E,F$2,'Datos Primaria'!$C:$C,">=01/10/2025",'Datos Primaria'!$C:$C,"<=31/10/2025") -> 2 | G36: =COUNTIFS('Datos Primaria'!$E:$E,G$2,'Datos Primaria'!$C:$C,">=01/10/2025",'Datos Primaria'!$C:$C,"<=31/10/2025") -> 2 | H36: =SUM(C36:G36) -> 9 | K36: Octubre | L36: =SUM(C$27:C36) -> 21 | M36: =SUM(D$27:D36) -> 19 | N36: =SUM(E$27:E36) -> 20 | O36: =SUM(F$27:F36) -> 19 | P36: =SUM(G$27:G36) -> 19 | Q36: =SUM(L36:P36) -> 98 | T36: Octubre | U36: =SUM(C$3:C36) -> 59 | V36: =SUM(D$3:D36) -> 46 | W36: =SUM(E$3:E36) -> 56 | X36: =SUM(F$3:F36) -> 53 | Y36: =SUM(G$3:G36) -> 56 | Z36: =SUM(U36:Y36) -> 270
B37: Noviembre | C37: =COUNTIFS('Datos Primaria'!$E:$E,C$2,'Datos Primaria'!$C:$C,">=01/11/2025",'Datos Primaria'!$C:$C,"<=30/11/2025") -> 2 | D37: =COUNTIFS('Datos Primaria'!$E:$E,D$2,'Datos Primaria'!$C:$C,">=01/11/2025",'Datos Primaria'!$C:$C,"<=30/11/2025") -> 0 | E37: =COUNTIFS('Datos Primaria'!$E:$E,E$2,'Datos Primaria'!$C:$C,">=01/11/2025",'Datos Primaria'!$C:$C,"<=30/11/2025") -> 5 | F37: =COUNTIFS('Datos Primaria'!$E:$E,F$2,'Datos Primaria'!$C:$C,">=01/11/2025",'Datos Primaria'!$C:$C,"<=30/11/2025") -> 1 | G37: =COUNTIFS('Datos Primaria'!$E:$E,G$2,'Datos Primaria'!$C:$C,">=01/11/2025",'Datos Primaria'!$C:$C,"<=30/11/2025") -> 0 | H37: =SUM(C37:G37) -> 8 | K37: Noviembre | L37: =SUM(C$27:C37) -> 23 | M37: =SUM(D$27:D37) -> 19 | N37: =SUM(E$27:E37) -> 25 | O37: =SUM(F$27:F37) -> 20 | P37: =SUM(G$27:G37) -> 19 | Q37: =SUM(L37:P37) -> 106 | T37: Noviembre | U37: =SUM(C$3:C37) -> 61 | V37: =SUM(D$3:D37) -> 46 | W37: =SUM(E$3:E37) -> 61 | X37: =SUM(F$3:F37) -> 54 | Y37: =SUM(G$3:G37) -> 56 | Z37: =SUM(U37:Y37) -> 278
B38: Diciembre | C38: =COUNTIFS('Datos Primaria'!$E:$E,C$2,'Datos Primaria'!$C:$C,">=01/12/2025",'Datos Primaria'!$C:$C,"<=31/12/2025") -> 2 | D38: =COUNTIFS('Datos Primaria'!$E:$E,D$2,'Datos Primaria'!$C:$C,">=01/12/2025",'Datos Primaria'!$C:$C,"<=31/12/2025") -> 0 | E38: =COUNTIFS('Datos Primaria'!$E:$E,E$2,'Datos Primaria'!$C:$C,">=01/12/2025",'Datos Primaria'!$C:$C,"<=31/12/2025") -> 2 | F38: =COUNTIFS('Datos Primaria'!$E:$E,F$2,'Datos Primaria'!$C:$C,">=01/12/2025",'Datos Primaria'!$C:$C,"<=31/12/2025") -> 1 | G38: =COUNTIFS('Datos Primaria'!$E:$E,G$2,'Datos Primaria'!$C:$C,">=01/12/2025",'Datos Primaria'!$C:$C,"<=31/12/2025") -> 2 | H38: =SUM(C38:G38) -> 7 | K38: Diciembre | L38: =SUM(C$27:C38) -> 25 | M38: =SUM(D$27:D38) -> 19 | N38: =SUM(E$27:E38) -> 27 | O38: =SUM(F$27:F38) -> 21 | P38: =SUM(G$27:G38) -> 21 | Q38: =SUM(L38:P38) -> 113 | T38: Diciembre | U38: =SUM(C$3:C38) -> 63 | V38: =SUM(D$3:D38) -> 46 | W38: =SUM(E$3:E38) -> 63 | X38: =SUM(F$3:F38) -> 55 | Y38: =SUM(G$3:G38) -> 58 | Z38: =SUM(U38:Y38) -> 285
B41: Inicio de pruebas por mes | K41: Inicio de pruebas acum año | T41: Inicio de pruebas acum todos los años
B42: MES | C42: 5° | D42: TOTAL | K42: MES | L42: 5° | M42: TOTAL | T42: MES | U42: 5° | V42: TOTAL
A43: =A3 -> 2023 | B43: Enero | C43: =COUNTIFS('Datos Primaria'!$E:$E,C$42,'Datos Primaria'!$H:$H,">=01/01/2023",'Datos Primaria'!$H:$H,"<=31/01/2023") -> 0 | D43: =SUM(C43) -> 0 | J43: =A43 -> 2023 | K43: Enero | L43: =SUM(C$43:C43) -> 0 | M43: =SUM(L43) -> 0 | S43: =A43 -> 2023 | T43: Enero | U43: =SUM(C$43:C43) -> 0 | V43: =SUM(U43) -> 0
B44: Febrero | C44: =COUNTIFS('Datos Primaria'!$E:$E,C$42,'Datos Primaria'!$H:$H,">=01/02/2023",'Datos Primaria'!$H:$H,"<=28/02/2023") -> 0 | D44: =SUM(C44) -> 0 | K44: Febrero | L44: =SUM(C$43:C44) -> 0 | M44: =SUM(L44) -> 0 | T44: Febrero | U44: =SUM(C$43:C44) -> 0 | V44: =SUM(U44) -> 0
B45: Marzo | C45: =COUNTIFS('Datos Primaria'!$E:$E,C$42,'Datos Primaria'!$H:$H,">=01/03/2023",'Datos Primaria'!$H:$H,"<=31/03/2023") -> 1 | D45: =SUM(C45) -> 1 | K45: Marzo | L45: =SUM(C$43:C45) -> 1 | M45: =SUM(L45) -> 1 | T45: Marzo | U45: =SUM(C$43:C45) -> 1 | V45: =SUM(U45) -> 1
B46: Abril | C46: =COUNTIFS('Datos Primaria'!$E:$E,C$42,'Datos Primaria'!$H:$H,">=01/04/2023",'Datos Primaria'!$H:$H,"<=30/04/2023") -> 0 | D46: =SUM(C46) -> 0 | K46: Abril | L46: =SUM(C$43:C46) -> 1 | M46: =SUM(L46) -> 1 | T46: Abril | U46: =SUM(C$43:C46) -> 1 | V46: =SUM(U46) -> 1
B47: Mayo | C47: =COUNTIFS('Datos Primaria'!$E:$E,C$42,'Datos Primaria'!$H:$H,">=01/05/2023",'Datos Primaria'!$H:$H,"<=31/05/2023") -> 0 | D47: =SUM(C47) -> 0 | K47: Mayo | L47: =SUM(C$43:C47) -> 1 | M47: =SUM(L47) -> 1 | T47: Mayo | U47: =SUM(C$43:C47) -> 1 | V47: =SUM(U47) -> 1
B48: Junio | C48: =COUNTIFS('Datos Primaria'!$E:$E,C$42,'Datos Primaria'!$H:$H,">=01/06/2023",'Datos Primaria'!$H:$H,"<=30/06/2023") -> 0 | D48: =SUM(C48) -> 0 | K48: Junio | L48: =SUM(C$43:C48) -> 1 | M48: =SUM(L48) -> 1 | T48: Junio | U48: =SUM(C$43:C48) -> 1 | V48: =SUM(U48) -> 1
B49: Julio | C49: =COUNTIFS('Datos Primaria'!$E:$E,C$42,'Datos Primaria'!$H:$H,">=01/07/2023",'Datos Primaria'!$H:$H,"<=31/07/2023") -> 1 | D49: =SUM(C49) -> 1 | K49: Julio | L49: =SUM(C$43:C49) -> 2 | M49: =SUM(L49) -> 2 | T49: Julio | U49: =SUM(C$43:C49) -> 2 | V49: =SUM(U49) -> 2
B50: Agosto | C50: =COUNTIFS('Datos Primaria'!$E:$E,C$42,'Datos Primaria'!$H:$H,">=01/08/2023",'Datos Primaria'!$H:$H,"<=31/08/2023") -> 1 | D50: =SUM(C50) -> 1 | K50: Agosto | L50: =SUM(C$43:C50) -> 3 | M50: =SUM(L50) -> 3 | T50: Agosto | U50: =SUM(C$43:C50) -> 3 | V50: =SUM(U50) -> 3
B51: Septiembre | C51: =COUNTIFS('Datos Primaria'!$E:$E,C$42,'Datos Primaria'!$H:$H,">=01/09/2023",'Datos Primaria'!$H:$H,"<=30/09/2023") -> 1 | D51: =SUM(C51) -> 1 | K51: Septiembre | L51: =SUM(C$43:C51) -> 4 | M51: =SUM(L51) -> 4 | T51: Septiembre | U51: =SUM(C$43:C51) -> 4 | V51: =SUM(U51) -> 4
B52: Octubre | C52: =COUNTIFS('Datos Primaria'!$E:$E,C$42,'Datos Primaria'!$H:$H,">=01/10/2023",'Datos Primaria'!$H:$H,"<=31/10/2023") -> 1 | D52: =SUM(C52) -> 1 | K52: Octubre | L52: =SUM(C$43:C52) -> 5 | M52: =SUM(L52) -> 5 | T52: Octubre | U52: =SUM(C$43:C52) -> 5 | V52: =SUM(U52) -> 5
B53: Noviembre | C53: =COUNTIFS('Datos Primaria'!$E:$E,C$42,'Datos Primaria'!$H:$H,">=01/11/2023",'Datos Primaria'!$H:$H,"<=30/11/2023") -> 1 | D53: =SUM(C53) -> 1 | K53: Noviembre | L53: =SUM(C$43:C53) -> 6 | M53: =SUM(L53) -> 6 | T53: Noviembre | U53: =SUM(C$43:C53) -> 6 | V53: =SUM(U53) -> 6
B54: Diciembre | C54: =COUNTIFS('Datos Primaria'!$E:$E,C$42,'Datos Primaria'!$H:$H,">=01/12/2023",'Datos Primaria'!$H:$H,"<=31/12/2023") -> 0 | D54: =SUM(C54) -> 0 | K54: Diciembre | L54: =SUM(C$43:C54) -> 6 | M54: =SUM(L54) -> 6 | T54: Diciembre | U54: =SUM(C$43:C54) -> 6 | V54: =SUM(U54) -> 6
A55: =A15 -> 2024 | B55: Enero | C55: =COUNTIFS('Datos Primaria'!$E:$E,C$42,'Datos Primaria'!$H:$H,">=01/01/2024",'Datos Primaria'!$H:$H,"<=31/01/2024") -> 0 | D55: =SUM(C55) -> 0 | J55: =A55 -> 2024 | K55: Enero | L55: =SUM(C$55:C55) -> 0 | M55: =SUM(L55) -> 0 | S55: =A55 -> 2024 | T55: Enero | U55: =SUM(C$43:C55) -> 6 | V55: =SUM(U55) -> 6
B56: Febrero | C56: =COUNTIFS('Datos Primaria'!$E:$E,C$42,'Datos Primaria'!$H:$H,">=01/02/2024",'Datos Primaria'!$H:$H,"<=29/02/2024") -> 0 | D56: =SUM(C56) -> 0 | K56: Febrero | L56: =SUM(C$55:C56) -> 0 | M56: =SUM(L56) -> 0 | T56: Febrero | U56: =SUM(C$43:C56) -> 6 | V56: =SUM(U56) -> 6
B57: Marzo | C57: =COUNTIFS('Datos Primaria'!$E:$E,C$42,'Datos Primaria'!$H:$H,">=01/03/2024",'Datos Primaria'!$H:$H,"<=31/03/2024") -> 0 | D57: =SUM(C57) -> 0 | K57: Marzo | L57: =SUM(C$55:C57) -> 0 | M57: =SUM(L57) -> 0 | T57: Marzo | U57: =SUM(C$43:C57) -> 6 | V57: =SUM(U57) -> 6
B58: Abril | C58: =COUNTIFS('Datos Primaria'!$E:$E,C$42,'Datos Primaria'!$H:$H,">=01/04/2024",'Datos Primaria'!$H:$H,"<=30/04/2024") -> 1 | D58: =SUM(C58) -> 1 | K58: Abril | L58: =SUM(C$55:C58) -> 1 | M58: =SUM(L58) -> 1 | T58: Abril | U58: =SUM(C$43:C58) -> 7 | V58: =SUM(U58) -> 7
B59: Mayo | C59: =COUNTIFS('Datos Primaria'!$E:$E,C$42,'Datos Primaria'!$H:$H,">=01/05/2024",'Datos Primaria'!$H:$H,"<=31/05/2024") -> 0 | D59: =SUM(C59) -> 0 | K59: Mayo | L59: =SUM(C$55:C59) -> 1 | M59: =SUM(L59) -> 1 | T59: Mayo | U59: =SUM(C$43:C59) -> 7 | V59: =SUM(U59) -> 7
B60: Junio | C60: =COUNTIFS('Datos Primaria'!$E:$E,C$42,'Datos Primaria'!$H:$H,">=01/06/2024",'Datos Primaria'!$H:$H,"<=30/06/2024") -> 1 | D60: =SUM(C60) -> 1 | K60: Junio | L60: =SUM(C$55:C60) -> 2 | M60: =SUM(L60) -> 2 | T60: Junio | U60: =SUM(C$43:C60) -> 8 | V60: =SUM(U60) -> 8
B61: Julio | C61: =COUNTIFS('Datos Primaria'!$E:$E,C$42,'Datos Primaria'!$H:$H,">=01/07/2024",'Datos Primaria'!$H:$H,"<=31/07/2024") -> 1 | D61: =SUM(C61) -> 1 | K61: Julio | L61: =SUM(C$55:C61) -> 3 | M61: =SUM(L61) -> 3 | T61: Julio | U61: =SUM(C$43:C61) -> 9 | V61: =SUM(U61) -> 9
B62: Agosto | C62: =COUNTIFS('Datos Primaria'!$E:$E,C$42,'Datos Primaria'!$H:$H,">=01/08/2024",'Datos Primaria'!$H:$H,"<=31/08/2024") -> 1 | D62: =SUM(C62) -> 1 | K62: Agosto | L62: =SUM(C$55:C62) -> 4 | M62: =SUM(L62) -> 4 | T62: Agosto | U62: =SUM(C$43:C62) -> 10 | V62: =SUM(U62) -> 10
B63: Septiembre | C63: =COUNTIFS('Datos Primaria'!$E:$E,C$42,'Datos Primaria'!$H:$H,">=01/09/2024",'Datos Primaria'!$H:$H,"<=30/09/2024") -> 1 | D63: =SUM(C63) -> 1 | K63: Septiembre | L63: =SUM(C$55:C63) -> 5 | M63: =SUM(L63) -> 5 | T63: Septiembre | U63: =SUM(C$43:C63) -> 11 | V63: =SUM(U63) -> 11
B64: Octubre | C64: =COUNTIFS('Datos Primaria'!$E:$E,C$42,'Datos Primaria'!$H:$H,">=01/10/2024",'Datos Primaria'!$H:$H,"<=31/10/2024") -> 2 | D64: =SUM(C64) -> 2 | K64: Octubre | L64: =SUM(C$55:C64) -> 7 | M64: =SUM(L64) -> 7 | T64: Octubre | U64: =SUM(C$43:C64) -> 13 | V64: =SUM(U64) -> 13
B65: Noviembre | C65: =COUNTIFS('Datos Primaria'!$E:$E,C$42,'Datos Primaria'!$H:$H,">=01/11/2024",'Datos Primaria'!$H:$H,"<=30/11/2024") -> 0 | D65: =SUM(C65) -> 0 | K65: Noviembre | L65: =SUM(C$55:C65) -> 7 | M65: =SUM(L65) -> 7 | T65: Noviembre | U65: =SUM(C$43:C65) -> 13 | V65: =SUM(U65) -> 13
B66: Diciembre | C66: =COUNTIFS('Datos Primaria'!$E:$E,C$42,'Datos Primaria'!$H:$H,">=01/12/2024",'Datos Primaria'!$H:$H,"<=31/12/2024") -> 3 | D66: =SUM(C66) -> 3 | K66: Diciembre | L66: =SUM(C$55:C66) -> 10 | M66: =SUM(L66) -> 10 | T66: Diciembre | U66: =SUM(C$43:C66) -> 16 | V66: =SUM(U66) -> 16
A67: =A27 -> 2025 | B67: Enero | C67: =COUNTIFS('Datos Primaria'!$E:$E,C$42,'Datos Primaria'!$H:$H,">=01/01/2025",'Datos Primaria'!$H:$H,"<=31/01/2025") -> 0 | D67: =SUM(C67) -> 0 | J67: =A67 -> 2025 | K67: Enero | L67: =SUM(C$67:C67) -> 0 | M67: =SUM(L67) -> 0 | S67: =A67 -> 2025 | T67: Enero | U67: =SUM(C$43:C67) -> 16 | V67: =SUM(U67) -> 16
B68: Febrero | C68: =COUNTIFS('Datos Primaria'!$E:$E,C$42,'Datos Primaria'!$H:$H,">=01/02/2025",'Datos Primaria'!$H:$H,"<=28/02/2025") -> 1 | D68: =SUM(C68) -> 1 | K68: Febrero | L68: =SUM(C$67:C68) -> 1 | M68: =SUM(L68) -> 1 | T68: Febrero | U68: =SUM(C$43:C68) -> 17 | V68: =SUM(U68) -> 17
B69: Marzo | C69: =COUNTIFS('Datos Primaria'!$E:$E,C$42,'Datos Primaria'!$H:$H,">=01/03/2025",'Datos Primaria'!$H:$H,"<=31/03/2025") -> 0 | D69: =SUM(C69) -> 0 | K69: Marzo | L69: =SUM(C$67:C69) -> 1 | M69: =SUM(L69) -> 1 | T69: Marzo | U69: =SUM(C$43:C69) -> 17 | V69: =SUM(U69) -> 17
B70: Abril | C70: =COUNTIFS('Datos Primaria'!$E:$E,C$42,'Datos Primaria'!$H:$H,">=01/04/2025",'Datos Primaria'!$H:$H,"<=30/04/2025") -> 1 | D70: =SUM(C70) -> 1 | K70: Abril | L70: =SUM(C$67:C70) -> 2 | M70: =SUM(L70) -> 2 | T70: Abril | U70: =SUM(C$43:C70) -> 18 | V70: =SUM(U70) -> 18
B71: Mayo | C71: =COUNTIFS('Datos Primaria'!$E:$E,C$42,'Datos Primaria'!$H:$H,">=01/05/2025",'Datos Primaria'!$H:$H,"<=31/05/2025") -> 0 | D71: =SUM(C71) -> 0 | K71: Mayo | L71: =SUM(C$67:C71) -> 2 | M71: =SUM(L71) -> 2 | T71: Mayo | U71: =SUM(C$43:C71) -> 18 | V71: =SUM(U71) -> 18
B72: Junio | C72: =COUNTIFS('Datos Primaria'!$E:$E,C$42,'Datos Primaria'!$H:$H,">=01/06/2025",'Datos Primaria'!$H:$H,"<=30/06/2025") -> 0 | D72: =SUM(C72) -> 0 | K72: Junio | L72: =SUM(C$67:C72) -> 2 | M72: =SUM(L72) -> 2 | T72: Junio | U72: =SUM(C$43:C72) -> 18 | V72: =SUM(U72) -> 18
B73: Julio | C73: =COUNTIFS('Datos Primaria'!$E:$E,C$42,'Datos Primaria'!$H:$H,">=01/07/2025",'Datos Primaria'!$H:$H,"<=31/07/2025") -> 0 | D73: =SUM(C73) -> 0 | K73: Julio | L73: =SUM(C$67:C73) -> 2 | M73: =SUM(L73) -> 2 | T73: Julio | U73: =SUM(C$43:C73) -> 18 | V73: =SUM(U73) -> 18
B74: Agosto | C74: =COUNTIFS('Datos Primaria'!$E:$E,C$42,'Datos Primaria'!$H:$H,">=01/08/2025",'Datos Primaria'!$H:$H,"<=31/08/2025") -> 2 | D74: =SUM(C74) -> 2 | K74: Agosto | L74: =SUM(C$67:C74) -> 4 | M74: =SUM(L74) -> 4 | T74: Agosto | U74: =SUM(C$43:C74) -> 20 | V74: =SUM(U74) -> 20
B75: Septiembre | C75: =COUNTIFS('Datos Primaria'!$E:$E,C$42,'Datos Primaria'!$H:$H,">=01/09/2025",'Datos Primaria'!$H:$H,"<=30/09/2025") -> 3 | D75: =SUM(C75) -> 3 | K75: Septiembre | L75: =SUM(C$67:C75) -> 7 | M75: =SUM(L75) -> 7 | T75: Septiembre | U75: =SUM(C$43:C75) -> 23 | V75: =SUM(U75) -> 23
B76: Octubre | C76: =COUNTIFS('Datos Primaria'!$E:$E,C$42,'Datos Primaria'!$H:$H,">=01/10/2025",'Datos Primaria'!$H:$H,"<=31/10/2025") -> 0 | D76: =SUM(C76) -> 0 | K76: Octubre | L76: =SUM(C$67:C76) -> 7 | M76: =SUM(L76) -> 7 | T76: Octubre | U76: =SUM(C$43:C76) -> 23 | V76: =SUM(U76) -> 23
B77: Noviembre | C77: =COUNTIFS('Datos Primaria'!$E:$E,C$42,'Datos Primaria'!$H:$H,">=01/11/2025",'Datos Primaria'!$H:$H,"<=30/11/2025") -> 1 | D77: =SUM(C77) -> 1 | K77: Noviembre | L77: =SUM(C$67:C77) -> 8 | M77: =SUM(L77) -> 8 | T77: Noviembre | U77: =SUM(C$43:C77) -> 24 | V77: =SUM(U77) -> 24
B78: Diciembre | C78: =COUNTIFS('Datos Primaria'!$E:$E,C$42,'Datos Primaria'!$H:$H,">=01/12/2025",'Datos Primaria'!$H:$H,"<=31/12/2025") -> 0 | D78: =SUM(C78) -> 0 | K78: Diciembre | L78: =SUM(C$67:C78) -> 8 | M78: =SUM(L78) -> 8 | T78: Diciembre | U78: =SUM(C$43:C78) -> 24 | V78: =SUM(U78) -> 24
B81: Inicio observación por mes | K81: Inicia observación acumulado por año | T81: Inicia observación acumulado todos los años
B82: MES | C82: 1° | D82: 2° | E82: 3° | F82: 4° | G82: 5° | H82: TOTAL | K82: MES | L82: 1° | M82: 2° | N82: 3° | O82: 4° | P82: 5° | Q82: TOTAL | T82: MES | U82: 1° | V82: 2° | W82: 3° | X82: 4° | Y82: 5° | Z82: TOTAL
A83: =A3 -> 2023 | B83: Enero | C83: =COUNTIFS('Datos Primaria'!$E:$E,C$82,'Datos Primaria'!$I:$I,">=01/01/2023",'Datos Primaria'!$I:$I,"<=31/01/2023") -> 0 | D83: =COUNTIFS('Datos Primaria'!$E:$E,D$82,'Datos Primaria'!$I:$I,">=01/01/2023",'Datos Primaria'!$I:$I,"<=31/01/2023") -> 0 | E83: =COUNTIFS('Datos Primaria'!$E:$E,E$82,'Datos Primaria'!$I:$I,">=01/01/2023",'Datos Primaria'!$I:$I,"<=31/01/2023") -> 0 | F83: =COUNTIFS('Datos Primaria'!$E:$E,F$82,'Datos Primaria'!$I:$I,">=01/01/2023",'Datos Primaria'!$I:$I,"<=31/01/2023") -> 0 | G83: =COUNTIFS('Datos Primaria'!$E:$E,G$82,'Datos Primaria'!$I:$I,">=01/01/2023",'Datos Primaria'!$I:$I,"<=31/01/2023") -> 0 | H83: =SUM(C83:G83) -> 0 | J83: =A83 -> 2023 | K83: Enero | L83: =SUM(C$83:C83) -> 0 | M83: =SUM(D$83:D83) -> 0 | N83: =SUM(E$83:E83) -> 0 | O83: =SUM(F$83:F83) -> 0 | P83: =SUM(G$83:G83) -> 0 | Q83: =SUM(L83:P83) -> 0 | S83: =A83 -> 2023 | T83: Enero | U83: =SUM(C$83:C83) -> 0 | V83: =SUM(D$83:D83) -> 0 | W83: =SUM(E$83:E83) -> 0 | X83: =SUM(F$83:F83) -> 0 | Y83: =SUM(G$83:G83) -> 0 | Z83: =SUM(U83:Y83) -> 0
B84: Febrero | C84: =COUNTIFS('Datos Primaria'!$E:$E,C$82,'Datos Primaria'!$I:$I,">=01/02/2023",'Datos Primaria'!$I:$I,"<=28/02/2023") -> 0 | D84: =COUNTIFS('Datos Primaria'!$E:$E,D$82,'Datos Primaria'!$I:$I,">=01/02/2023",'Datos Primaria'!$I:$I,"<=28/02/2023") -> 0 | E84: =COUNTIFS('Datos Primaria'!$E:$E,E$82,'Datos Primaria'!$I:$I,">=01/02/2023",'Datos Primaria'!$I:$I,"<=28/02/2023") -> 0 | F84: =COUNTIFS('Datos Primaria'!$E:$E,F$82,'Datos Primaria'!$I:$I,">=01/02/2023",'Datos Primaria'!$I:$I,"<=28/02/2023") -> 0 | G84: =COUNTIFS('Datos Primaria'!$E:$E,G$82,'Datos Primaria'!$I:$I,">=01/02/2023",'Datos Primaria'!$I:$I,"<=28/02/2023") -> 0 | H84: =SUM(C84:G84) -> 0 | K84: Febrero | L84: =SUM(C$83:C84) -> 0 | M84: =SUM(D$83:D84) -> 0 | N84: =SUM(E$83:E84) -> 0 | O84: =SUM(F$83:F84) -> 0 | P84: =SUM(G$83:G84) -> 0 | Q84: =SUM(L84:P84) -> 0 | T84: Febrero | U84: =SUM(C$83:C84) -> 0 | V84: =SUM(D$83:D84) -> 0 | W84: =SUM(E$83:E84) -> 0 | X84: =SUM(F$83:F84) -> 0 | Y84: =SUM(G$83:G84) -> 0 | Z84: =SUM(U84:Y84) -> 0
B85: Marzo | C85: =COUNTIFS('Datos Primaria'!$E:$E,C$82,'Datos Primaria'!$I:$I,">=01/03/2023",'Datos Primaria'!$I:$I,"<=31/03/2023") -> 0 | D85: =COUNTIFS('Datos Primaria'!$E:$E,D$82,'Datos Primaria'!$I:$I,">=01/03/2023",'Datos Primaria'!$I:$I,"<=31/03/2023") -> 0 | E85: =COUNTIFS('Datos Primaria'!$E:$E,E$82,'Datos Primaria'!$I:$I,">=01/03/2023",'Datos Primaria'!$I:$I,"<=31/03/2023") -> 0 | F85: =COUNTIFS('Datos Primaria'!$E:$E,F$82,'Datos Primaria'!$I:$I,">=01/03/2023",'Datos Primaria'!$I:$I,"<=31/03/2023") -> 0 | G85: =COUNTIFS('Datos Primaria'!$E:$E,G$82,'Datos Primaria'!$I:$I,">=01/03/2023",'Datos Primaria'!$I:$I,"<=31/03/2023") -> 1 | H85: =SUM(C85:G85) -> 1 | K85: Marzo | L85: =SUM(C$83:C85) -> 0 | M85: =SUM(D$83:D85) -> 0 | N85: =SUM(E$83:E85) -> 0 | O85: =SUM(F$83:F85) -> 0 | P85: =SUM(G$83:G85) -> 1 | Q85: =SUM(L85:P85) -> 1 | T85: Marzo | U85: =SUM(C$83:C85) -> 0 | V85: =SUM(D$83:D85) -> 0 | W85: =SUM(E$83:E85) -> 0 | X85: =SUM(F$83:F85) -> 0 | Y85: =SUM(G$83:G85) -> 1 | Z85: =SUM(U85:Y85) -> 1
B86: Abril | C86: =COUNTIFS('Datos Primaria'!$E:$E,C$82,'Datos Primaria'!$I:$I,">=01/04/2023",'Datos Primaria'!$I:$I,"<=30/04/2023") -> 1 | D86: =COUNTIFS('Datos Primaria'!$E:$E,D$82,'Datos Primaria'!$I:$I,">=01/04/2023",'Datos Primaria'!$I:$I,"<=30/04/2023") -> 0 | E86: =COUNTIFS('Datos Primaria'!$E:$E,E$82,'Datos Primaria'!$I:$I,">=01/04/2023",'Datos Primaria'!$I:$I,"<=30/04/2023") -> 0 | F86: =COUNTIFS('Datos Primaria'!$E:$E,F$82,'Datos Primaria'!$I:$I,">=01/04/2023",'Datos Primaria'!$I:$I,"<=30/04/2023") -> 0 | G86: =COUNTIFS('Datos Primaria'!$E:$E,G$82,'Datos Primaria'!$I:$I,">=01/04/2023",'Datos Primaria'!$I:$I,"<=30/04/2023") -> 0 | H86: =SUM(C86:G86) -> 1 | K86: Abril | L86: =SUM(C$83:C86) -> 1 | M86: =SUM(D$83:D86) -> 0 | N86: =SUM(E$83:E86) -> 0 | O86: =SUM(F$83:F86) -> 0 | P86: =SUM(G$83:G86) -> 1 | Q86: =SUM(L86:P86) -> 2 | T86: Abril | U86: =SUM(C$83:C86) -> 1 | V86: =SUM(D$83:D86) -> 0 | W86: =SUM(E$83:E86) -> 0 | X86: =SUM(F$83:F86) -> 0 | Y86: =SUM(G$83:G86) -> 1 | Z86: =SUM(U86:Y86) -> 2
B87: Mayo | C87: =COUNTIFS('Datos Primaria'!$E:$E,C$82,'Datos Primaria'!$I:$I,">=01/05/2023",'Datos Primaria'!$I:$I,"<=31/05/2023") -> 0 | D87: =COUNTIFS('Datos Primaria'!$E:$E,D$82,'Datos Primaria'!$I:$I,">=01/05/2023",'Datos Primaria'!$I:$I,"<=31/05/2023") -> 2 | E87: =COUNTIFS('Datos Primaria'!$E:$E,E$82,'Datos Primaria'!$I:$I,">=01/05/2023",'Datos Primaria'!$I:$I,"<=31/05/2023") -> 0 | F87: =COUNTIFS('Datos Primaria'!$E:$E,F$82,'Datos Primaria'!$I:$I,">=01/05/2023",'Datos Primaria'!$I:$I,"<=31/05/2023") -> 0 | G87: =COUNTIFS('Datos Primaria'!$E:$E,G$82,'Datos Primaria'!$I:$I,">=01/05/2023",'Datos Primaria'!$I:$I,"<=31/05/2023") -> 0 | H87: =SUM(C87:G87) -> 2 | K87: Mayo | L87: =SUM(C$83:C87) -> 1 | M87: =SUM(D$83:D87) -> 2 | N87: =SUM(E$83:E87) -> 0 | O87: =SUM(F$83:F87) -> 0 | P87: =SUM(G$83:G87) -> 1 | Q87: =SUM(L87:P87) -> 4 | T87: Mayo | U87: =SUM(C$83:C87) -> 1 | V87: =SUM(D$83:D87) -> 2 | W87: =SUM(E$83:E87) -> 0 | X87: =SUM(F$83:F87) -> 0 | Y87: =SUM(G$83:G87) -> 1 | Z87: =SUM(U87:Y87) -> 4
B88: Junio | C88: =COUNTIFS('Datos Primaria'!$E:$E,C$82,'Datos Primaria'!$I:$I,">=01/06/2023",'Datos Primaria'!$I:$I,"<=30/06/2023") -> 0 | D88: =COUNTIFS('Datos Primaria'!$E:$E,D$82,'Datos Primaria'!$I:$I,">=01/06/2023",'Datos Primaria'!$I:$I,"<=30/06/2023") -> 0 | E88: =COUNTIFS('Datos Primaria'!$E:$E,E$82,'Datos Primaria'!$I:$I,">=01/06/2023",'Datos Primaria'!$I:$I,"<=30/06/2023") -> 1 | F88: =COUNTIFS('Datos Primaria'!$E:$E,F$82,'Datos Primaria'!$I:$I,">=01/06/2023",'Datos Primaria'!$I:$I,"<=30/06/2023") -> 0 | G88: =COUNTIFS('Datos Primaria'!$E:$E,G$82,'Datos Primaria'!$I:$I,">=01/06/2023",'Datos Primaria'!$I:$I,"<=30/06/2023") -> 1 | H88: =SUM(C88:G88) -> 2 | K88: Junio | L88: =SUM(C$83:C88) -> 1 | M88: =SUM(D$83:D88) -> 2 | N88: =SUM(E$83:E88) -> 1 | O88: =SUM(F$83:F88) -> 0 | P88: =SUM(G$83:G88) -> 2 | Q88: =SUM(L88:P88) -> 6 | T88: Junio | U88: =SUM(C$83:C88) -> 1 | V88: =SUM(D$83:D88) -> 2 | W88: =SUM(E$83:E88) -> 1 | X88: =SUM(F$83:F88) -> 0 | Y88: =SUM(G$83:G88) -> 2 | Z88: =SUM(U88:Y88) -> 6
B89: Julio | C89: =COUNTIFS('Datos Primaria'!$E:$E,C$82,'Datos Primaria'!$I:$I,">=01/07/2023",'Datos Primaria'!$I:$I,"<=31/07/2023") -> 2 | D89: =COUNTIFS('Datos Primaria'!$E:$E,D$82,'Datos Primaria'!$I:$I,">=01/07/2023",'Datos Primaria'!$I:$I,"<=31/07/2023") -> 1 | E89: =COUNTIFS('Datos Primaria'!$E:$E,E$82,'Datos Primaria'!$I:$I,">=01/07/2023",'Datos Primaria'!$I:$I,"<=31/07/2023") -> 1 | F89: =COUNTIFS('Datos Primaria'!$E:$E,F$82,'Datos Primaria'!$I:$I,">=01/07/2023",'Datos Primaria'!$I:$I,"<=31/07/2023") -> 1 | G89: =COUNTIFS('Datos Primaria'!$E:$E,G$82,'Datos Primaria'!$I:$I,">=01/07/2023",'Datos Primaria'!$I:$I,"<=31/07/2023") -> 1 | H89: =SUM(C89:G89) -> 6 | K89: Julio | L89: =SUM(C$83:C89) -> 3 | M89: =SUM(D$83:D89) -> 3 | N89: =SUM(E$83:E89) -> 2 | O89: =SUM(F$83:F89) -> 1 | P89: =SUM(G$83:G89) -> 3 | Q89: =SUM(L89:P89) -> 12 | T89: Julio | U89: =SUM(C$83:C89) -> 3 | V89: =SUM(D$83:D89) -> 3 | W89: =SUM(E$83:E89) -> 2 | X89: =SUM(F$83:F89) -> 1 | Y89: =SUM(G$83:G89) -> 3 | Z89: =SUM(U89:Y89) -> 12
B90: Agosto | C90: =COUNTIFS('Datos Primaria'!$E:$E,C$82,'Datos Primaria'!$I:$I,">=01/08/2023",'Datos Primaria'!$I:$I,"<=31/08/2023") -> 1 | D90: =COUNTIFS('Datos Primaria'!$E:$E,D$82,'Datos Primaria'!$I:$I,">=01/08/2023",'Datos Primaria'!$I:$I,"<=31/08/2023") -> 0 | E90: =COUNTIFS('Datos Primaria'!$E:$E,E$82,'Datos Primaria'!$I:$I,">=01/08/2023",'Datos Primaria'!$I:$I,"<=31/08/2023") -> 0 | F90: =COUNTIFS('Datos Primaria'!$E:$E,F$82,'Datos Primaria'!$I:$I,">=01/08/2023",'Datos Primaria'!$I:$I,"<=31/08/2023") -> 0 | G90: =COUNTIFS('Datos Primaria'!$E:$E,G$82,'Datos Primaria'!$I:$I,">=01/08/2023",'Datos Primaria'!$I:$I,"<=31/08/2023") -> 0 | H90: =SUM(C90:G90) -> 1 | K90: Agosto | L90: =SUM(C$83:C90) -> 4 | M90: =SUM(D$83:D90) -> 3 | N90: =SUM(E$83:E90) -> 2 | O90: =SUM(F$83:F90) -> 1 | P90: =SUM(G$83:G90) -> 3 | Q90: =SUM(L90:P90) -> 13 | T90: Agosto | U90: =SUM(C$83:C90) -> 4 | V90: =SUM(D$83:D90) -> 3 | W90: =SUM(E$83:E90) -> 2 | X90: =SUM(F$83:F90) -> 1 | Y90: =SUM(G$83:G90) -> 3 | Z90: =SUM(U90:Y90) -> 13
B91: Septiembre | C91: =COUNTIFS('Datos Primaria'!$E:$E,C$82,'Datos Primaria'!$I:$I,">=01/09/2023",'Datos Primaria'!$I:$I,"<=30/09/2023") -> 0 | D91: =COUNTIFS('Datos Primaria'!$E:$E,D$82,'Datos Primaria'!$I:$I,">=01/09/2023",'Datos Primaria'!$I:$I,"<=30/09/2023") -> 0 | E91: =COUNTIFS('Datos Primaria'!$E:$E,E$82,'Datos Primaria'!$I:$I,">=01/09/2023",'Datos Primaria'!$I:$I,"<=30/09/2023") -> 1 | F91: =COUNTIFS('Datos Primaria'!$E:$E,F$82,'Datos Primaria'!$I:$I,">=01/09/2023",'Datos Primaria'!$I:$I,"<=30/09/2023") -> 2 | G91: =COUNTIFS('Datos Primaria'!$E:$E,G$82,'Datos Primaria'!$I:$I,">=01/09/2023",'Datos Primaria'!$I:$I,"<=30/09/2023") -> 1 | H91: =SUM(C91:G91) -> 4 | K91: Septiembre | L91: =SUM(C$83:C91) -> 4 | M91: =SUM(D$83:D91) -> 3 | N91: =SUM(E$83:E91) -> 3 | O91: =SUM(F$83:F91) -> 3 | P91: =SUM(G$83:G91) -> 4 | Q91: =SUM(L91:P91) -> 17 | T91: Septiembre | U91: =SUM(C$83:C91) -> 4 | V91: =SUM(D$83:D91) -> 3 | W91: =SUM(E$83:E91) -> 3 | X91: =SUM(F$83:F91) -> 3 | Y91: =SUM(G$83:G91) -> 4 | Z91: =SUM(U91:Y91) -> 17
B92: Octubre | C92: =COUNTIFS('Datos Primaria'!$E:$E,C$82,'Datos Primaria'!$I:$I,">=01/10/2023",'Datos Primaria'!$I:$I,"<=31/10/2023") -> 1 | D92: =COUNTIFS('Datos Primaria'!$E:$E,D$82,'Datos Primaria'!$I:$I,">=01/10/2023",'Datos Primaria'!$I:$I,"<=31/10/2023") -> 0 | E92: =COUNTIFS('Datos Primaria'!$E:$E,E$82,'Datos Primaria'!$I:$I,">=01/10/2023",'Datos Primaria'!$I:$I,"<=31/10/2023") -> 0 | F92: =COUNTIFS('Datos Primaria'!$E:$E,F$82,'Datos Primaria'!$I:$I,">=01/10/2023",'Datos Primaria'!$I:$I,"<=31/10/2023") -> 0 | G92: =COUNTIFS('Datos Primaria'!$E:$E,G$82,'Datos Primaria'!$I:$I,">=01/10/2023",'Datos Primaria'!$I:$I,"<=31/10/2023") -> 0 | H92: =SUM(C92:G92) -> 1 | K92: Octubre | L92: =SUM(C$83:C92) -> 5 | M92: =SUM(D$83:D92) -> 3 | N92: =SUM(E$83:E92) -> 3 | O92: =SUM(F$83:F92) -> 3 | P92: =SUM(G$83:G92) -> 4 | Q92: =SUM(L92:P92) -> 18 | T92: Octubre | U92: =SUM(C$83:C92) -> 5 | V92: =SUM(D$83:D92) -> 3 | W92: =SUM(E$83:E92) -> 3 | X92: =SUM(F$83:F92) -> 3 | Y92: =SUM(G$83:G92) -> 4 | Z92: =SUM(U92:Y92) -> 18
B93: Noviembre | C93: =COUNTIFS('Datos Primaria'!$E:$E,C$82,'Datos Primaria'!$I:$I,">=01/11/2023",'Datos Primaria'!$I:$I,"<=30/11/2023") -> 0 | D93: =COUNTIFS('Datos Primaria'!$E:$E,D$82,'Datos Primaria'!$I:$I,">=01/11/2023",'Datos Primaria'!$I:$I,"<=30/11/2023") -> 2 | E93: =COUNTIFS('Datos Primaria'!$E:$E,E$82,'Datos Primaria'!$I:$I,">=01/11/2023",'Datos Primaria'!$I:$I,"<=30/11/2023") -> 1 | F93: =COUNTIFS('Datos Primaria'!$E:$E,F$82,'Datos Primaria'!$I:$I,">=01/11/2023",'Datos Primaria'!$I:$I,"<=30/11/2023") -> 1 | G93: =COUNTIFS('Datos Primaria'!$E:$E,G$82,'Datos Primaria'!$I:$I,">=01/11/2023",'Datos Primaria'!$I:$I,"<=30/11/2023") -> 3 | H93: =SUM(C93:G93) -> 7 | K93: Noviembre | L93: =SUM(C$83:C93) -> 5 | M93: =SUM(D$83:D93) -> 5 | N93: =SUM(E$83:E93) -> 4 | O93: =SUM(F$83:F93) -> 4 | P93: =SUM(G$83:G93) -> 7 | Q93: =SUM(L93:P93) -> 25 | T93: Noviembre | U93: =SUM(C$83:C93) -> 5 | V93: =SUM(D$83:D93) -> 5 | W93: =SUM(E$83:E93) -> 4 | X93: =SUM(F$83:F93) -> 4 | Y93: =SUM(G$83:G93) -> 7 | Z93: =SUM(U93:Y93) -> 25
B94: Diciembre | C94: =COUNTIFS('Datos Primaria'!$E:$E,C$82,'Datos Primaria'!$I:$I,">=01/12/2023",'Datos Primaria'!$I:$I,"<=31/12/2023") -> 0 | D94: =COUNTIFS('Datos Primaria'!$E:$E,D$82,'Datos Primaria'!$I:$I,">=01/12/2023",'Datos Primaria'!$I:$I,"<=31/12/2023") -> 0 | E94: =COUNTIFS('Datos Primaria'!$E:$E,E$82,'Datos Primaria'!$I:$I,">=01/12/2023",'Datos Primaria'!$I:$I,"<=31/12/2023") -> 0 | F94: =COUNTIFS('Datos Primaria'!$E:$E,F$82,'Datos Primaria'!$I:$I,">=01/12/2023",'Datos Primaria'!$I:$I,"<=31/12/2023") -> 0 | G94: =COUNTIFS('Datos Primaria'!$E:$E,G$82,'Datos Primaria'!$I:$I,">=01/12/2023",'Datos Primaria'!$I:$I,"<=31/12/2023") -> 0 | H94: =SUM(C94:G94) -> 0 | K94: Diciembre | L94: =SUM(C$83:C94) -> 5 | M94: =SUM(D$83:D94) -> 5 | N94: =SUM(E$83:E94) -> 4 | O94: =SUM(F$83:F94) -> 4 | P94: =SUM(G$83:G94) -> 7 | Q94: =SUM(L94:P94) -> 25 | T94: Diciembre | U94: =SUM(C$83:C94) -> 5 | V94: =SUM(D$83:D94) -> 5 | W94: =SUM(E$83:E94) -> 4 | X94: =SUM(F$83:F94) -> 4 | Y94: =SUM(G$83:G94) -> 7 | Z94: =SUM(U94:Y94) -> 25
A95: =A15 -> 2024 | B95: Enero | C95: =COUNTIFS('Datos Primaria'!$E:$E,C$82,'Datos Primaria'!$I:$I,">=01/01/2024",'Datos Primaria'!$I:$I,"<=31/01/2024") -> 1 | D95: =COUNTIFS('Datos Primaria'!$E:$E,D$82,'Datos Primaria'!$I:$I,">=01/01/2024",'Datos Primaria'!$I:$I,"<=31/01/2024") -> 1 | E95: =COUNTIFS('Datos Primaria'!$E:$E,E$82,'Datos Primaria'!$I:$I,">=01/01/2024",'Datos Primaria'!$I:$I,"<=31/01/2024") -> 0 | F95: =COUNTIFS('Datos Primaria'!$E:$E,F$82,'Datos Primaria'!$I:$I,">=01/01/2024",'Datos Primaria'!$I:$I,"<=31/01/2024") -> 1 | G95: =COUNTIFS('Datos Primaria'!$E:$E,G$82,'Datos Primaria'!$I:$I,">=01/01/2024",'Datos Primaria'!$I:$I,"<=31/01/2024") -> 0 | H95: =SUM(C95:G95) -> 3 | J95: =A95 -> 2024 | K95: Enero | L95: =SUM(C$95:C95) -> 1 | M95: =SUM(D$95:D95) -> 1 | N95: =SUM(E$95:E95) -> 0 | O95: =SUM(F$95:F95) -> 1 | P95: =SUM(G$95:G95) -> 0 | Q95: =SUM(L95:P95) -> 3 | S95: =A95 -> 2024 | T95: Enero | U95: =SUM(C$83:C95) -> 6 | V95: =SUM(D$83:D95) -> 6 | W95: =SUM(E$83:E95) -> 4 | X95: =SUM(F$83:F95) -> 5 | Y95: =SUM(G$83:G95) -> 7 | Z95: =SUM(U95:Y95) -> 28
B96: Febrero | C96: =COUNTIFS('Datos Primaria'!$E:$E,C$82,'Datos Primaria'!$I:$I,">=01/02/2024",'Datos Primaria'!$I:$I,"<=29/02/2024") -> 1 | D96: =COUNTIFS('Datos Primaria'!$E:$E,D$82,'Datos Primaria'!$I:$I,">=01/02/2024",'Datos Primaria'!$I:$I,"<=29/02/2024") -> 0 | E96: =COUNTIFS('Datos Primaria'!$E:$E,E$82,'Datos Primaria'!$I:$I,">=01/02/2024",'Datos Primaria'!$I:$I,"<=29/02/2024") -> 0 | F96: =COUNTIFS('Datos Primaria'!$E:$E,F$82,'Datos Primaria'!$I:$I,">=01/02/2024",'Datos Primaria'!$I:$I,"<=29/02/2024") -> 0 | G96: =COUNTIFS('Datos Primaria'!$E:$E,G$82,'Datos Primaria'!$I:$I,">=01/02/2024",'Datos Primaria'!$I:$I,"<=29/02/2024") -> 0 | H96: =SUM(C96:G96) -> 1 | K96: Febrero | L96: =SUM(C$95:C96) -> 2 | M96: =SUM(D$95:D96) -> 1 | N96: =SUM(E$95:E96) -> 0 | O96: =SUM(F$95:F96) -> 1 | P96: =SUM(G$95:G96) -> 0 | Q96: =SUM(L96:P96) -> 4 | T96: Febrero | U96: =SUM(C$83:C96) -> 7 | V96: =SUM(D$83:D96) -> 6 | W96: =SUM(E$83:E96) -> 4 | X96: =SUM(F$83:F96) -> 5 | Y96: =SUM(G$83:G96) -> 7 | Z96: =SUM(U96:Y96) -> 29
B97: Marzo | C97: =COUNTIFS('Datos Primaria'!$E:$E,C$82,'Datos Primaria'!$I:$I,">=01/03/2024",'Datos Primaria'!$I:$I,"<=31/03/2024") -> 0 | D97: =COUNTIFS('Datos Primaria'!$E:$E,D$82,'Datos Primaria'!$I:$I,">=01/03/2024",'Datos Primaria'!$I:$I,"<=31/03/2024") -> 0 | E97: =COUNTIFS('Datos Primaria'!$E:$E,E$82,'Datos Primaria'!$I:$I,">=01/03/2024",'Datos Primaria'!$I:$I,"<=31/03/2024") -> 0 | F97: =COUNTIFS('Datos Primaria'!$E:$E,F$82,'Datos Primaria'!$I:$I,">=01/03/2024",'Datos Primaria'!$I:$I,"<=31/03/2024") -> 0 | G97: =COUNTIFS('Datos Primaria'!$E:$E,G$82,'Datos Primaria'!$I:$I,">=01/03/2024",'Datos Primaria'!$I:$I,"<=31/03/2024") -> 0 | H97: =SUM(C97:G97) -> 0 | K97: Marzo | L97: =SUM(C$95:C97) -> 2 | M97: =SUM(D$95:D97) -> 1 | N97: =SUM(E$95:E97) -> 0 | O97: =SUM(F$95:F97) -> 1 | P97: =SUM(G$95:G97) -> 0 | Q97: =SUM(L97:P97) -> 4 | T97: Marzo | U97: =SUM(C$83:C97) -> 7 | V97: =SUM(D$83:D97) -> 6 | W97: =SUM(E$83:E97) -> 4 | X97: =SUM(F$83:F97) -> 5 | Y97: =SUM(G$83:G97) -> 7 | Z97: =SUM(U97:Y97) -> 29
B98: Abril | C98: =COUNTIFS('Datos Primaria'!$E:$E,C$82,'Datos Primaria'!$I:$I,">=01/04/2024",'Datos Primaria'!$I:$I,"<=30/04/2024") -> 0 | D98: =COUNTIFS('Datos Primaria'!$E:$E,D$82,'Datos Primaria'!$I:$I,">=01/04/2024",'Datos Primaria'!$I:$I,"<=30/04/2024") -> 0 | E98: =COUNTIFS('Datos Primaria'!$E:$E,E$82,'Datos Primaria'!$I:$I,">=01/04/2024",'Datos Primaria'!$I:$I,"<=30/04/2024") -> 2 | F98: =COUNTIFS('Datos Primaria'!$E:$E,F$82,'Datos Primaria'!$I:$I,">=01/04/2024",'Datos Primaria'!$I:$I,"<=30/04/2024") -> 0 | G98: =COUNTIFS('Datos Primaria'!$E:$E,G$82,'Datos Primaria'!$I:$I,">=01/04/2024",'Datos Primaria'!$I:$I,"<=30/04/2024") -> 1 | H98: =SUM(C98:G98) -> 3 | K98: Abril | L98: =SUM(C$95:C98) -> 2 | M98: =SUM(D$95:D98) -> 1 | N98: =SUM(E$95:E98) -> 2 | O98: =SUM(F$95:F98) -> 1 | P98: =SUM(G$95:G98) -> 1 | Q98: =SUM(L98:P98) -> 7 | T98: Abril | U98: =SUM(C$83:C98) -> 7 | V98: =SUM(D$83:D98) -> 6 | W98: =SUM(E$83:E98) -> 6 | X98: =SUM(F$83:F98) -> 5 | Y98: =SUM(G$83:G98) -> 8 | Z98: =SUM(U98:Y98) -> 32
B99: Mayo | C99: =COUNTIFS('Datos Primaria'!$E:$E,C$82,'Datos Primaria'!$I:$I,">=01/05/2024",'Datos Primaria'!$I:$I,"<=31/05/2024") -> 0 | D99: =COUNTIFS('Datos Primaria'!$E:$E,D$82,'Datos Primaria'!$I:$I,">=01/05/2024",'Datos Primaria'!$I:$I,"<=31/05/2024") -> 1 | E99: =COUNTIFS('Datos Primaria'!$E:$E,E$82,'Datos Primaria'!$I:$I,">=01/05/2024",'Datos Primaria'!$I:$I,"<=31/05/2024") -> 0 | F99: =COUNTIFS('Datos Primaria'!$E:$E,F$82,'Datos Primaria'!$I:$I,">=01/05/2024",'Datos Primaria'!$I:$I,"<=31/05/2024") -> 0 | G99: =COUNTIFS('Datos Primaria'!$E:$E,G$82,'Datos Primaria'!$I:$I,">=01/05/2024",'Datos Primaria'!$I:$I,"<=31/05/2024") -> 0 | H99: =SUM(C99:G99) -> 1 | K99: Mayo | L99: =SUM(C$95:C99) -> 2 | M99: =SUM(D$95:D99) -> 2 | N99: =SUM(E$95:E99) -> 2 | O99: =SUM(F$95:F99) -> 1 | P99: =SUM(G$95:G99) -> 1 | Q99: =SUM(L99:P99) -> 8 | T99: Mayo | U99: =SUM(C$83:C99) -> 7 | V99: =SUM(D$83:D99) -> 7 | W99: =SUM(E$83:E99) -> 6 | X99: =SUM(F$83:F99) -> 5 | Y99: =SUM(G$83:G99) -> 8 | Z99: =SUM(U99:Y99) -> 33
B100: Junio | C100: =COUNTIFS('Datos Primaria'!$E:$E,C$82,'Datos Primaria'!$I:$I,">=01/06/2024",'Datos Primaria'!$I:$I,"<=30/06/2024") -> 0 | D100: =COUNTIFS('Datos Primaria'!$E:$E,D$82,'Datos Primaria'!$I:$I,">=01/06/2024",'Datos Primaria'!$I:$I,"<=30/06/2024") -> 0 | E100: =COUNTIFS('Datos Primaria'!$E:$E,E$82,'Datos Primaria'!$I:$I,">=01/06/2024",'Datos Primaria'!$I:$I,"<=30/06/2024") -> 0 | F100: =COUNTIFS('Datos Primaria'!$E:$E,F$82,'Datos Primaria'!$I:$I,">=01/06/2024",'Datos Primaria'!$I:$I,"<=30/06/2024") -> 0 | G100: =COUNTIFS('Datos Primaria'!$E:$E,G$82,'Datos Primaria'!$I:$I,">=01/06/2024",'Datos Primaria'!$I:$I,"<=30/06/2024") -> 0 | H100: =SUM(C100:G100) -> 0 | K100: Junio | L100: =SUM(C$95:C100) -> 2 | M100: =SUM(D$95:D100) -> 2 | N100: =SUM(E$95:E100) -> 2 | O100: =SUM(F$95:F100) -> 1 | P100: =SUM(G$95:G100) -> 1 | Q100: =SUM(L100:P100) -> 8 | T100: Junio | U100: =SUM(C$83:C100) -> 7 | V100: =SUM(D$83:D100) -> 7 | W100: =SUM(E$83:E100) -> 6 | X100: =SUM(F$83:F100) -> 5 | Y100: =SUM(G$83:G100) -> 8 | Z100: =SUM(U100:Y100) -> 33
B101: Julio | C101: =COUNTIFS('Datos Primaria'!$E:$E,C$82,'Datos Primaria'!$I:$I,">=01/07/2024",'Datos Primaria'!$I:$I,"<=31/07/2024") -> 1 | D101: =COUNTIFS('Datos Primaria'!$E:$E,D$82,'Datos Primaria'!$I:$I,">=01/07/2024",'Datos Primaria'!$I:$I,"<=31/07/2024") -> 3 | E101: =COUNTIFS('Datos Primaria'!$E:$E,E$82,'Datos Primaria'!$I:$I,">=01/07/2024",'Datos Primaria'!$I:$I,"<=31/07/2024") -> 1 | F101: =COUNTIFS('Datos Primaria'!$E:$E,F$82,'Datos Primaria'!$I:$I,">=01/07/2024",'Datos Primaria'!$I:$I,"<=31/07/2024") -> 2 | G101: =COUNTIFS('Datos Primaria'!$E:$E,G$82,'Datos Primaria'!$I:$I,">=01/07/2024",'Datos Primaria'!$I:$I,"<=31/07/2024") -> 1 | H101: =SUM(C101:G101) -> 8 | K101: Julio | L101: =SUM(C$95:C101) -> 3 | M101: =SUM(D$95:D101) -> 5 | N101: =SUM(E$95:E101) -> 3 | O101: =SUM(F$95:F101) -> 3 | P101: =SUM(G$95:G101) -> 2 | Q101: =SUM(L101:P101) -> 16 | T101: Julio | U101: =SUM(C$83:C101) -> 8 | V101: =SUM(D$83:D101) -> 10 | W101: =SUM(E$83:E101) -> 7 | X101: =SUM(F$83:F101) -> 7 | Y101: =SUM(G$83:G101) -> 9 | Z101: =SUM(U101:Y101) -> 41
